Workbook

Sheet __FDSCACHE__
B1: This sheet contains FactSet XML data for use with this workbook's =FDS codes. Modifying the worksheet's contents may damage the workbook's =FDS functionality.

Sheet 1 — Universe Reconciliation
A1: STEP 4 — Universe Reconciliation | FactSet vs External Research
A2: Compare FactSet universe (from Component A) against names surfaced by AlphaSense, Grok/X and Deep Research. Claude makes ADD / EXCLUDE / CONFIRM recommendations. Analyst approves before Tab 5 scoring.
A4: TICKER | B4: COMPANY NAME | C4: RBICS L5 | D4: FACTSET | E4: ALPHASENSE | F4: GROK/X | G4: DEEP RESEARCH | H4: RECOMMENDATION | I4: RATIONALE / NOTES
A5: Paste FactSet Component A tickers here. Mark each external source with ✓ if name appears. Recommendation: CONFIRM (in FactSet + external) | ADD (external only, passes criteria) | EXCLUDE (FactSet only, Claude recommends remove) | REVIEW (conflicting signals).

Sheet 2 — IC Universe Table
A1: Full RBICS-screened universe — all names passing L5 filter and liquidity floor. Not pre-filtered. Composite Score (col BF) = Claude weighted score. Sort by Score descending before IC presentation.
A2: RANK / ID | C2: IDENTIFICATION | F2: LIQUIDITY | I2: FUNDAMENTAL QUALITY | V2: VALUATION | AB2: MOMENTUM | AH2: SCORING — PERCENTILE RANKS (0–100) | BF2: FINAL SCORE
A3: RANK | B3: TICKER | C3: COMPANY NAME | D3: RBICS L5 NAME | E3: COUNTRY | F3: MKT CAP (USD mm) | G3: ADV 30D (USD mm) | H3: FLOAT (%) | I3: REVENUE ANNUAL | J3: EPS ANNUAL | K3: SALES CAGR NEXT 2Y | L3: EPS CAGR NEXT 2Y | M3: GROSS MARGIN LTM | N3: EBITDA MARGIN LTM | O3: NET PROFIT MARGIN LTM | P3: NET DEBT/EBITDA NTM | Q3: FCF YIELD NTM | R3: DIVIDEND YIELD NTM | S3: ROE NTM | T3: ROIC NTM | U3: RULE OF 40 | V3: P/E NTM | W3: P/S NTM | X3: EV/SALES NTM | Y3: EV/EBITDA NTM | Z3: P/E NTM CHANGE 52W | AA3: EV/EBITDA NTM CHANGE 52W | AB3: PRICE VS 52W HIGH | AC3: TGT PRICE UPSIDE | AD3: PRICE VS 50 DAY MA | AE3: PRICE VS 100 DAY MA | AF3: PRICE VS 200 DAY MA | AG3: ANALYST RATING | AH3: REVENUE SCORE | AI3: EPS SCORE | AJ3: SALES GR SCORE | AK3: EPS GR SCORE | AL3: GROSS MG SCORE | AM3: EBITDA MG SCORE | AN3: NET MG SCORE | AO3: ND/EBITDA SCORE | AP3: FCF YLD SCORE | AQ3: DIV YLD SCORE | AR3: ROE SCORE | AS3: ROIC SCORE | AT3: RULE 40 SCORE | AU3: P/E SCORE | AV3: P/S SCORE | AW3: EV/SALES SCORE | AX3: EV/EBITDA SCORE | AY3: P/E NTM CHANGE 52W2 | AZ3: EV/EBITDA NTM CHANGE 52W3 | BA3: 52W HIGH SCORE | BB3: TGT UPSD SCORE | BC3: VS 50D MA SCORE | BD3: VS 100D MA SCORE | BE3: VS 200D MA SCORE | BF3: CLAUDE SCORE | BG3: CAPE IMC SCORE
A4: =IFERROR(RANK(BG4,BG$4:BG$91),"") -> 1 | B4: HUBS-US | C4: HubSpot, Inc. | D4: {=IFERROR(_xll.FDS($B4,"FR_RBICS_NAME_CURR(""IND"")"), "")} -> Customer Relationship Management Software | E4: {=PROPER(IFERROR(_xll.FDS($B4,"P_DCOUNTRY"), ""))} -> United States | F4: {=IFERROR(_xll.FDS($B4,"FCS_EV_DAILY(MV,NOW,,,USD,M)"), "")} -> 12609.603 | G4: {=IFERROR(_xll.FDS($B4,"AVG(P_VOLUME_FRQ(-1AM,NOW,D,,6))*P_PRICE_AVG(-1AM,NOW,,USD)"), "")} -> 578.23509 | H4: {=IFERROR(_xll.FDS($B4,"OS_SEC_FLT_PCT(0D,,MTD,SEC)")/100, "")} -> 0.962729 | I4: {=IFERROR(_xll.FDS($B4,"FE_ACTUAL(ACTUAL,SALES,ANN_ROLL,0,,,,'CURRENCY=USD')"), "")} -> 3131.266 | J4: {=IFERROR(_xll.FDS($B4,"FE_ACTUAL(ACTUAL,EPS,ANN_ROLL,0,,,,'CURRENCY=USD')"), "")} -> 9.7 | K4: {=IFERROR(_xll.FDS($B4,"POW(FE_ESTIMATE(SALES,MEAN,STMA,,NOW,,,'CURRENCY=USD')/FE_ESTIMATE(SALES,MEAN,LTMA,,NOW,,,'CURRENCY=USD'),0.5)-1"), "")} -> 0.16894538 | L4: {=IFERROR(_xll.FDS($B4,"POW(FE_ESTIMATE(EPS,MEAN,STMA,,NOW,,,'CURRENCY=USD')/FE_ESTIMATE(EPS,MEAN,LTMA,,NOW,,,'CURRENCY=USD'),0.5)-1"), "")} -> 0.2476427 | M4: {=IFERROR(_xll.FDS($B4,"FF_GROSS_MGN(LTM_R,0)"), "")} -> 83.758949 | N4: {=IFERROR(_xll.FDS($B4,"FF_EBITDA_OPER_MGN(LTM_R,0)"), "")} -> 5.6062922 | O4: {=IFERROR(_xll.FDS($B4,"FF_NET_MGN(LTM_R,0)"), "")} -> 1.4663952 | P4: {=IFERROR(_xll.FDS($B4,"FE_VALUATION(NETDEBT_EBITDA,MEAN,NTMA,,NOW,,,'')"), "")} -> -2.2464297 | Q4: {=IFERROR(_xll.FDS($B4,"FE_VALUATION(MCAP_FCF,MEAN,NTMA,,NOW,,,'')"), "")} -> 6.2337174 | R4: {=IFERROR(_xll.FDS($B4,"FE_VALUATION(DIV_YLD,MEAN,NTMA,,NOW,,,'')"), "")} -> 0 | S4: {=IFERROR(_xll.FDS($B4,"FE_VALUATION(ROE,MEAN,NTMA,,0,,,'')" ), "")} -> 25.60649 | T4: {=IFERROR(_xll.FDS($B4,"FE_VALUATION(ROIC,MEAN,NTMA,,0,,,'')" ), "")} -> 23.986855 | U4: {=IFERROR(((_xll.FDS($B4,"FE_ACTUAL(ACTUAL,SALES,ANN_ROLL,0,,,,'CURRENCY=USD')")/_xll.FDS($B4,"FE_ACTUAL(ACTUAL,SALES,ANN_ROLL,-1,,,,'CURRENCY=USD')")-1)*100)+(_xll.FDS($B4,"FE_VALUATION(EBITDA_MARGIN,MEAN,ANN_ROLL,0,NOW,,,'')") ), "")} -> 41.915656 | V4: {=IFERROR(_xll.FDS($B4,"FE_VALUATION(PE,MEAN,NTMA,,0,,,'')" ), "")} -> 18.106287 | W4: {=IFERROR(_xll.FDS($B4,"FE_VALUATION(P_SALESPS,MEAN,NTMA,,0,,,'')" ), "")} -> 3.238714 | X4: {=IFERROR(_xll.FDS($B4,"FE_VALUATION(FFEV_SALES,MEAN,NTMA,,0,,,'')" ), "")} -> 2.8859944 | Y4: {=IFERROR(_xll.FDS($B4,"FE_VALUATION(FFEV_EBITDA,MEAN,NTMA,,0,,,'')" ), "")} -> 11.89469 | Z4: {=IFERROR(_xll.FDS($B4,"PERCENT_CHANGE(FE_VALUATION(PE,MEAN,NTMA,,0,,,''),MAX(FE_VALUATION(PE,MEAN,NTMA,,-1AY,0,,'')))")/100,"")} -> -0.76062538 | AA4: {=IFERROR(_xll.FDS($B4,"PERCENT_CHANGE(FE_VALUATION(FFEV_EBITDA,MEAN,NTMA,,0,,,''),MAX(FE_VALUATION(FFEV_EBITDA,MEAN,NTMA,,-1AY,0,,'')))")/100,"")} -> -0.78299652 | AB4: {=IFERROR(_xll.FDS($B4,"FG_PRICE(0,,,USD)/P_PRICE_HIGH(-1AY,0,USD,,,""PRICE"",""INTRA"")")-1, "")} -> -0.6850543 | AC4: {=IFERROR(_xll.FDS($B4,"RTP_PRICE_TARGET(USD)/FG_PRICE(0,,,USD)")-1, "")} -> 0.51851634 | AD4: {=IFERROR(_xll.FDS($B4,"FG_PRICE(0,,,USD)/FG_PRICE_MAVG(0,,,USD,50)")-1, "")} -> -0.27519839 | AE4: {=IFERROR(_xll.FDS($B4,"FG_PRICE(0,,,USD)/FG_PRICE_MAVG(0,,,USD,100)")-1, "")} -> -0.37289944 | AF4: {=IFERROR(_xll.FDS($B4,"FG_PRICE(0,,,USD)/FG_PRICE_MAVG(0,,,USD,200)")-1, "")} -> -0.48767564 | AG4: {=IFERROR(_xll.FDS($B4,"FE_RATING(MEAN,TEXTONLY,0,NOW,,,'')"), "")} -> Buy | AH4: =IFERROR(IF('3 — Weights'!$E$2=1,PERCENTRANK(I$4:I$91,I4),1-PERCENTRANK(I$4:I$91,I4))*100,"") -> 67.8 | AI4: =IFERROR(IF('3 — Weights'!$E$3=1,PERCENTRANK(J$4:J$91,J4),1-PERCENTRANK(J$4:J$91,J4))*100,"") -> 88.5 | AJ4: =IFERROR(IF('3 — Weights'!$E$4=1,PERCENTRANK(K$4:K$91,K4),1-PERCENTRANK(K$4:K$91,K4))*100,"") -> 68.9 | AK4: =IFERROR(IF('3 — Weights'!$E$5=1,PERCENTRANK(L$4:L$91,L4),1-PERCENTRANK(L$4:L$91,L4))*100,"") -> 75 | AL4: =IFERROR(IF('3 — Weights'!$E$6=1,PERCENTRANK(M$4:M$91,M4),1-PERCENTRANK(M$4:M$91,M4))*100,"") -> 92.6 | AM4: =IFERROR(IF('3 — Weights'!$E$7=1,PERCENTRANK(N$4:N$91,N4),1-PERCENTRANK(N$4:N$91,N4))*100,"") -> 25.9 | AN4: =IFERROR(IF('3 — Weights'!$E$8=1,PERCENTRANK(O$4:O$91,O4),1-PERCENTRANK(O$4:O$91,O4))*100,"") -> 31.3 | AO4: =IFERROR(IF('3 — Weights'!$E$9=1,PERCENTRANK(P$4:P$91,P4),1-PERCENTRANK(P$4:P$91,P4))*100,"") -> 71.1 | AP4: =IFERROR(IF('3 — Weights'!$E$10=1,PERCENTRANK(Q$4:Q$91,Q4),1-PERCENTRANK(Q$4:Q$91,Q4))*100,"") -> 63 | AQ4: =IFERROR(IF('3 — Weights'!$E$11=1,PERCENTRANK(R$4:R$91,R4),1-PERCENTRANK(R$4:R$91,R4))*100,"") -> 0 | AR4: =IFERROR(IF('3 — Weights'!$E$12=1,PERCENTRANK(S$4:S$91,S4),1-PERCENTRANK(S$4:S$91,S4))*100,"") -> 64.1 | AS4: =IFERROR(IF('3 — Weights'!$E$13=1,PERCENTRANK(T$4:T$91,T4),1-PERCENTRANK(T$4:T$91,T4))*100,"") -> 73.6 | AT4: =IFERROR(IF('3 — Weights'!$E$14=1,PERCENTRANK(U$4:U$91,U4),1-PERCENTRANK(U$4:U$91,U4))*100,"") -> 42.6 | AU4: =IFERROR(IF('3 — Weights'!$E$15=1,PERCENTRANK(V$4:V$91,V4),1-PERCENTRANK(V$4:V$91,V4))*100,"") -> 65.6 | AV4: =IFERROR(IF('3 — Weights'!$E$16=1,PERCENTRANK(W$4:W$91,W4),1-PERCENTRANK(W$4:W$91,W4))*100,"") -> 70.2 | AW4: =IFERROR(IF('3 — Weights'!$E$17=1,PERCENTRANK(X$4:X$91,X4),1-PERCENTRANK(X$4:X$91,X4))*100,"") -> 81.7 | AX4: =IFERROR(IF('3 — Weights'!$E$18=1,PERCENTRANK(Y$4:Y$91,Y4),1-PERCENTRANK(Y$4:Y$91,Y4))*100,"") -> 68.7 | AY4: =IFERROR(IF('3 — Weights'!$E$18=1,PERCENTRANK(Z$4:Z$91,Z4),1-PERCENTRANK(Z$4:Z$91,Z4))*100,"") -> 95.5 | AZ4: =IFERROR(IF('3 — Weights'!$E$18=1,PERCENTRANK(AA$4:AA$91,AA4),1-PERCENTRANK(AA$4:AA$91,AA4))*100,"") -> 98.9 | BA4: =IFERROR(IF('3 — Weights'!$E$21=1,PERCENTRANK(AB$4:AB$91,AB4),1-PERCENTRANK(AB$4:AB$91,AB4))*100,"") -> 2.2 | BB4: =IFERROR(IF('3 — Weights'!$E$22=1,PERCENTRANK(AC$4:AC$91,AC4),1-PERCENTRANK(AC$4:AC$91,AC4))*100,"") -> 49.4 | BC4: =IFERROR(IF('3 — Weights'!$E$23=1,PERCENTRANK(AD$4:AD$91,AD4),1-PERCENTRANK(AD$4:AD$91,AD4))*100,"") -> 86.3 | BD4: =IFERROR(IF('3 — Weights'!$E$24=1,PERCENTRANK(AE$4:AE$91,AE4),1-PERCENTRANK(AE$4:AE$91,AE4))*100,"") -> 92 | BE4: =IFERROR(IF('3 — Weights'!$E$25=1,PERCENTRANK(AF$4:AF$91,AF4),1-PERCENTRANK(AF$4:AF$91,AF4))*100,"") -> 95.5 | BF4: {=IFERROR(SUMPRODUCT(TRANSPOSE(AH4:BE4), [1]!Table2[Weight Claude]),"")} -> 67.865 | BG4: {=IFERROR(SUMPRODUCT(TRANSPOSE(AH4:BE4), [1]!Table2[Weight Cape IMC]),"")} -> 67.865
A5: =IFERROR(RANK(BG5,BG$4:BG$91),"") -> 2 | B5: NTNX-US | C5: Nutanix, Inc. | D5: {=IFERROR(_xll.FDS($B5,"FR_RBICS_NAME_CURR(""IND"")"), "")} -> Data Storage Infrastructure Software | E5: {=PROPER(IFERROR(_xll.FDS($B5,"P_DCOUNTRY"), ""))} -> United States | F5: {=IFERROR(_xll.FDS($B5,"FCS_EV_DAILY(MV,NOW,,,USD,M)"), "")} -> 10743.046 | G5: {=IFERROR(_xll.FDS($B5,"AVG(P_VOLUME_FRQ(-1AM,NOW,D,,6))*P_PRICE_AVG(-1AM,NOW,,USD)"), "")} -> 167.96063 | H5: {=IFERROR(_xll.FDS($B5,"OS_SEC_FLT_PCT(0D,,MTD,SEC)")/100, "")} -> 0.975413 | I5: {=IFERROR(_xll.FDS($B5,"FE_ACTUAL(ACTUAL,SALES,ANN_ROLL,0,,,,'CURRENCY=USD')"), "")} -> 2537.927 | J5: {=IFERROR(_xll.FDS($B5,"FE_ACTUAL(ACTUAL,EPS,ANN_ROLL,0,,,,'CURRENCY=USD')"), "")} -> 1.78 | K5: {=IFERROR(_xll.FDS($B5,"POW(FE_ESTIMATE(SALES,MEAN,STMA,,NOW,,,'CURRENCY=USD')/FE_ESTIMATE(SALES,MEAN,LTMA,,NOW,,,'CURRENCY=USD'),0.5)-1"), "")} -> 0.12762747 | L5: {=IFERROR(_xll.FDS($B5,"POW(FE_ESTIMATE(EPS,MEAN,STMA,,NOW,,,'CURRENCY=USD')/FE_ESTIMATE(EPS,MEAN,LTMA,,NOW,,,'CURRENCY=USD'),0.5)-1"), "")} -> 0.14773324 | M5: {=IFERROR(_xll.FDS($B5,"FF_GROSS_MGN(LTM_R,0)"), "")} -> 87.013223 | N5: {=IFERROR(_xll.FDS($B5,"FF_EBITDA_OPER_MGN(LTM_R,0)"), "")} -> 10.771803 | O5: {=IFERROR(_xll.FDS($B5,"FF_NET_MGN(LTM_R,0)"), "")} -> 8.4252928 | P5: {=IFERROR(_xll.FDS($B5,"FE_VALUATION(NETDEBT_EBITDA,MEAN,NTMA,,NOW,,,'')"), "")} -> -2.2384424 | Q5: {=IFERROR(_xll.FDS($B5,"FE_VALUATION(MCAP_FCF,MEAN,NTMA,,NOW,,,'')"), "")} -> 8.521549 | R5: {=IFERROR(_xll.FDS($B5,"FE_VALUATION(DIV_YLD,MEAN,NTMA,,NOW,,,'')"), "")} -> 0 | S5: {=IFERROR(_xll.FDS($B5,"FE_VALUATION(ROE,MEAN,NTMA,,0,,,'')" ), "")} -> 1583.1248 | T5: {=IFERROR(_xll.FDS($B5,"FE_VALUATION(ROIC,MEAN,NTMA,,0,,,'')" ), "")} -> 44.851734 | U5: {=IFERROR(((_xll.FDS($B5,"FE_ACTUAL(ACTUAL,SALES,ANN_ROLL,0,,,,'CURRENCY=USD')")/_xll.FDS($B5,"FE_ACTUAL(ACTUAL,SALES,ANN_ROLL,-1,,,,'CURRENCY=USD')")-1)*100)+(_xll.FDS($B5,"FE_VALUATION(EBITDA_MARGIN,MEAN,ANN_ROLL,0,NOW,,,'')") ), "")} -> 42.097692 | V5: {=IFERROR(_xll.FDS($B5,"FE_VALUATION(PE,MEAN,NTMA,,0,,,'')" ), "")} -> 19.05695 | W5: {=IFERROR(_xll.FDS($B5,"FE_VALUATION(P_SALESPS,MEAN,NTMA,,0,,,'')" ), "")} -> 3.3473253 | X5: {=IFERROR(_xll.FDS($B5,"FE_VALUATION(FFEV_SALES,MEAN,NTMA,,0,,,'')" ), "")} -> 3.4821198 | Y5: {=IFERROR(_xll.FDS($B5,"FE_VALUATION(FFEV_EBITDA,MEAN,NTMA,,0,,,'')" ), "")} -> 13.97298 | Z5: {=IFERROR(_xll.FDS($B5,"PERCENT_CHANGE(FE_VALUATION(PE,MEAN,NTMA,,0,,,''),MAX(FE_VALUATION(PE,MEAN,NTMA,,-1AY,0,,'')))")/100,"")} -> -0.58102081 | AA5: {=IFERROR(_xll.FDS($B5,"PERCENT_CHANGE(FE_VALUATION(FFEV_EBITDA,MEAN,NTMA,,0,,,''),MAX(FE_VALUATION(FFEV_EBITDA,MEAN,NTMA,,-1AY,0,,'')))")/100,"")} -> -0.63910111 | AB5: {=IFERROR(_xll.FDS($B5,"FG_PRICE(0,,,USD)/P_PRICE_HIGH(-1AY,0,USD,,,""PRICE"",""INTRA"")")-1, "")} -> -0.54582534 | AC5: {=IFERROR(_xll.FDS($B5,"RTP_PRICE_TARGET(USD)/FG_PRICE(0,,,USD)")-1, "")} -> 0.60104023 | AD5: {=IFERROR(_xll.FDS($B5,"FG_PRICE(0,,,USD)/FG_PRICE_MAVG(0,,,USD,50)")-1, "")} -> -0.17404773 | AE5: {=IFERROR(_xll.FDS($B5,"FG_PRICE(0,,,USD)/FG_PRICE_MAVG(0,,,USD,100)")-1, "")} -> -0.31066126 | AF5: {=IFERROR(_xll.FDS($B5,"FG_PRICE(0,,,USD)/FG_PRICE_MAVG(0,,,USD,200)")-1, "")} -> -0.41555088 | AG5: {=IFERROR(_xll.FDS($B5,"FE_RATING(MEAN,TEXTONLY,0,NOW,,,'')"), "")} -> Overweight | AH5: =IFERROR(IF('3 — Weights'!$E$2=1,PERCENTRANK(I$4:I$91,I5),1-PERCENTRANK(I$4:I$91,I5))*100,"") -> 60.9 | AI5: =IFERROR(IF('3 — Weights'!$E$3=1,PERCENTRANK(J$4:J$91,J5),1-PERCENTRANK(J$4:J$91,J5))*100,"") -> 42.5 | AJ5: =IFERROR(IF('3 — Weights'!$E$4=1,PERCENTRANK(K$4:K$91,K5),1-PERCENTRANK(K$4:K$91,K5))*100,"") -> 49.4 | AK5: =IFERROR(IF('3 — Weights'!$E$5=1,PERCENTRANK(L$4:L$91,L5),1-PERCENTRANK(L$4:L$91,L5))*100,"") -> 42.8 | AL5: =IFERROR(IF('3 — Weights'!$E$6=1,PERCENTRANK(M$4:M$91,M5),1-PERCENTRANK(M$4:M$91,M5))*100,"") -> 97.5 | AM5: =IFERROR(IF('3 — Weights'!$E$7=1,PERCENTRANK(N$4:N$91,N5),1-PERCENTRANK(N$4:N$91,N5))*100,"") -> 35 | AN5: =IFERROR(IF('3 — Weights'!$E$8=1,PERCENTRANK(O$4:O$91,O5),1-PERCENTRANK(O$4:O$91,O5))*100,"") -> 44.5 | AO5: =IFERROR(IF('3 — Weights'!$E$9=1,PERCENTRANK(P$4:P$91,P5),1-PERCENTRANK(P$4:P$91,P5))*100,"") -> 69.9 | AP5: =IFERROR(IF('3 — Weights'!$E$10=1,PERCENTRANK(Q$4:Q$91,Q5),1-PERCENTRANK(Q$4:Q$91,Q5))*100,"") -> 83.3 | AQ5: =IFERROR(IF('3 — Weights'!$E$11=1,PERCENTRANK(R$4:R$91,R5),1-PERCENTRANK(R$4:R$91,R5))*100,"") -> 0 | AR5: =IFERROR(IF('3 — Weights'!$E$12=1,PERCENTRANK(S$4:S$91,S5),1-PERCENTRANK(S$4:S$91,S5))*100,"") -> 100 | AS5: =IFERROR(IF('3 — Weights'!$E$13=1,PERCENTRANK(T$4:T$91,T5),1-PERCENTRANK(T$4:T$91,T5))*100,"") -> 95.8 | AT5: =IFERROR(IF('3 — Weights'!$E$14=1,PERCENTRANK(U$4:U$91,U5),1-PERCENTRANK(U$4:U$91,U5))*100,"") -> 43.9 | AU5: =IFERROR(IF('3 — Weights'!$E$15=1,PERCENTRANK(V$4:V$91,V5),1-PERCENTRANK(V$4:V$91,V5))*100,"") -> 57.5 | AV5: =IFERROR(IF('3 — Weights'!$E$16=1,PERCENTRANK(W$4:W$91,W5),1-PERCENTRANK(W$4:W$91,W5))*100,"") -> 67.9 | AW5: =IFERROR(IF('3 — Weights'!$E$17=1,PERCENTRANK(X$4:X$91,X5),1-PERCENTRANK(X$4:X$91,X5))*100,"") -> 65.6 | AX5: =IFERROR(IF('3 — Weights'!$E$18=1,PERCENTRANK(Y$4:Y$91,Y5),1-PERCENTRANK(Y$4:Y$91,Y5))*100,"") -> 57 | AY5: =IFERROR(IF('3 — Weights'!$E$18=1,PERCENTRANK(Z$4:Z$91,Z5),1-PERCENTRANK(Z$4:Z$91,Z5))*100,"") -> 63.3 | AZ5: =IFERROR(IF('3 — Weights'!$E$18=1,PERCENTRANK(AA$4:AA$91,AA5),1-PERCENTRANK(AA$4:AA$91,AA5))*100,"") -> 83.8 | BA5: =IFERROR(IF('3 — Weights'!$E$21=1,PERCENTRANK(AB$4:AB$91,AB5),1-PERCENTRANK(AB$4:AB$91,AB5))*100,"") -> 16 | BB5: =IFERROR(IF('3 — Weights'!$E$22=1,PERCENTRANK(AC$4:AC$91,AC5),1-PERCENTRANK(AC$4:AC$91,AC5))*100,"") -> 62 | BC5: =IFERROR(IF('3 — Weights'!$E$23=1,PERCENTRANK(AD$4:AD$91,AD5),1-PERCENTRANK(AD$4:AD$91,AD5))*100,"") -> 43.7 | BD5: =IFERROR(IF('3 — Weights'!$E$24=1,PERCENTRANK(AE$4:AE$91,AE5),1-PERCENTRANK(AE$4:AE$91,AE5))*100,"") -> 73.6 | BE5: =IFERROR(IF('3 — Weights'!$E$25=1,PERCENTRANK(AF$4:AF$91,AF5),1-PERCENTRANK(AF$4:AF$91,AF5))*100,"") -> 87.4 | BF5: {=IFERROR(SUMPRODUCT(TRANSPOSE(AH5:BE5), [1]!Table2[Weight Claude]),"")} -> 66.91 | BG5: {=IFERROR(SUMPRODUCT(TRANSPOSE(AH5:BE5), [1]!Table2[Weight Cape IMC]),"")} -> 66.91
A6: =IFERROR(RANK(BG6,BG$4:BG$91),"") -> 4 | B6: APP-US | C6: AppLovin Corp. Class A | D6: {=IFERROR(_xll.FDS($B6,"FR_RBICS_NAME_CURR(""IND"")"), "")} -> Customer Relationship Management Software | E6: {=PROPER(IFERROR(_xll.FDS($B6,"P_DCOUNTRY"), ""))} -> United States | F6: {=IFERROR(_xll.FDS($B6,"FCS_EV_DAILY(MV,NOW,,,USD,M)"), "")} -> 133672.51 | G6: {=IFERROR(_xll.FDS($B6,"AVG(P_VOLUME_FRQ(-1AM,NOW,D,,6))*P_PRICE_AVG(-1AM,NOW,,USD)"), "")} -> 3372.0398 | H6: {=IFERROR(_xll.FDS($B6,"OS_SEC_FLT_PCT(0D,,MTD,SEC)")/100, "")} -> 0.726322 | I6: {=IFERROR(_xll.FDS($B6,"FE_ACTUAL(ACTUAL,SALES,ANN_ROLL,0,,,,'CURRENCY=USD')"), "")} -> 5480.717 | J6: {=IFERROR(_xll.FDS($B6,"FE_ACTUAL(ACTUAL,EPS,ANN_ROLL,0,,,,'CURRENCY=USD')"), "")} -> 9.75 | K6: {=IFERROR(_xll.FDS($B6,"POW(FE_ESTIMATE(SALES,MEAN,STMA,,NOW,,,'CURRENCY=USD')/FE_ESTIMATE(SALES,MEAN,LTMA,,NOW,,,'CURRENCY=USD'),0.5)-1"), "")} -> 0.34842794 | L6: {=IFERROR(_xll.FDS($B6,"POW(FE_ESTIMATE(EPS,MEAN,STMA,,NOW,,,'CURRENCY=USD')/FE_ESTIMATE(EPS,MEAN,LTMA,,NOW,,,'CURRENCY=USD'),0.5)-1"), "")} -> 0.42091098 | M6: {=IFERROR(_xll.FDS($B6,"FF_GROSS_MGN(LTM_R,0)"), "")} -> 85.470904 | N6: {=IFERROR(_xll.FDS($B6,"FF_EBITDA_OPER_MGN(LTM_R,0)"), "")} -> 75.735838 | O6: {=IFERROR(_xll.FDS($B6,"FF_NET_MGN(LTM_R,0)"), "")} -> 56.592276 | P6: {=IFERROR(_xll.FDS($B6,"FE_VALUATION(NETDEBT_EBITDA,MEAN,NTMA,,NOW,,,'')"), "")} -> -0.42884582 | Q6: {=IFERROR(_xll.FDS($B6,"FE_VALUATION(MCAP_FCF,MEAN,NTMA,,NOW,,,'')"), "")} -> 4.0581355 | R6: {=IFERROR(_xll.FDS($B6,"FE_VALUATION(DIV_YLD,MEAN,NTMA,,NOW,,,'')"), "")} -> 0 | S6: {=IFERROR(_xll.FDS($B6,"FE_VALUATION(ROE,MEAN,NTMA,,0,,,'')" ), "")} -> 103.1667 | T6: {=IFERROR(_xll.FDS($B6,"FE_VALUATION(ROIC,MEAN,NTMA,,0,,,'')" ), "")} -> 54.05012 | U6: {=IFERROR(((_xll.FDS($B6,"FE_ACTUAL(ACTUAL,SALES,ANN_ROLL,0,,,,'CURRENCY=USD')")/_xll.FDS($B6,"FE_ACTUAL(ACTUAL,SALES,ANN_ROLL,-1,,,,'CURRENCY=USD')")-1)*100)+(_xll.FDS($B6,"FE_VALUATION(EBITDA_MARGIN,MEAN,ANN_ROLL,0,NOW,,,'')") ), "")} -> 98.71525 | V6: {=IFERROR(_xll.FDS($B6,"FE_VALUATION(PE,MEAN,NTMA,,0,,,'')" ), "")} -> 24.144264 | W6: {=IFERROR(_xll.FDS($B6,"FE_VALUATION(P_SALESPS,MEAN,NTMA,,0,,,'')" ), "")} -> 16.01234 | X6: {=IFERROR(_xll.FDS($B6,"FE_VALUATION(FFEV_SALES,MEAN,NTMA,,0,,,'')" ), "")} -> 16.355515 | Y6: {=IFERROR(_xll.FDS($B6,"FE_VALUATION(FFEV_EBITDA,MEAN,NTMA,,0,,,'')" ), "")} -> 19.3847 | Z6: {=IFERROR(_xll.FDS($B6,"PERCENT_CHANGE(FE_VALUATION(PE,MEAN,NTMA,,0,,,''),MAX(FE_VALUATION(PE,MEAN,NTMA,,-1AY,0,,'')))")/100,"")} -> -0.58231354 | AA6: {=IFERROR(_xll.FDS($B6,"PERCENT_CHANGE(FE_VALUATION(FFEV_EBITDA,MEAN,NTMA,,0,,,''),MAX(FE_VALUATION(FFEV_EBITDA,MEAN,NTMA,,-1AY,0,,'')))")/100,"")} -> -0.55731331 | AB6: {=IFERROR(_xll.FDS($B6,"FG_PRICE(0,,,USD)/P_PRICE_HIGH(-1AY,0,USD,,,""PRICE"",""INTRA"")")-1, "")} -> -0.47261973 | AC6: {=IFERROR(_xll.FDS($B6,"RTP_PRICE_TARGET(USD)/FG_PRICE(0,,,USD)")-1, "")} -> 0.70164285 | AD6: {=IFERROR(_xll.FDS($B6,"FG_PRICE(0,,,USD)/FG_PRICE_MAVG(0,,,USD,50)")-1, "")} -> -0.3009329 | AE6: {=IFERROR(_xll.FDS($B6,"FG_PRICE(0,,,USD)/FG_PRICE_MAVG(0,,,USD,100)")-1, "")} -> -0.32975212 | AF6: {=IFERROR(_xll.FDS($B6,"FG_PRICE(0,,,USD)/FG_PRICE_MAVG(0,,,USD,200)")-1, "")} -> -0.22455901 | AG6: {=IFERROR(_xll.FDS($B6,"FE_RATING(MEAN,TEXTONLY,0,NOW,,,'')"), "")} -> Buy | AH6: =IFERROR(IF('3 — Weights'!$E$2=1,PERCENTRANK(I$4:I$91,I6),1-PERCENTRANK(I$4:I$91,I6))*100,"") -> 79.3 | AI6: =IFERROR(IF('3 — Weights'!$E$3=1,PERCENTRANK(J$4:J$91,J6),1-PERCENTRANK(J$4:J$91,J6))*100,"") -> 89.6 | AJ6: =IFERROR(IF('3 — Weights'!$E$4=1,PERCENTRANK(K$4:K$91,K6),1-PERCENTRANK(K$4:K$91,K6))*100,"") -> 97.7 | AK6: =IFERROR(IF('3 — Weights'!$E$5=1,PERCENTRANK(L$4:L$91,L6),1-PERCENTRANK(L$4:L$91,L6))*100,"") -> 91.6 | AL6: =IFERROR(IF('3 — Weights'!$E$6=1,PERCENTRANK(M$4:M$91,M6),1-PERCENTRANK(M$4:M$91,M6))*100,"") -> 95.1 | AM6: =IFERROR(IF('3 — Weights'!$E$7=1,PERCENTRANK(N$4:N$91,N6),1-PERCENTRANK(N$4:N$91,N6))*100,"") -> 100 | AN6: =IFERROR(IF('3 — Weights'!$E$8=1,PERCENTRANK(O$4:O$91,O6),1-PERCENTRANK(O$4:O$91,O6))*100,"") -> 98.7 | AO6: =IFERROR(IF('3 — Weights'!$E$9=1,PERCENTRANK(P$4:P$91,P6),1-PERCENTRANK(P$4:P$91,P6))*100,"") -> 35 | AP6: =IFERROR(IF('3 — Weights'!$E$10=1,PERCENTRANK(Q$4:Q$91,Q6),1-PERCENTRANK(Q$4:Q$91,Q6))*100,"") -> 35.7 | AQ6: =IFERROR(IF('3 — Weights'!$E$11=1,PERCENTRANK(R$4:R$91,R6),1-PERCENTRANK(R$4:R$91,R6))*100,"") -> 0 | AR6: =IFERROR(IF('3 — Weights'!$E$12=1,PERCENTRANK(S$4:S$91,S6),1-PERCENTRANK(S$4:S$91,S6))*100,"") -> 97.5 | AS6: =IFERROR(IF('3 — Weights'!$E$13=1,PERCENTRANK(T$4:T$91,T6),1-PERCENTRANK(T$4:T$91,T6))*100,"") -> 98.6 | AT6: =IFERROR(IF('3 — Weights'!$E$14=1,PERCENTRANK(U$4:U$91,U6),1-PERCENTRANK(U$4:U$91,U6))*100,"") -> 97.5 | AU6: =IFERROR(IF('3 — Weights'!$E$15=1,PERCENTRANK(V$4:V$91,V6),1-PERCENTRANK(V$4:V$91,V6))*100,"") -> 42.6 | AV6: =IFERROR(IF('3 — Weights'!$E$16=1,PERCENTRANK(W$4:W$91,W6),1-PERCENTRANK(W$4:W$91,W6))*100,"") -> 4.6 | AW6: =IFERROR(IF('3 — Weights'!$E$17=1,PERCENTRANK(X$4:X$91,X6),1-PERCENTRANK(X$4:X$91,X6))*100,"") -> 4.6 | AX6: =IFERROR(IF('3 — Weights'!$E$18=1,PERCENTRANK(Y$4:Y$91,Y6),1-PERCENTRANK(Y$4:Y$91,Y6))*100,"") -> 33.8 | AY6: =IFERROR(IF('3 — Weights'!$E$18=1,PERCENTRANK(Z$4:Z$91,Z6),1-PERCENTRANK(Z$4:Z$91,Z6))*100,"") -> 64.4 | AZ6: =IFERROR(IF('3 — Weights'!$E$18=1,PERCENTRANK(AA$4:AA$91,AA6),1-PERCENTRANK(AA$4:AA$91,AA6))*100,"") -> 59.4 | BA6: =IFERROR(IF('3 — Weights'!$E$21=1,PERCENTRANK(AB$4:AB$91,AB6),1-PERCENTRANK(AB$4:AB$91,AB6))*100,"") -> 41.3 | BB6: =IFERROR(IF('3 — Weights'!$E$22=1,PERCENTRANK(AC$4:AC$91,AC6),1-PERCENTRANK(AC$4:AC$91,AC6))*100,"") -> 75.8 | BC6: =IFERROR(IF('3 — Weights'!$E$23=1,PERCENTRANK(AD$4:AD$91,AD6),1-PERCENTRANK(AD$4:AD$91,AD6))*100,"") -> 89.7 | BD6: =IFERROR(IF('3 — Weights'!$E$24=1,PERCENTRANK(AE$4:AE$91,AE6),1-PERCENTRANK(AE$4:AE$91,AE6))*100,"") -> 81.7 | BE6: =IFERROR(IF('3 — Weights'!$E$25=1,PERCENTRANK(AF$4:AF$91,AF6),1-PERCENTRANK(AF$4:AF$91,AF6))*100,"") -> 31.1 | BF6: {=IFERROR(SUMPRODUCT(TRANSPOSE(AH6:BE6), [1]!Table2[Weight Claude]),"")} -> 66.26 | BG6: {=IFERROR(SUMPRODUCT(TRANSPOSE(AH6:BE6), [1]!Table2[Weight Cape IMC]),"")} -> 66.26
A7: =IFERROR(RANK(BG7,BG$4:BG$91),"") -> 3 | B7: QLYS-US | C7: Qualys, Inc. | D7: {=IFERROR(_xll.FDS($B7,"FR_RBICS_NAME_CURR(""IND"")"), "")} -> Network Infrastructure Software | E7: {=PROPER(IFERROR(_xll.FDS($B7,"P_DCOUNTRY"), ""))} -> United States | F7: {=IFERROR(_xll.FDS($B7,"FCS_EV_DAILY(MV,NOW,,,USD,M)"), "")} -> 3197.4215 | G7: {=IFERROR(_xll.FDS($B7,"AVG(P_VOLUME_FRQ(-1AM,NOW,D,,6))*P_PRICE_AVG(-1AM,NOW,,USD)"), "")} -> 90.699946 | H7: {=IFERROR(_xll.FDS($B7,"OS_SEC_FLT_PCT(0D,,MTD,SEC)")/100, "")} -> 0.986738 | I7: {=IFERROR(_xll.FDS($B7,"FE_ACTUAL(ACTUAL,SALES,ANN_ROLL,0,,,,'CURRENCY=USD')"), "")} -> 669.125 | J7: {=IFERROR(_xll.FDS($B7,"FE_ACTUAL(ACTUAL,EPS,ANN_ROLL,0,,,,'CURRENCY=USD')"), "")} -> 7.07 | K7: {=IFERROR(_xll.FDS($B7,"POW(FE_ESTIMATE(SALES,MEAN,STMA,,NOW,,,'CURRENCY=USD')/FE_ESTIMATE(SALES,MEAN,LTMA,,NOW,,,'CURRENCY=USD'),0.5)-1"), "")} -> 0.073531089 | L7: {=IFERROR(_xll.FDS($B7,"POW(FE_ESTIMATE(EPS,MEAN,STMA,,NOW,,,'CURRENCY=USD')/FE_ESTIMATE(EPS,MEAN,LTMA,,NOW,,,'CURRENCY=USD'),0.5)-1"), "")} -> 0.063374111 | M7: {=IFERROR(_xll.FDS($B7,"FF_GROSS_MGN(LTM_R,0)"), "")} -> 82.89279 | N7: {=IFERROR(_xll.FDS($B7,"FF_EBITDA_OPER_MGN(LTM_R,0)"), "")} -> 35.531867 | O7: {=IFERROR(_xll.FDS($B7,"FF_NET_MGN(LTM_R,0)"), "")} -> 29.646638 | P7: {=IFERROR(_xll.FDS($B7,"FE_VALUATION(NETDEBT_EBITDA,MEAN,NTMA,,NOW,,,'')"), "")} -> -2.324673 | Q7: {=IFERROR(_xll.FDS($B7,"FE_VALUATION(MCAP_FCF,MEAN,NTMA,,NOW,,,'')"), "")} -> 9.681528 | R7: {=IFERROR(_xll.FDS($B7,"FE_VALUATION(DIV_YLD,MEAN,NTMA,,NOW,,,'')"), "")} -> 0 | S7: {=IFERROR(_xll.FDS($B7,"FE_VALUATION(ROE,MEAN,NTMA,,0,,,'')" ), "")} -> 36.514206 | T7: {=IFERROR(_xll.FDS($B7,"FE_VALUATION(ROIC,MEAN,NTMA,,0,,,'')" ), "")} -> 35.78148 | U7: {=IFERROR(((_xll.FDS($B7,"FE_ACTUAL(ACTUAL,SALES,ANN_ROLL,0,,,,'CURRENCY=USD')")/_xll.FDS($B7,"FE_ACTUAL(ACTUAL,SALES,ANN_ROLL,-1,,,,'CURRENCY=USD')")-1)*100)+(_xll.FDS($B7,"FE_VALUATION(EBITDA_MARGIN,MEAN,ANN_ROLL,0,NOW,,,'')") ), "")} -> 56.975736 | V7: {=IFERROR(_xll.FDS($B7,"FE_VALUATION(PE,MEAN,NTMA,,0,,,'')" ), "")} -> 11.629527 | W7: {=IFERROR(_xll.FDS($B7,"FE_VALUATION(P_SALESPS,MEAN,NTMA,,0,,,'')" ), "")} -> 4.249773 | X7: {=IFERROR(_xll.FDS($B7,"FE_VALUATION(FFEV_SALES,MEAN,NTMA,,0,,,'')" ), "")} -> 3.802272 | Y7: {=IFERROR(_xll.FDS($B7,"FE_VALUATION(FFEV_EBITDA,MEAN,NTMA,,0,,,'')" ), "")} -> 8.539159 | Z7: {=IFERROR(_xll.FDS($B7,"PERCENT_CHANGE(FE_VALUATION(PE,MEAN,NTMA,,0,,,''),MAX(FE_VALUATION(PE,MEAN,NTMA,,-1AY,0,,'')))")/100,"")} -> -0.50436705 | AA7: {=IFERROR(_xll.FDS($B7,"PERCENT_CHANGE(FE_VALUATION(FFEV_EBITDA,MEAN,NTMA,,0,,,''),MAX(FE_VALUATION(FFEV_EBITDA,MEAN,NTMA,,-1AY,0,,'')))")/100,"")} -> -0.51984789 | AB7: {=IFERROR(_xll.FDS($B7,"FG_PRICE(0,,,USD)/P_PRICE_HIGH(-1AY,0,USD,,,""PRICE"",""INTRA"")")-1, "")} -> -0.44149997 | AC7: {=IFERROR(_xll.FDS($B7,"RTP_PRICE_TARGET(USD)/FG_PRICE(0,,,USD)")-1, "")} -> 0.5906674 | AD7: {=IFERROR(_xll.FDS($B7,"FG_PRICE(0,,,USD)/FG_PRICE_MAVG(0,,,USD,50)")-1, "")} -> -0.31967086 | AE7: {=IFERROR(_xll.FDS($B7,"FG_PRICE(0,,,USD)/FG_PRICE_MAVG(0,,,USD,100)")-1, "")} -> -0.34233797 | AF7: {=IFERROR(_xll.FDS($B7,"FG_PRICE(0,,,USD)/FG_PRICE_MAVG(0,,,USD,200)")-1, "")} -> -0.35358095 | AG7: {=IFERROR(_xll.FDS($B7,"FE_RATING(MEAN,TEXTONLY,0,NOW,,,'')"), "")} -> Hold | AH7: =IFERROR(IF('3 — Weights'!$E$2=1,PERCENTRANK(I$4:I$91,I7),1-PERCENTRANK(I$4:I$91,I7))*100,"") -> 11.4 | AI7: =IFERROR(IF('3 — Weights'!$E$3=1,PERCENTRANK(J$4:J$91,J7),1-PERCENTRANK(J$4:J$91,J7))*100,"") -> 79.3 | AJ7: =IFERROR(IF('3 — Weights'!$E$4=1,PERCENTRANK(K$4:K$91,K7),1-PERCENTRANK(K$4:K$91,K7))*100,"") -> 19.5 | AK7: =IFERROR(IF('3 — Weights'!$E$5=1,PERCENTRANK(L$4:L$91,L7),1-PERCENTRANK(L$4:L$91,L7))*100,"") -> 2.3 | AL7: =IFERROR(IF('3 — Weights'!$E$6=1,PERCENTRANK(M$4:M$91,M7),1-PERCENTRANK(M$4:M$91,M7))*100,"") -> 90.2 | AM7: =IFERROR(IF('3 — Weights'!$E$7=1,PERCENTRANK(N$4:N$91,N7),1-PERCENTRANK(N$4:N$91,N7))*100,"") -> 83.1 | AN7: =IFERROR(IF('3 — Weights'!$E$8=1,PERCENTRANK(O$4:O$91,O7),1-PERCENTRANK(O$4:O$91,O7))*100,"") -> 90.3 | AO7: =IFERROR(IF('3 — Weights'!$E$9=1,PERCENTRANK(P$4:P$91,P7),1-PERCENTRANK(P$4:P$91,P7))*100,"") -> 72.3 | AP7: =IFERROR(IF('3 — Weights'!$E$10=1,PERCENTRANK(Q$4:Q$91,Q7),1-PERCENTRANK(Q$4:Q$91,Q7))*100,"") -> 94 | AQ7: =IFERROR(IF('3 — Weights'!$E$11=1,PERCENTRANK(R$4:R$91,R7),1-PERCENTRANK(R$4:R$91,R7))*100,"") -> 0 | AR7: =IFERROR(IF('3 — Weights'!$E$12=1,PERCENTRANK(S$4:S$91,S7),1-PERCENTRANK(S$4:S$91,S7))*100,"") -> 83.9 | AS7: =IFERROR(IF('3 — Weights'!$E$13=1,PERCENTRANK(T$4:T$91,T7),1-PERCENTRANK(T$4:T$91,T7))*100,"") -> 93 | AT7: =IFERROR(IF('3 — Weights'!$E$14=1,PERCENTRANK(U$4:U$91,U7),1-PERCENTRANK(U$4:U$91,U7))*100,"") -> 78 | AU7: =IFERROR(IF('3 — Weights'!$E$15=1,PERCENTRANK(V$4:V$91,V7),1-PERCENTRANK(V$4:V$91,V7))*100,"") -> 89.7 | AV7: =IFERROR(IF('3 — Weights'!$E$16=1,PERCENTRANK(W$4:W$91,W7),1-PERCENTRANK(W$4:W$91,W7))*100,"") -> 56.4 | AW7: =IFERROR(IF('3 — Weights'!$E$17=1,PERCENTRANK(X$4:X$91,X7),1-PERCENTRANK(X$4:X$91,X7))*100,"") -> 59.8 | AX7: =IFERROR(IF('3 — Weights'!$E$18=1,PERCENTRANK(Y$4:Y$91,Y7),1-PERCENTRANK(Y$4:Y$91,Y7))*100,"") -> 87.3 | AY7: =IFERROR(IF('3 — Weights'!$E$18=1,PERCENTRANK(Z$4:Z$91,Z7),1-PERCENTRANK(Z$4:Z$91,Z7))*100,"") -> 49.5 | AZ7: =IFERROR(IF('3 — Weights'!$E$18=1,PERCENTRANK(AA$4:AA$91,AA7),1-PERCENTRANK(AA$4:AA$91,AA7))*100,"") -> 48.9 | BA7: =IFERROR(IF('3 — Weights'!$E$21=1,PERCENTRANK(AB$4:AB$91,AB7),1-PERCENTRANK(AB$4:AB$91,AB7))*100,"") -> 49.4 | BB7: =IFERROR(IF('3 — Weights'!$E$22=1,PERCENTRANK(AC$4:AC$91,AC7),1-PERCENTRANK(AC$4:AC$91,AC7))*100,"") -> 58.6 | BC7: =IFERROR(IF('3 — Weights'!$E$23=1,PERCENTRANK(AD$4:AD$91,AD7),1-PERCENTRANK(AD$4:AD$91,AD7))*100,"") -> 95.5 | BD7: =IFERROR(IF('3 — Weights'!$E$24=1,PERCENTRANK(AE$4:AE$91,AE7),1-PERCENTRANK(AE$4:AE$91,AE7))*100,"") -> 85.1 | BE7: =IFERROR(IF('3 — Weights'!$E$25=1,PERCENTRANK(AF$4:AF$91,AF7),1-PERCENTRANK(AF$4:AF$91,AF7))*100,"") -> 71.3 | BF7: {=IFERROR(SUMPRODUCT(TRANSPOSE(AH7:BE7), [1]!Table2[Weight Claude]),"")} -> 66.345 | BG7: {=IFERROR(SUMPRODUCT(TRANSPOSE(AH7:BE7), [1]!Table2[Weight Cape IMC]),"")} -> 66.345
A8: =IFERROR(RANK(BG8,BG$4:BG$91),"") -> 5 | B8: WK-US | C8: Workiva Inc. | D8: {=IFERROR(_xll.FDS($B8,"FR_RBICS_NAME_CURR(""IND"")"), "")} -> Enterprise Resource Planning Software | E8: {=PROPER(IFERROR(_xll.FDS($B8,"P_DCOUNTRY"), ""))} -> United States | F8: {=IFERROR(_xll.FDS($B8,"FCS_EV_DAILY(MV,NOW,,,USD,M)"), "")} -> 3464.5608 | G8: {=IFERROR(_xll.FDS($B8,"AVG(P_VOLUME_FRQ(-1AM,NOW,D,,6))*P_PRICE_AVG(-1AM,NOW,,USD)"), "")} -> 79.748816 | H8: {=IFERROR(_xll.FDS($B8,"OS_SEC_FLT_PCT(0D,,MTD,SEC)")/100, "")} -> 0.945492 | I8: {=IFERROR(_xll.FDS($B8,"FE_ACTUAL(ACTUAL,SALES,ANN_ROLL,0,,,,'CURRENCY=USD')"), "")} -> 884.568 | J8: {=IFERROR(_xll.FDS($B8,"FE_ACTUAL(ACTUAL,EPS,ANN_ROLL,0,,,,'CURRENCY=USD')"), "")} -> 1.78 | K8: {=IFERROR(_xll.FDS($B8,"POW(FE_ESTIMATE(SALES,MEAN,STMA,,NOW,,,'CURRENCY=USD')/FE_ESTIMATE(SALES,MEAN,LTMA,,NOW,,,'CURRENCY=USD'),0.5)-1"), "")} -> 0.16463642 | L8: {=IFERROR(_xll.FDS($B8,"POW(FE_ESTIMATE(EPS,MEAN,STMA,,NOW,,,'CURRENCY=USD')/FE_ESTIMATE(EPS,MEAN,LTMA,,NOW,,,'CURRENCY=USD'),0.5)-1"), "")} -> 0.35751335 | M8: {=IFERROR(_xll.FDS($B8,"FF_GROSS_MGN(LTM_R,0)"), "")} -> 78.471977 | N8: {=IFERROR(_xll.FDS($B8,"FF_EBITDA_OPER_MGN(LTM_R,0)"), "")} -> -3.5555209 | O8: {=IFERROR(_xll.FDS($B8,"FF_NET_MGN(LTM_R,0)"), "")} -> -2.9583932 | P8: {=IFERROR(_xll.FDS($B8,"FE_VALUATION(NETDEBT_EBITDA,MEAN,NTMA,,NOW,,,'')"), "")} -> -2.0960221 | Q8: {=IFERROR(_xll.FDS($B8,"FE_VALUATION(MCAP_FCF,MEAN,NTMA,,NOW,,,'')"), "")} -> 6.3010397 | R8: {=IFERROR(_xll.FDS($B8,"FE_VALUATION(DIV_YLD,MEAN,NTMA,,NOW,,,'')"), "")} -> 0 | S8: {=IFERROR(_xll.FDS($B8,"FE_VALUATION(ROE,MEAN,NTMA,,0,,,'')" ), "")} -> 308.23563 | T8: {=IFERROR(_xll.FDS($B8,"FE_VALUATION(ROIC,MEAN,NTMA,,0,,,'')" ), "")} -> 26.25933 | U8: {=IFERROR(((_xll.FDS($B8,"FE_ACTUAL(ACTUAL,SALES,ANN_ROLL,0,,,,'CURRENCY=USD')")/_xll.FDS($B8,"FE_ACTUAL(ACTUAL,SALES,ANN_ROLL,-1,,,,'CURRENCY=USD')")-1)*100)+(_xll.FDS($B8,"FE_VALUATION(EBITDA_MARGIN,MEAN,ANN_ROLL,0,NOW,,,'')") ), "")} -> 30.250543 | V8: {=IFERROR(_xll.FDS($B8,"FE_VALUATION(PE,MEAN,NTMA,,0,,,'')" ), "")} -> 20.549168 | W8: {=IFERROR(_xll.FDS($B8,"FE_VALUATION(P_SALESPS,MEAN,NTMA,,0,,,'')" ), "")} -> 3.087611 | X8: {=IFERROR(_xll.FDS($B8,"FE_VALUATION(FFEV_SALES,MEAN,NTMA,,0,,,'')" ), "")} -> 2.9676418 | Y8: {=IFERROR(_xll.FDS($B8,"FE_VALUATION(FFEV_EBITDA,MEAN,NTMA,,0,,,'')" ), "")} -> 18.165535 | Z8: {=IFERROR(_xll.FDS($B8,"PERCENT_CHANGE(FE_VALUATION(PE,MEAN,NTMA,,0,,,''),MAX(FE_VALUATION(PE,MEAN,NTMA,,-1AY,0,,'')))")/100,"")} -> -0.73145283 | AA8: {=IFERROR(_xll.FDS($B8,"PERCENT_CHANGE(FE_VALUATION(FFEV_EBITDA,MEAN,NTMA,,0,,,''),MAX(FE_VALUATION(FFEV_EBITDA,MEAN,NTMA,,-1AY,0,,'')))")/100,"")} -> -0.77442807 | AB8: {=IFERROR(_xll.FDS($B8,"FG_PRICE(0,,,USD)/P_PRICE_HIGH(-1AY,0,USD,,,""PRICE"",""INTRA"")")-1, "")} -> -0.40573665 | AC8: {=IFERROR(_xll.FDS($B8,"RTP_PRICE_TARGET(USD)/FG_PRICE(0,,,USD)")-1, "")} -> 0.55033872 | AD8: {=IFERROR(_xll.FDS($B8,"FG_PRICE(0,,,USD)/FG_PRICE_MAVG(0,,,USD,50)")-1, "")} -> -0.26861854 | AE8: {=IFERROR(_xll.FDS($B8,"FG_PRICE(0,,,USD)/FG_PRICE_MAVG(0,,,USD,100)")-1, "")} -> -0.31228472 | AF8: {=IFERROR(_xll.FDS($B8,"FG_PRICE(0,,,USD)/FG_PRICE_MAVG(0,,,USD,200)")-1, "")} -> -0.26266315 | AG8: {=IFERROR(_xll.FDS($B8,"FE_RATING(MEAN,TEXTONLY,0,NOW,,,'')"), "")} -> Buy | AH8: =IFERROR(IF('3 — Weights'!$E$2=1,PERCENTRANK(I$4:I$91,I8),1-PERCENTRANK(I$4:I$91,I8))*100,"") -> 27.5 | AI8: =IFERROR(IF('3 — Weights'!$E$3=1,PERCENTRANK(J$4:J$91,J8),1-PERCENTRANK(J$4:J$91,J8))*100,"") -> 42.5 | AJ8: =IFERROR(IF('3 — Weights'!$E$4=1,PERCENTRANK(K$4:K$91,K8),1-PERCENTRANK(K$4:K$91,K8))*100,"") -> 64.3 | AK8: =IFERROR(IF('3 — Weights'!$E$5=1,PERCENTRANK(L$4:L$91,L8),1-PERCENTRANK(L$4:L$91,L8))*100,"") -> 90.4 | AL8: =IFERROR(IF('3 — Weights'!$E$6=1,PERCENTRANK(M$4:M$91,M8),1-PERCENTRANK(M$4:M$91,M8))*100,"") -> 74.3 | AM8: =IFERROR(IF('3 — Weights'!$E$7=1,PERCENTRANK(N$4:N$91,N8),1-PERCENTRANK(N$4:N$91,N8))*100,"") -> 12.9 | AN8: =IFERROR(IF('3 — Weights'!$E$8=1,PERCENTRANK(O$4:O$91,O8),1-PERCENTRANK(O$4:O$91,O8))*100,"") -> 24 | AO8: =IFERROR(IF('3 — Weights'!$E$9=1,PERCENTRANK(P$4:P$91,P8),1-PERCENTRANK(P$4:P$91,P8))*100,"") -> 65.1 | AP8: =IFERROR(IF('3 — Weights'!$E$10=1,PERCENTRANK(Q$4:Q$91,Q8),1-PERCENTRANK(Q$4:Q$91,Q8))*100,"") -> 64.2 | AQ8: =IFERROR(IF('3 — Weights'!$E$11=1,PERCENTRANK(R$4:R$91,R8),1-PERCENTRANK(R$4:R$91,R8))*100,"") -> 0 | AR8: =IFERROR(IF('3 — Weights'!$E$12=1,PERCENTRANK(S$4:S$91,S8),1-PERCENTRANK(S$4:S$91,S8))*100,"") -> 98.7 | AS8: =IFERROR(IF('3 — Weights'!$E$13=1,PERCENTRANK(T$4:T$91,T8),1-PERCENTRANK(T$4:T$91,T8))*100,"") -> 80.5 | AT8: =IFERROR(IF('3 — Weights'!$E$14=1,PERCENTRANK(U$4:U$91,U8),1-PERCENTRANK(U$4:U$91,U8))*100,"") -> 12.1 | AU8: =IFERROR(IF('3 — Weights'!$E$15=1,PERCENTRANK(V$4:V$91,V8),1-PERCENTRANK(V$4:V$91,V8))*100,"") -> 51.8 | AV8: =IFERROR(IF('3 — Weights'!$E$16=1,PERCENTRANK(W$4:W$91,W8),1-PERCENTRANK(W$4:W$91,W8))*100,"") -> 73.6 | AW8: =IFERROR(IF('3 — Weights'!$E$17=1,PERCENTRANK(X$4:X$91,X8),1-PERCENTRANK(X$4:X$91,X8))*100,"") -> 77.1 | AX8: =IFERROR(IF('3 — Weights'!$E$18=1,PERCENTRANK(Y$4:Y$91,Y8),1-PERCENTRANK(Y$4:Y$91,Y8))*100,"") -> 37.3 | AY8: =IFERROR(IF('3 — Weights'!$E$18=1,PERCENTRANK(Z$4:Z$91,Z8),1-PERCENTRANK(Z$4:Z$91,Z8))*100,"") -> 90.9 | AZ8: =IFERROR(IF('3 — Weights'!$E$18=1,PERCENTRANK(AA$4:AA$91,AA8),1-PERCENTRANK(AA$4:AA$91,AA8))*100,"") -> 97.7 | BA8: =IFERROR(IF('3 — Weights'!$E$21=1,PERCENTRANK(AB$4:AB$91,AB8),1-PERCENTRANK(AB$4:AB$91,AB8))*100,"") -> 58.6 | BB8: =IFERROR(IF('3 — Weights'!$E$22=1,PERCENTRANK(AC$4:AC$91,AC8),1-PERCENTRANK(AC$4:AC$91,AC8))*100,"") -> 52.8 | BC8: =IFERROR(IF('3 — Weights'!$E$23=1,PERCENTRANK(AD$4:AD$91,AD8),1-PERCENTRANK(AD$4:AD$91,AD8))*100,"") -> 80.5 | BD8: =IFERROR(IF('3 — Weights'!$E$24=1,PERCENTRANK(AE$4:AE$91,AE8),1-PERCENTRANK(AE$4:AE$91,AE8))*100,"") -> 74.8 | BE8: =IFERROR(IF('3 — Weights'!$E$25=1,PERCENTRANK(AF$4:AF$91,AF8),1-PERCENTRANK(AF$4:AF$91,AF8))*100,"") -> 46 | BF8: {=IFERROR(SUMPRODUCT(TRANSPOSE(AH8:BE8), [1]!Table2[Weight Claude]),"")} -> 64.795 | BG8: {=IFERROR(SUMPRODUCT(TRANSPOSE(AH8:BE8), [1]!Table2[Weight Cape IMC]),"")} -> 64.795
A9: =IFERROR(RANK(BG9,BG$4:BG$91),"") -> 7 | B9: PLTR-US | C9: Palantir Technologies Inc. Class A | D9: {=IFERROR(_xll.FDS($B9,"FR_RBICS_NAME_CURR(""IND"")"), "")} -> Government and Not-For-Profit Industry Software | E9: {=PROPER(IFERROR(_xll.FDS($B9,"P_DCOUNTRY"), ""))} -> United States | F9: {=IFERROR(_xll.FDS($B9,"FCS_EV_DAILY(MV,NOW,,,USD,M)"), "")} -> 331614.85 | G9: {=IFERROR(_xll.FDS($B9,"AVG(P_VOLUME_FRQ(-1AM,NOW,D,,6))*P_PRICE_AVG(-1AM,NOW,,USD)"), "")} -> 7934.6961 | H9: {=IFERROR(_xll.FDS($B9,"OS_SEC_FLT_PCT(0D,,MTD,SEC)")/100, "")} -> 0.954558 | I9: {=IFERROR(_xll.FDS($B9,"FE_ACTUAL(ACTUAL,SALES,ANN_ROLL,0,,,,'CURRENCY=USD')"), "")} -> 4475.446 | J9: {=IFERROR(_xll.FDS($B9,"FE_ACTUAL(ACTUAL,EPS,ANN_ROLL,0,,,,'CURRENCY=USD')"), "")} -> 0.75 | K9: {=IFERROR(_xll.FDS($B9,"POW(FE_ESTIMATE(SALES,MEAN,STMA,,NOW,,,'CURRENCY=USD')/FE_ESTIMATE(SALES,MEAN,LTMA,,NOW,,,'CURRENCY=USD'),0.5)-1"), "")} -> 0.49188126 | L9: {=IFERROR(_xll.FDS($B9,"POW(FE_ESTIMATE(EPS,MEAN,STMA,,NOW,,,'CURRENCY=USD')/FE_ESTIMATE(EPS,MEAN,LTMA,,NOW,,,'CURRENCY=USD'),0.5)-1"), "")} -> 0.52567539 | M9: {=IFERROR(_xll.FDS($B9,"FF_GROSS_MGN(LTM_R,0)"), "")} -> 82.366517 | N9: {=IFERROR(_xll.FDS($B9,"FF_EBITDA_OPER_MGN(LTM_R,0)"), "")} -> 32.179139 | O9: {=IFERROR(_xll.FDS($B9,"FF_NET_MGN(LTM_R,0)"), "")} -> 36.309968 | P9: {=IFERROR(_xll.FDS($B9,"FE_VALUATION(NETDEBT_EBITDA,MEAN,NTMA,,NOW,,,'')"), "")} -> -2.7048798 | Q9: {=IFERROR(_xll.FDS($B9,"FE_VALUATION(MCAP_FCF,MEAN,NTMA,,NOW,,,'')"), "")} -> 1.3955652 | R9: {=IFERROR(_xll.FDS($B9,"FE_VALUATION(DIV_YLD,MEAN,NTMA,,NOW,,,'')"), "")} -> 0 | S9: {=IFERROR(_xll.FDS($B9,"FE_VALUATION(ROE,MEAN,NTMA,,0,,,'')" ), "")} -> 28.090036 | T9: {=IFERROR(_xll.FDS($B9,"FE_VALUATION(ROIC,MEAN,NTMA,,0,,,'')" ), "")} | U9: {=IFERROR(((_xll.FDS($B9,"FE_ACTUAL(ACTUAL,SALES,ANN_ROLL,0,,,,'CURRENCY=USD')")/_xll.FDS($B9,"FE_ACTUAL(ACTUAL,SALES,ANN_ROLL,-1,,,,'CURRENCY=USD')")-1)*100)+(_xll.FDS($B9,"FE_VALUATION(EBITDA_MARGIN,MEAN,ANN_ROLL,0,NOW,,,'')") ), "")} -> 107.1295 | V9: {=IFERROR(_xll.FDS($B9,"FE_VALUATION(PE,MEAN,NTMA,,0,,,'')" ), "")} -> 94.17743 | W9: {=IFERROR(_xll.FDS($B9,"FE_VALUATION(P_SALESPS,MEAN,NTMA,,0,,,'')" ), "")} -> 40.327347 | X9: {=IFERROR(_xll.FDS($B9,"FE_VALUATION(FFEV_SALES,MEAN,NTMA,,0,,,'')" ), "")} -> 42.356777 | Y9: {=IFERROR(_xll.FDS($B9,"FE_VALUATION(FFEV_EBITDA,MEAN,NTMA,,0,,,'')" ), "")} -> 74.32565 | Z9: {=IFERROR(_xll.FDS($B9,"PERCENT_CHANGE(FE_VALUATION(PE,MEAN,NTMA,,0,,,''),MAX(FE_VALUATION(PE,MEAN,NTMA,,-1AY,0,,'')))")/100,"")} -> -0.63115369 | AA9: {=IFERROR(_xll.FDS($B9,"PERCENT_CHANGE(FE_VALUATION(FFEV_EBITDA,MEAN,NTMA,,0,,,''),MAX(FE_VALUATION(FFEV_EBITDA,MEAN,NTMA,,-1AY,0,,'')))")/100,"")} -> -0.63703464 | AB9: {=IFERROR(_xll.FDS($B9,"FG_PRICE(0,,,USD)/P_PRICE_HIGH(-1AY,0,USD,,,""PRICE"",""INTRA"")")-1, "")} -> -0.37914418 | AC9: {=IFERROR(_xll.FDS($B9,"RTP_PRICE_TARGET(USD)/FG_PRICE(0,,,USD)")-1, "")} -> 0.45431481 | AD9: {=IFERROR(_xll.FDS($B9,"FG_PRICE(0,,,USD)/FG_PRICE_MAVG(0,,,USD,50)")-1, "")} -> -0.2144573 | AE9: {=IFERROR(_xll.FDS($B9,"FG_PRICE(0,,,USD)/FG_PRICE_MAVG(0,,,USD,100)")-1, "")} -> -0.24982128 | AF9: {=IFERROR(_xll.FDS($B9,"FG_PRICE(0,,,USD)/FG_PRICE_MAVG(0,,,USD,200)")-1, "")} -> -0.20094255 | AG9: {=IFERROR(_xll.FDS($B9,"FE_RATING(MEAN,TEXTONLY,0,NOW,,,'')"), "")} -> Overweight | AH9: =IFERROR(IF('3 — Weights'!$E$2=1,PERCENTRANK(I$4:I$91,I9),1-PERCENTRANK(I$4:I$91,I9))*100,"") -> 74.7 | AI9: =IFERROR(IF('3 — Weights'!$E$3=1,PERCENTRANK(J$4:J$91,J9),1-PERCENTRANK(J$4:J$91,J9))*100,"") -> 28.7 | AJ9: =IFERROR(IF('3 — Weights'!$E$4=1,PERCENTRANK(K$4:K$91,K9),1-PERCENTRANK(K$4:K$91,K9))*100,"") -> 98.8 | AK9: =IFERROR(IF('3 — Weights'!$E$5=1,PERCENTRANK(L$4:L$91,L9),1-PERCENTRANK(L$4:L$91,L9))*100,"") -> 96.4 | AL9: =IFERROR(IF('3 — Weights'!$E$6=1,PERCENTRANK(M$4:M$91,M9),1-PERCENTRANK(M$4:M$91,M9))*100,"") -> 86.5 | AM9: =IFERROR(IF('3 — Weights'!$E$7=1,PERCENTRANK(N$4:N$91,N9),1-PERCENTRANK(N$4:N$91,N9))*100,"") -> 79.2 | AN9: =IFERROR(IF('3 — Weights'!$E$8=1,PERCENTRANK(O$4:O$91,O9),1-PERCENTRANK(O$4:O$91,O9))*100,"") -> 93.9 | AO9: =IFERROR(IF('3 — Weights'!$E$9=1,PERCENTRANK(P$4:P$91,P9),1-PERCENTRANK(P$4:P$91,P9))*100,"") -> 77.2 | AP9: =IFERROR(IF('3 — Weights'!$E$10=1,PERCENTRANK(Q$4:Q$91,Q9),1-PERCENTRANK(Q$4:Q$91,Q9))*100,"") -> 5.9 | AQ9: =IFERROR(IF('3 — Weights'!$E$11=1,PERCENTRANK(R$4:R$91,R9),1-PERCENTRANK(R$4:R$91,R9))*100,"") -> 0 | AR9: =IFERROR(IF('3 — Weights'!$E$12=1,PERCENTRANK(S$4:S$91,S9),1-PERCENTRANK(S$4:S$91,S9))*100,"") -> 74 | AS9: =IFERROR(IF('3 — Weights'!$E$13=1,PERCENTRANK(T$4:T$91,T9),1-PERCENTRANK(T$4:T$91,T9))*100,"") | AT9: =IFERROR(IF('3 — Weights'!$E$14=1,PERCENTRANK(U$4:U$91,U9),1-PERCENTRANK(U$4:U$91,U9))*100,"") -> 98.7 | AU9: =IFERROR(IF('3 — Weights'!$E$15=1,PERCENTRANK(V$4:V$91,V9),1-PERCENTRANK(V$4:V$91,V9))*100,"") -> 8.1 | AV9: =IFERROR(IF('3 — Weights'!$E$16=1,PERCENTRANK(W$4:W$91,W9),1-PERCENTRANK(W$4:W$91,W9))*100,"") -> 1.2 | AW9: =IFERROR(IF('3 — Weights'!$E$17=1,PERCENTRANK(X$4:X$91,X9),1-PERCENTRANK(X$4:X$91,X9))*100,"") -> 1.2 | AX9: =IFERROR(IF('3 — Weights'!$E$18=1,PERCENTRANK(Y$4:Y$91,Y9),1-PERCENTRANK(Y$4:Y$91,Y9))*100,"") -> 3.5 | AY9: =IFERROR(IF('3 — Weights'!$E$18=1,PERCENTRANK(Z$4:Z$91,Z9),1-PERCENTRANK(Z$4:Z$91,Z9))*100,"") -> 82.8 | AZ9: =IFERROR(IF('3 — Weights'!$E$18=1,PERCENTRANK(AA$4:AA$91,AA9),1-PERCENTRANK(AA$4:AA$91,AA9))*100,"") -> 82.6 | BA9: =IFERROR(IF('3 — Weights'!$E$21=1,PERCENTRANK(AB$4:AB$91,AB9),1-PERCENTRANK(AB$4:AB$91,AB9))*100,"") -> 67.8 | BB9: =IFERROR(IF('3 — Weights'!$E$22=1,PERCENTRANK(AC$4:AC$91,AC9),1-PERCENTRANK(AC$4:AC$91,AC9))*100,"") -> 40.2 | BC9: =IFERROR(IF('3 — Weights'!$E$23=1,PERCENTRANK(AD$4:AD$91,AD9),1-PERCENTRANK(AD$4:AD$91,AD9))*100,"") -> 65.6 | BD9: =IFERROR(IF('3 — Weights'!$E$24=1,PERCENTRANK(AE$4:AE$91,AE9),1-PERCENTRANK(AE$4:AE$91,AE9))*100,"") -> 48.3 | BE9: =IFERROR(IF('3 — Weights'!$E$25=1,PERCENTRANK(AF$4:AF$91,AF9),1-PERCENTRANK(AF$4:AF$91,AF9))*100,"") -> 29.9 | BF9: {=IFERROR(SUMPRODUCT(TRANSPOSE(AH9:BE9), [1]!Table2[Weight Claude]),"")} -> 61.155 | BG9: {=IFERROR(SUMPRODUCT(TRANSPOSE(AH9:BE9), [1]!Table2[Weight Cape IMC]),"")} -> 61.155
A10: =IFERROR(RANK(BG10,BG$4:BG$91),"") -> 9 | B10: DT-US | C10: Dynatrace, Inc. | D10: {=IFERROR(_xll.FDS($B10,"FR_RBICS_NAME_CURR(""IND"")"), "")} -> Network Infrastructure Software | E10: {=PROPER(IFERROR(_xll.FDS($B10,"P_DCOUNTRY"), ""))} -> United States | F10: {=IFERROR(_xll.FDS($B10,"FCS_EV_DAILY(MV,NOW,,,USD,M)"), "")} -> 10620.581 | G10: {=IFERROR(_xll.FDS($B10,"AVG(P_VOLUME_FRQ(-1AM,NOW,D,,6))*P_PRICE_AVG(-1AM,NOW,,USD)"), "")} -> 235.06203 | H10: {=IFERROR(_xll.FDS($B10,"OS_SEC_FLT_PCT(0D,,MTD,SEC)")/100, "")} -> 0.988897 | I10: {=IFERROR(_xll.FDS($B10,"FE_ACTUAL(ACTUAL,SALES,ANN_ROLL,0,,,,'CURRENCY=USD')"), "")} -> 1698.683 | J10: {=IFERROR(_xll.FDS($B10,"FE_ACTUAL(ACTUAL,EPS,ANN_ROLL,0,,,,'CURRENCY=USD')"), "")} -> 1.39 | K10: {=IFERROR(_xll.FDS($B10,"POW(FE_ESTIMATE(SALES,MEAN,STMA,,NOW,,,'CURRENCY=USD')/FE_ESTIMATE(SALES,MEAN,LTMA,,NOW,,,'CURRENCY=USD'),0.5)-1"), "")} -> 0.14754063 | L10: {=IFERROR(_xll.FDS($B10,"POW(FE_ESTIMATE(EPS,MEAN,STMA,,NOW,,,'CURRENCY=USD')/FE_ESTIMATE(EPS,MEAN,LTMA,,NOW,,,'CURRENCY=USD'),0.5)-1"), "")} -> 0.14545838 | M10: {=IFERROR(_xll.FDS($B10,"FF_GROSS_MGN(LTM_R,0)"), "")} -> 81.574419 | N10: {=IFERROR(_xll.FDS($B10,"FF_EBITDA_OPER_MGN(LTM_R,0)"), "")} -> 14.261511 | O10: {=IFERROR(_xll.FDS($B10,"FF_NET_MGN(LTM_R,0)"), "")} -> 9.5534507 | P10: {=IFERROR(_xll.FDS($B10,"FE_VALUATION(NETDEBT_EBITDA,MEAN,NTMA,,NOW,,,'')"), "")} -> -2.5842223 | Q10: {=IFERROR(_xll.FDS($B10,"FE_VALUATION(MCAP_FCF,MEAN,NTMA,,NOW,,,'')"), "")} -> 5.884752 | R10: {=IFERROR(_xll.FDS($B10,"FE_VALUATION(DIV_YLD,MEAN,NTMA,,NOW,,,'')"), "")} -> 0 | S10: {=IFERROR(_xll.FDS($B10,"FE_VALUATION(ROE,MEAN,NTMA,,0,,,'')" ), "")} -> 17.984053 | T10: {=IFERROR(_xll.FDS($B10,"FE_VALUATION(ROIC,MEAN,NTMA,,0,,,'')" ), "")} -> 16.54999 | U10: {=IFERROR(((_xll.FDS($B10,"FE_ACTUAL(ACTUAL,SALES,ANN_ROLL,0,,,,'CURRENCY=USD')")/_xll.FDS($B10,"FE_ACTUAL(ACTUAL,SALES,ANN_ROLL,-1,,,,'CURRENCY=USD')")-1)*100)+(_xll.FDS($B10,"FE_VALUATION(EBITDA_MARGIN,MEAN,ANN_ROLL,0,NOW,,,'')") ), "")} -> 49.576971 | V10: {=IFERROR(_xll.FDS($B10,"FE_VALUATION(PE,MEAN,NTMA,,0,,,'')" ), "")} -> 18.10821 | W10: {=IFERROR(_xll.FDS($B10,"FE_VALUATION(P_SALESPS,MEAN,NTMA,,0,,,'')" ), "")} -> 4.487807 | X10: {=IFERROR(_xll.FDS($B10,"FE_VALUATION(FFEV_SALES,MEAN,NTMA,,0,,,'')" ), "")} -> 4.078665 | Y10: {=IFERROR(_xll.FDS($B10,"FE_VALUATION(FFEV_EBITDA,MEAN,NTMA,,0,,,'')" ), "")} -> 13.261618 | Z10: {=IFERROR(_xll.FDS($B10,"PERCENT_CHANGE(FE_VALUATION(PE,MEAN,NTMA,,0,,,''),MAX(FE_VALUATION(PE,MEAN,NTMA,,-1AY,0,,'')))")/100,"")} -> -0.53002122 | AA10: {=IFERROR(_xll.FDS($B10,"PERCENT_CHANGE(FE_VALUATION(FFEV_EBITDA,MEAN,NTMA,,0,,,''),MAX(FE_VALUATION(FFEV_EBITDA,MEAN,NTMA,,-1AY,0,,'')))")/100,"")} -> -0.54523905 | AB10: {=IFERROR(_xll.FDS($B10,"FG_PRICE(0,,,USD)/P_PRICE_HIGH(-1AY,0,USD,,,""PRICE"",""INTRA"")")-1, "")} -> -0.43011647 | AC10: {=IFERROR(_xll.FDS($B10,"RTP_PRICE_TARGET(USD)/FG_PRICE(0,,,USD)")-1, "")} -> 0.46082724 | AD10: {=IFERROR(_xll.FDS($B10,"FG_PRICE(0,,,USD)/FG_PRICE_MAVG(0,,,USD,50)")-1, "")} -> -0.14760708 | AE10: {=IFERROR(_xll.FDS($B10,"FG_PRICE(0,,,USD)/FG_PRICE_MAVG(0,,,USD,100)")-1, "")} -> -0.21662538 | AF10: {=IFERROR(_xll.FDS($B10,"FG_PRICE(0,,,USD)/FG_PRICE_MAVG(0,,,USD,200)")-1, "")} -> -0.28230542 | AG10: {=IFERROR(_xll.FDS($B10,"FE_RATING(MEAN,TEXTONLY,0,NOW,,,'')"), "")} -> Overweight | AH10: =IFERROR(IF('3 — Weights'!$E$2=1,PERCENTRANK(I$4:I$91,I10),1-PERCENTRANK(I$4:I$91,I10))*100,"") -> 51.7 | AI10: =IFERROR(IF('3 — Weights'!$E$3=1,PERCENTRANK(J$4:J$91,J10),1-PERCENTRANK(J$4:J$91,J10))*100,"") -> 37.9 | AJ10: =IFERROR(IF('3 — Weights'!$E$4=1,PERCENTRANK(K$4:K$91,K10),1-PERCENTRANK(K$4:K$91,K10))*100,"") -> 57.4 | AK10: =IFERROR(IF('3 — Weights'!$E$5=1,PERCENTRANK(L$4:L$91,L10),1-PERCENTRANK(L$4:L$91,L10))*100,"") -> 39.2 | AL10: =IFERROR(IF('3 — Weights'!$E$6=1,PERCENTRANK(M$4:M$91,M10),1-PERCENTRANK(M$4:M$91,M10))*100,"") -> 82.9 | AM10: =IFERROR(IF('3 — Weights'!$E$7=1,PERCENTRANK(N$4:N$91,N10),1-PERCENTRANK(N$4:N$91,N10))*100,"") -> 41.5 | AN10: =IFERROR(IF('3 — Weights'!$E$8=1,PERCENTRANK(O$4:O$91,O10),1-PERCENTRANK(O$4:O$91,O10))*100,"") -> 45.7 | AO10: =IFERROR(IF('3 — Weights'!$E$9=1,PERCENTRANK(P$4:P$91,P10),1-PERCENTRANK(P$4:P$91,P10))*100,"") -> 76 | AP10: =IFERROR(IF('3 — Weights'!$E$10=1,PERCENTRANK(Q$4:Q$91,Q10),1-PERCENTRANK(Q$4:Q$91,Q10))*100,"") -> 60.7 | AQ10: =IFERROR(IF('3 — Weights'!$E$11=1,PERCENTRANK(R$4:R$91,R10),1-PERCENTRANK(R$4:R$91,R10))*100,"") -> 0 | AR10: =IFERROR(IF('3 — Weights'!$E$12=1,PERCENTRANK(S$4:S$91,S10),1-PERCENTRANK(S$4:S$91,S10))*100,"") -> 40.7 | AS10: =IFERROR(IF('3 — Weights'!$E$13=1,PERCENTRANK(T$4:T$91,T10),1-PERCENTRANK(T$4:T$91,T10))*100,"") -> 50 | AT10: =IFERROR(IF('3 — Weights'!$E$14=1,PERCENTRANK(U$4:U$91,U10),1-PERCENTRANK(U$4:U$91,U10))*100,"") -> 60.9 | AU10: =IFERROR(IF('3 — Weights'!$E$15=1,PERCENTRANK(V$4:V$91,V10),1-PERCENTRANK(V$4:V$91,V10))*100,"") -> 64.4 | AV10: =IFERROR(IF('3 — Weights'!$E$16=1,PERCENTRANK(W$4:W$91,W10),1-PERCENTRANK(W$4:W$91,W10))*100,"") -> 51.8 | AW10: =IFERROR(IF('3 — Weights'!$E$17=1,PERCENTRANK(X$4:X$91,X10),1-PERCENTRANK(X$4:X$91,X10))*100,"") -> 57.5 | AX10: =IFERROR(IF('3 — Weights'!$E$18=1,PERCENTRANK(Y$4:Y$91,Y10),1-PERCENTRANK(Y$4:Y$91,Y10))*100,"") -> 61.7 | AY10: =IFERROR(IF('3 — Weights'!$E$18=1,PERCENTRANK(Z$4:Z$91,Z10),1-PERCENTRANK(Z$4:Z$91,Z10))*100,"") -> 54.1 | AZ10: =IFERROR(IF('3 — Weights'!$E$18=1,PERCENTRANK(AA$4:AA$91,AA10),1-PERCENTRANK(AA$4:AA$91,AA10))*100,"") -> 57 | BA10: =IFERROR(IF('3 — Weights'!$E$21=1,PERCENTRANK(AB$4:AB$91,AB10),1-PERCENTRANK(AB$4:AB$91,AB10))*100,"") -> 52.8 | BB10: =IFERROR(IF('3 — Weights'!$E$22=1,PERCENTRANK(AC$4:AC$91,AC10),1-PERCENTRANK(AC$4:AC$91,AC10))*100,"") -> 43.6 | BC10: =IFERROR(IF('3 — Weights'!$E$23=1,PERCENTRANK(AD$4:AD$91,AD10),1-PERCENTRANK(AD$4:AD$91,AD10))*100,"") -> 33.4 | BD10: =IFERROR(IF('3 — Weights'!$E$24=1,PERCENTRANK(AE$4:AE$91,AE10),1-PERCENTRANK(AE$4:AE$91,AE10))*100,"") -> 36.8 | BE10: =IFERROR(IF('3 — Weights'!$E$25=1,PERCENTRANK(AF$4:AF$91,AF10),1-PERCENTRANK(AF$4:AF$91,AF10))*100,"") -> 49.5 | BF10: {=IFERROR(SUMPRODUCT(TRANSPOSE(AH10:BE10), [1]!Table2[Weight Claude]),"")} -> 60.77 | BG10: {=IFERROR(SUMPRODUCT(TRANSPOSE(AH10:BE10), [1]!Table2[Weight Cape IMC]),"")} -> 60.77
A11: =IFERROR(RANK(BG11,BG$4:BG$91),"") -> 8 | B11: NOW-US | C11: ServiceNow, Inc. | D11: {=IFERROR(_xll.FDS($B11,"FR_RBICS_NAME_CURR(""IND"")"), "")} -> General Enterprise Management Software | E11: {=PROPER(IFERROR(_xll.FDS($B11,"P_DCOUNTRY"), ""))} -> United States | F11: {=IFERROR(_xll.FDS($B11,"FCS_EV_DAILY(MV,NOW,,,USD,M)"), "")} -> 109870.41 | G11: {=IFERROR(_xll.FDS($B11,"AVG(P_VOLUME_FRQ(-1AM,NOW,D,,6))*P_PRICE_AVG(-1AM,NOW,,USD)"), "")} -> 2659.886 | H11: {=IFERROR(_xll.FDS($B11,"OS_SEC_FLT_PCT(0D,,MTD,SEC)")/100, "")} -> 0.993365 | I11: {=IFERROR(_xll.FDS($B11,"FE_ACTUAL(ACTUAL,SALES,ANN_ROLL,0,,,,'CURRENCY=USD')"), "")} -> 13278 | J11: {=IFERROR(_xll.FDS($B11,"FE_ACTUAL(ACTUAL,EPS,ANN_ROLL,0,,,,'CURRENCY=USD')"), "")} -> 3.51 | K11: {=IFERROR(_xll.FDS($B11,"POW(FE_ESTIMATE(SALES,MEAN,STMA,,NOW,,,'CURRENCY=USD')/FE_ESTIMATE(SALES,MEAN,LTMA,,NOW,,,'CURRENCY=USD'),0.5)-1"), "")} -> 0.19397127 | L11: {=IFERROR(_xll.FDS($B11,"POW(FE_ESTIMATE(EPS,MEAN,STMA,,NOW,,,'CURRENCY=USD')/FE_ESTIMATE(EPS,MEAN,LTMA,,NOW,,,'CURRENCY=USD'),0.5)-1"), "")} -> 0.20121788 | M11: {=IFERROR(_xll.FDS($B11,"FF_GROSS_MGN(LTM_R,0)"), "")} -> 77.534267 | N11: {=IFERROR(_xll.FDS($B11,"FF_EBITDA_OPER_MGN(LTM_R,0)"), "")} -> 19.596325 | O11: {=IFERROR(_xll.FDS($B11,"FF_NET_MGN(LTM_R,0)"), "")} -> 13.164633 | P11: {=IFERROR(_xll.FDS($B11,"FE_VALUATION(NETDEBT_EBITDA,MEAN,NTMA,,NOW,,,'')"), "")} -> -1.4570582 | Q11: {=IFERROR(_xll.FDS($B11,"FE_VALUATION(MCAP_FCF,MEAN,NTMA,,NOW,,,'')"), "")} -> 5.4903965 | R11: {=IFERROR(_xll.FDS($B11,"FE_VALUATION(DIV_YLD,MEAN,NTMA,,NOW,,,'')"), "")} -> 0 | S11: {=IFERROR(_xll.FDS($B11,"FE_VALUATION(ROE,MEAN,NTMA,,0,,,'')" ), "")} -> 27.540297 | T11: {=IFERROR(_xll.FDS($B11,"FE_VALUATION(ROIC,MEAN,NTMA,,0,,,'')" ), "")} -> 24.644463 | U11: {=IFERROR(((_xll.FDS($B11,"FE_ACTUAL(ACTUAL,SALES,ANN_ROLL,0,,,,'CURRENCY=USD')")/_xll.FDS($B11,"FE_ACTUAL(ACTUAL,SALES,ANN_ROLL,-1,,,,'CURRENCY=USD')")-1)*100)+(_xll.FDS($B11,"FE_VALUATION(EBITDA_MARGIN,MEAN,ANN_ROLL,0,NOW,,,'')") ), "")} -> 58.205637 | V11: {=IFERROR(_xll.FDS($B11,"FE_VALUATION(PE,MEAN,NTMA,,0,,,'')" ), "")} -> 23.757355 | W11: {=IFERROR(_xll.FDS($B11,"FE_VALUATION(P_SALESPS,MEAN,NTMA,,0,,,'')" ), "")} -> 6.5305815 | X11: {=IFERROR(_xll.FDS($B11,"FE_VALUATION(FFEV_SALES,MEAN,NTMA,,0,,,'')" ), "")} -> 6.2981114 | Y11: {=IFERROR(_xll.FDS($B11,"FE_VALUATION(FFEV_EBITDA,MEAN,NTMA,,0,,,'')" ), "")} -> 17.151566 | Z11: {=IFERROR(_xll.FDS($B11,"PERCENT_CHANGE(FE_VALUATION(PE,MEAN,NTMA,,0,,,''),MAX(FE_VALUATION(PE,MEAN,NTMA,,-1AY,0,,'')))")/100,"")} -> -0.59356938 | AA11: {=IFERROR(_xll.FDS($B11,"PERCENT_CHANGE(FE_VALUATION(FFEV_EBITDA,MEAN,NTMA,,0,,,''),MAX(FE_VALUATION(FFEV_EBITDA,MEAN,NTMA,,-1AY,0,,'')))")/100,"")} -> -0.60575563 | AB11: {=IFERROR(_xll.FDS($B11,"FG_PRICE(0,,,USD)/P_PRICE_HIGH(-1AY,0,USD,,,""PRICE"",""INTRA"")")-1, "")} -> -0.51536325 | AC11: {=IFERROR(_xll.FDS($B11,"RTP_PRICE_TARGET(USD)/FG_PRICE(0,,,USD)")-1, "")} -> 0.83132306 | AD11: {=IFERROR(_xll.FDS($B11,"FG_PRICE(0,,,USD)/FG_PRICE_MAVG(0,,,USD,50)")-1, "")} -> -0.22275533 | AE11: {=IFERROR(_xll.FDS($B11,"FG_PRICE(0,,,USD)/FG_PRICE_MAVG(0,,,USD,100)")-1, "")} -> -0.33323809 | AF11: {=IFERROR(_xll.FDS($B11,"FG_PRICE(0,,,USD)/FG_PRICE_MAVG(0,,,USD,200)")-1, "")} -> -0.40764628 | AG11: {=IFERROR(_xll.FDS($B11,"FE_RATING(MEAN,TEXTONLY,0,NOW,,,'')"), "")} -> Buy | AH11: =IFERROR(IF('3 — Weights'!$E$2=1,PERCENTRANK(I$4:I$91,I11),1-PERCENTRANK(I$4:I$91,I11))*100,"") -> 94.2 | AI11: =IFERROR(IF('3 — Weights'!$E$3=1,PERCENTRANK(J$4:J$91,J11),1-PERCENTRANK(J$4:J$91,J11))*100,"") -> 60.9 | AJ11: =IFERROR(IF('3 — Weights'!$E$4=1,PERCENTRANK(K$4:K$91,K11),1-PERCENTRANK(K$4:K$91,K11))*100,"") -> 81.6 | AK11: =IFERROR(IF('3 — Weights'!$E$5=1,PERCENTRANK(L$4:L$91,L11),1-PERCENTRANK(L$4:L$91,L11))*100,"") -> 66.6 | AL11: =IFERROR(IF('3 — Weights'!$E$6=1,PERCENTRANK(M$4:M$91,M11),1-PERCENTRANK(M$4:M$91,M11))*100,"") -> 69.5 | AM11: =IFERROR(IF('3 — Weights'!$E$7=1,PERCENTRANK(N$4:N$91,N11),1-PERCENTRANK(N$4:N$91,N11))*100,"") -> 50.6 | AN11: =IFERROR(IF('3 — Weights'!$E$8=1,PERCENTRANK(O$4:O$91,O11),1-PERCENTRANK(O$4:O$91,O11))*100,"") -> 59 | AO11: =IFERROR(IF('3 — Weights'!$E$9=1,PERCENTRANK(P$4:P$91,P11),1-PERCENTRANK(P$4:P$91,P11))*100,"") -> 57.9 | AP11: =IFERROR(IF('3 — Weights'!$E$10=1,PERCENTRANK(Q$4:Q$91,Q11),1-PERCENTRANK(Q$4:Q$91,Q11))*100,"") -> 55.9 | AQ11: =IFERROR(IF('3 — Weights'!$E$11=1,PERCENTRANK(R$4:R$91,R11),1-PERCENTRANK(R$4:R$91,R11))*100,"") -> 0 | AR11: =IFERROR(IF('3 — Weights'!$E$12=1,PERCENTRANK(S$4:S$91,S11),1-PERCENTRANK(S$4:S$91,S11))*100,"") -> 69.1 | AS11: =IFERROR(IF('3 — Weights'!$E$13=1,PERCENTRANK(T$4:T$91,T11),1-PERCENTRANK(T$4:T$91,T11))*100,"") -> 76.3 | AT11: =IFERROR(IF('3 — Weights'!$E$14=1,PERCENTRANK(U$4:U$91,U11),1-PERCENTRANK(U$4:U$91,U11))*100,"") -> 80.4 | AU11: =IFERROR(IF('3 — Weights'!$E$15=1,PERCENTRANK(V$4:V$91,V11),1-PERCENTRANK(V$4:V$91,V11))*100,"") -> 43.7 | AV11: =IFERROR(IF('3 — Weights'!$E$16=1,PERCENTRANK(W$4:W$91,W11),1-PERCENTRANK(W$4:W$91,W11))*100,"") -> 29.9 | AW11: =IFERROR(IF('3 — Weights'!$E$17=1,PERCENTRANK(X$4:X$91,X11),1-PERCENTRANK(X$4:X$91,X11))*100,"") -> 32.2 | AX11: =IFERROR(IF('3 — Weights'!$E$18=1,PERCENTRANK(Y$4:Y$91,Y11),1-PERCENTRANK(Y$4:Y$91,Y11))*100,"") -> 41.9 | AY11: =IFERROR(IF('3 — Weights'!$E$18=1,PERCENTRANK(Z$4:Z$91,Z11),1-PERCENTRANK(Z$4:Z$91,Z11))*100,"") -> 71.3 | AZ11: =IFERROR(IF('3 — Weights'!$E$18=1,PERCENTRANK(AA$4:AA$91,AA11),1-PERCENTRANK(AA$4:AA$91,AA11))*100,"") -> 78 | BA11: =IFERROR(IF('3 — Weights'!$E$21=1,PERCENTRANK(AB$4:AB$91,AB11),1-PERCENTRANK(AB$4:AB$91,AB11))*100,"") -> 24.1 | BB11: =IFERROR(IF('3 — Weights'!$E$22=1,PERCENTRANK(AC$4:AC$91,AC11),1-PERCENTRANK(AC$4:AC$91,AC11))*100,"") -> 82.7 | BC11: =IFERROR(IF('3 — Weights'!$E$23=1,PERCENTRANK(AD$4:AD$91,AD11),1-PERCENTRANK(AD$4:AD$91,AD11))*100,"") -> 70.2 | BD11: =IFERROR(IF('3 — Weights'!$E$24=1,PERCENTRANK(AE$4:AE$91,AE11),1-PERCENTRANK(AE$4:AE$91,AE11))*100,"") -> 82.8 | BE11: =IFERROR(IF('3 — Weights'!$E$25=1,PERCENTRANK(AF$4:AF$91,AF11),1-PERCENTRANK(AF$4:AF$91,AF11))*100,"") -> 84 | BF11: {=IFERROR(SUMPRODUCT(TRANSPOSE(AH11:BE11), [1]!Table2[Weight Claude]),"")} -> 60.795 | BG11: {=IFERROR(SUMPRODUCT(TRANSPOSE(AH11:BE11), [1]!Table2[Weight Cape IMC]),"")} -> 60.795
A12: =IFERROR(RANK(BG12,BG$4:BG$91),"") -> 10 | B12: TENB-US | C12: Tenable Holdings, Inc. | D12: {=IFERROR(_xll.FDS($B12,"FR_RBICS_NAME_CURR(""IND"")"), "")} -> Network Infrastructure Software | E12: {=PROPER(IFERROR(_xll.FDS($B12,"P_DCOUNTRY"), ""))} -> United States | F12: {=IFERROR(_xll.FDS($B12,"FCS_EV_DAILY(MV,NOW,,,USD,M)"), "")} -> 2365.7286 | G12: {=IFERROR(_xll.FDS($B12,"AVG(P_VOLUME_FRQ(-1AM,NOW,D,,6))*P_PRICE_AVG(-1AM,NOW,,USD)"), "")} -> 69.851512 | H12: {=IFERROR(_xll.FDS($B12,"OS_SEC_FLT_PCT(0D,,MTD,SEC)")/100, "")} -> 0.97952 | I12: {=IFERROR(_xll.FDS($B12,"FE_ACTUAL(ACTUAL,SALES,ANN_ROLL,0,,,,'CURRENCY=USD')"), "")} -> 999.405 | J12: {=IFERROR(_xll.FDS($B12,"FE_ACTUAL(ACTUAL,EPS,ANN_ROLL,0,,,,'CURRENCY=USD')"), "")} -> 1.59 | K12: {=IFERROR(_xll.FDS($B12,"POW(FE_ESTIMATE(SALES,MEAN,STMA,,NOW,,,'CURRENCY=USD')/FE_ESTIMATE(SALES,MEAN,LTMA,,NOW,,,'CURRENCY=USD'),0.5)-1"), "")} -> 0.071790185 | L12: {=IFERROR(_xll.FDS($B12,"POW(FE_ESTIMATE(EPS,MEAN,STMA,,NOW,,,'CURRENCY=USD')/FE_ESTIMATE(EPS,MEAN,LTMA,,NOW,,,'CURRENCY=USD'),0.5)-1"), "")} -> 0.14481693 | M12: {=IFERROR(_xll.FDS($B12,"FF_GROSS_MGN(LTM_R,0)"), "")} -> 81.955464 | N12: {=IFERROR(_xll.FDS($B12,"FF_EBITDA_OPER_MGN(LTM_R,0)"), "")} -> 4.3181693 | O12: {=IFERROR(_xll.FDS($B12,"FF_NET_MGN(LTM_R,0)"), "")} -> -3.6139503 | P12: {=IFERROR(_xll.FDS($B12,"FE_VALUATION(NETDEBT_EBITDA,MEAN,NTMA,,NOW,,,'')"), "")} -> -0.88758624 | Q12: {=IFERROR(_xll.FDS($B12,"FE_VALUATION(MCAP_FCF,MEAN,NTMA,,NOW,,,'')"), "")} -> 12.433495 | R12: {=IFERROR(_xll.FDS($B12,"FE_VALUATION(DIV_YLD,MEAN,NTMA,,NOW,,,'')"), "")} -> 0 | S12: {=IFERROR(_xll.FDS($B12,"FE_VALUATION(ROE,MEAN,NTMA,,0,,,'')" ), "")} -> 46.280136 | T12: {=IFERROR(_xll.FDS($B12,"FE_VALUATION(ROIC,MEAN,NTMA,,0,,,'')" ), "")} -> 26.39757 | U12: {=IFERROR(((_xll.FDS($B12,"FE_ACTUAL(ACTUAL,SALES,ANN_ROLL,0,,,,'CURRENCY=USD')")/_xll.FDS($B12,"FE_ACTUAL(ACTUAL,SALES,ANN_ROLL,-1,,,,'CURRENCY=USD')")-1)*100)+(_xll.FDS($B12,"FE_VALUATION(EBITDA_MARGIN,MEAN,ANN_ROLL,0,NOW,,,'')") ), "")} -> 34.589799 | V12: {=IFERROR(_xll.FDS($B12,"FE_VALUATION(PE,MEAN,NTMA,,0,,,'')" ), "")} -> 9.616364 | W12: {=IFERROR(_xll.FDS($B12,"FE_VALUATION(P_SALESPS,MEAN,NTMA,,0,,,'')" ), "")} -> 2.016584 | X12: {=IFERROR(_xll.FDS($B12,"FE_VALUATION(FFEV_SALES,MEAN,NTMA,,0,,,'')" ), "")} -> 2.0413074 | Y12: {=IFERROR(_xll.FDS($B12,"FE_VALUATION(FFEV_EBITDA,MEAN,NTMA,,0,,,'')" ), "")} -> 8.11703 | Z12: {=IFERROR(_xll.FDS($B12,"PERCENT_CHANGE(FE_VALUATION(PE,MEAN,NTMA,,0,,,''),MAX(FE_VALUATION(PE,MEAN,NTMA,,-1AY,0,,'')))")/100,"")} -> -0.61633428 | AA12: {=IFERROR(_xll.FDS($B12,"PERCENT_CHANGE(FE_VALUATION(FFEV_EBITDA,MEAN,NTMA,,0,,,''),MAX(FE_VALUATION(FFEV_EBITDA,MEAN,NTMA,,-1AY,0,,'')))")/100,"")} -> -0.56193107 | AB12: {=IFERROR(_xll.FDS($B12,"FG_PRICE(0,,,USD)/P_PRICE_HIGH(-1AY,0,USD,,,""PRICE"",""INTRA"")")-1, "")} -> -0.53252396 | AC12: {=IFERROR(_xll.FDS($B12,"RTP_PRICE_TARGET(USD)/FG_PRICE(0,,,USD)")-1, "")} -> 0.67972777 | AD12: {=IFERROR(_xll.FDS($B12,"FG_PRICE(0,,,USD)/FG_PRICE_MAVG(0,,,USD,50)")-1, "")} -> -0.19493279 | AE12: {=IFERROR(_xll.FDS($B12,"FG_PRICE(0,,,USD)/FG_PRICE_MAVG(0,,,USD,100)")-1, "")} -> -0.27975538 | AF12: {=IFERROR(_xll.FDS($B12,"FG_PRICE(0,,,USD)/FG_PRICE_MAVG(0,,,USD,200)")-1, "")} -> -0.3595445 | AG12: {=IFERROR(_xll.FDS($B12,"FE_RATING(MEAN,TEXTONLY,0,NOW,,,'')"), "")} -> Overweight | AH12: =IFERROR(IF('3 — Weights'!$E$2=1,PERCENTRANK(I$4:I$91,I12),1-PERCENTRANK(I$4:I$91,I12))*100,"") -> 32.1 | AI12: =IFERROR(IF('3 — Weights'!$E$3=1,PERCENTRANK(J$4:J$91,J12),1-PERCENTRANK(J$4:J$91,J12))*100,"") -> 41.3 | AJ12: =IFERROR(IF('3 — Weights'!$E$4=1,PERCENTRANK(K$4:K$91,K12),1-PERCENTRANK(K$4:K$91,K12))*100,"") -> 17.2 | AK12: =IFERROR(IF('3 — Weights'!$E$5=1,PERCENTRANK(L$4:L$91,L12),1-PERCENTRANK(L$4:L$91,L12))*100,"") -> 38 | AL12: =IFERROR(IF('3 — Weights'!$E$6=1,PERCENTRANK(M$4:M$91,M12),1-PERCENTRANK(M$4:M$91,M12))*100,"") -> 84.1 | AM12: =IFERROR(IF('3 — Weights'!$E$7=1,PERCENTRANK(N$4:N$91,N12),1-PERCENTRANK(N$4:N$91,N12))*100,"") -> 23.3 | AN12: =IFERROR(IF('3 — Weights'!$E$8=1,PERCENTRANK(O$4:O$91,O12),1-PERCENTRANK(O$4:O$91,O12))*100,"") -> 20.4 | AO12: =IFERROR(IF('3 — Weights'!$E$9=1,PERCENTRANK(P$4:P$91,P12),1-PERCENTRANK(P$4:P$91,P12))*100,"") -> 45.8 | AP12: =IFERROR(IF('3 — Weights'!$E$10=1,PERCENTRANK(Q$4:Q$91,Q12),1-PERCENTRANK(Q$4:Q$91,Q12))*100,"") -> 96.4 | AQ12: =IFERROR(IF('3 — Weights'!$E$11=1,PERCENTRANK(R$4:R$91,R12),1-PERCENTRANK(R$4:R$91,R12))*100,"") -> 0 | AR12: =IFERROR(IF('3 — Weights'!$E$12=1,PERCENTRANK(S$4:S$91,S12),1-PERCENTRANK(S$4:S$91,S12))*100,"") -> 86.4 | AS12: =IFERROR(IF('3 — Weights'!$E$13=1,PERCENTRANK(T$4:T$91,T12),1-PERCENTRANK(T$4:T$91,T12))*100,"") -> 81.9 | AT12: =IFERROR(IF('3 — Weights'!$E$14=1,PERCENTRANK(U$4:U$91,U12),1-PERCENTRANK(U$4:U$91,U12))*100,"") -> 23.1 | AU12: =IFERROR(IF('3 — Weights'!$E$15=1,PERCENTRANK(V$4:V$91,V12),1-PERCENTRANK(V$4:V$91,V12))*100,"") -> 95.5 | AV12: =IFERROR(IF('3 — Weights'!$E$16=1,PERCENTRANK(W$4:W$91,W12),1-PERCENTRANK(W$4:W$91,W12))*100,"") -> 94.3 | AW12: =IFERROR(IF('3 — Weights'!$E$17=1,PERCENTRANK(X$4:X$91,X12),1-PERCENTRANK(X$4:X$91,X12))*100,"") -> 96.6 | AX12: =IFERROR(IF('3 — Weights'!$E$18=1,PERCENTRANK(Y$4:Y$91,Y12),1-PERCENTRANK(Y$4:Y$91,Y12))*100,"") -> 89.6 | AY12: =IFERROR(IF('3 — Weights'!$E$18=1,PERCENTRANK(Z$4:Z$91,Z12),1-PERCENTRANK(Z$4:Z$91,Z12))*100,"") -> 80.5 | AZ12: =IFERROR(IF('3 — Weights'!$E$18=1,PERCENTRANK(AA$4:AA$91,AA12),1-PERCENTRANK(AA$4:AA$91,AA12))*100,"") -> 61.7 | BA12: =IFERROR(IF('3 — Weights'!$E$21=1,PERCENTRANK(AB$4:AB$91,AB12),1-PERCENTRANK(AB$4:AB$91,AB12))*100,"") -> 19.5 | BB12: =IFERROR(IF('3 — Weights'!$E$22=1,PERCENTRANK(AC$4:AC$91,AC12),1-PERCENTRANK(AC$4:AC$91,AC12))*100,"") -> 73.5 | BC12: =IFERROR(IF('3 — Weights'!$E$23=1,PERCENTRANK(AD$4:AD$91,AD12),1-PERCENTRANK(AD$4:AD$91,AD12))*100,"") -> 55.2 | BD12: =IFERROR(IF('3 — Weights'!$E$24=1,PERCENTRANK(AE$4:AE$91,AE12),1-PERCENTRANK(AE$4:AE$91,AE12))*100,"") -> 65.6 | BE12: =IFERROR(IF('3 — Weights'!$E$25=1,PERCENTRANK(AF$4:AF$91,AF12),1-PERCENTRANK(AF$4:AF$91,AF12))*100,"") -> 74.8 | BF12: {=IFERROR(SUMPRODUCT(TRANSPOSE(AH12:BE12), [1]!Table2[Weight Claude]),"")} -> 60.215 | BG12: {=IFERROR(SUMPRODUCT(TRANSPOSE(AH12:BE12), [1]!Table2[Weight Cape IMC]),"")} -> 60.215
A13: =IFERROR(RANK(BG13,BG$4:BG$91),"") -> 6 | B13: FICO-US | C13: Fair Isaac Corporation | D13: {=IFERROR(_xll.FDS($B13,"FR_RBICS_NAME_CURR(""IND"")"), "")} -> Other Business Administrative Services | E13: {=PROPER(IFERROR(_xll.FDS($B13,"P_DCOUNTRY"), ""))} -> United States | F13: {=IFERROR(_xll.FDS($B13,"FCS_EV_DAILY(MV,NOW,,,USD,M)"), "")} -> 29497.052 | G13: {=IFERROR(_xll.FDS($B13,"AVG(P_VOLUME_FRQ(-1AM,NOW,D,,6))*P_PRICE_AVG(-1AM,NOW,,USD)"), "")} -> 466.76972 | H13: {=IFERROR(_xll.FDS($B13,"OS_SEC_FLT_PCT(0D,,MTD,SEC)")/100, "")} -> 0.969984 | I13: {=IFERROR(_xll.FDS($B13,"FE_ACTUAL(ACTUAL,SALES,ANN_ROLL,0,,,,'CURRENCY=USD')"), "")} -> 1990.869 | J13: {=IFERROR(_xll.FDS($B13,"FE_ACTUAL(ACTUAL,EPS,ANN_ROLL,0,,,,'CURRENCY=USD')"), "")} -> 29.88 | K13: {=IFERROR(_xll.FDS($B13,"POW(FE_ESTIMATE(SALES,MEAN,STMA,,NOW,,,'CURRENCY=USD')/FE_ESTIMATE(SALES,MEAN,LTMA,,NOW,,,'CURRENCY=USD'),0.5)-1"), "")} -> 0.18327503 | L13: {=IFERROR(_xll.FDS($B13,"POW(FE_ESTIMATE(EPS,MEAN,STMA,,NOW,,,'CURRENCY=USD')/FE_ESTIMATE(EPS,MEAN,LTMA,,NOW,,,'CURRENCY=USD'),0.5)-1"), "")} -> 0.27673173 | M13: {=IFERROR(_xll.FDS($B13,"FF_GROSS_MGN(LTM_R,0)"), "")} -> 82.856907 | N13: {=IFERROR(_xll.FDS($B13,"FF_EBITDA_OPER_MGN(LTM_R,0)"), "")} -> 48.754011 | O13: {=IFERROR(_xll.FDS($B13,"FF_NET_MGN(LTM_R,0)"), "")} -> 31.887331 | P13: {=IFERROR(_xll.FDS($B13,"FE_VALUATION(NETDEBT_EBITDA,MEAN,NTMA,,NOW,,,'')"), "")} -> 1.762651 | Q13: {=IFERROR(_xll.FDS($B13,"FE_VALUATION(MCAP_FCF,MEAN,NTMA,,NOW,,,'')"), "")} -> 3.8997357 | R13: {=IFERROR(_xll.FDS($B13,"FE_VALUATION(DIV_YLD,MEAN,NTMA,,NOW,,,'')"), "")} -> 0 | S13: {=IFERROR(_xll.FDS($B13,"FE_VALUATION(ROE,MEAN,NTMA,,0,,,'')" ), "")} | T13: {=IFERROR(_xll.FDS($B13,"FE_VALUATION(ROIC,MEAN,NTMA,,0,,,'')" ), "")} -> 61.22264 | U13: {=IFERROR(((_xll.FDS($B13,"FE_ACTUAL(ACTUAL,SALES,ANN_ROLL,0,,,,'CURRENCY=USD')")/_xll.FDS($B13,"FE_ACTUAL(ACTUAL,SALES,ANN_ROLL,-1,,,,'CURRENCY=USD')")-1)*100)+(_xll.FDS($B13,"FE_VALUATION(EBITDA_MARGIN,MEAN,ANN_ROLL,0,NOW,,,'')") ), "")} -> 71.080796 | V13: {=IFERROR(_xll.FDS($B13,"FE_VALUATION(PE,MEAN,NTMA,,0,,,'')" ), "")} -> 26.600693 | W13: {=IFERROR(_xll.FDS($B13,"FE_VALUATION(P_SALESPS,MEAN,NTMA,,0,,,'')" ), "")} -> 10.938102 | X13: {=IFERROR(_xll.FDS($B13,"FE_VALUATION(FFEV_SALES,MEAN,NTMA,,0,,,'')" ), "")} -> 12.193437 | Y13: {=IFERROR(_xll.FDS($B13,"FE_VALUATION(FFEV_EBITDA,MEAN,NTMA,,0,,,'')" ), "")} -> 19.825321 | Z13: {=IFERROR(_xll.FDS($B13,"PERCENT_CHANGE(FE_VALUATION(PE,MEAN,NTMA,,0,,,''),MAX(FE_VALUATION(PE,MEAN,NTMA,,-1AY,0,,'')))")/100,"")} -> -0.59415404 | AA13: {=IFERROR(_xll.FDS($B13,"PERCENT_CHANGE(FE_VALUATION(FFEV_EBITDA,MEAN,NTMA,,0,,,''),MAX(FE_VALUATION(FFEV_EBITDA,MEAN,NTMA,,-1AY,0,,'')))")/100,"")} -> -0.56480038 | AB13: {=IFERROR(_xll.FDS($B13,"FG_PRICE(0,,,USD)/P_PRICE_HIGH(-1AY,0,USD,,,""PRICE"",""INTRA"")")-1, "")} -> -0.44641504 | AC13: {=IFERROR(_xll.FDS($B13,"RTP_PRICE_TARGET(USD)/FG_PRICE(0,,,USD)")-1, "")} -> 0.57985191 | AD13: {=IFERROR(_xll.FDS($B13,"FG_PRICE(0,,,USD)/FG_PRICE_MAVG(0,,,USD,50)")-1, "")} -> -0.21109585 | AE13: {=IFERROR(_xll.FDS($B13,"FG_PRICE(0,,,USD)/FG_PRICE_MAVG(0,,,USD,100)")-1, "")} -> -0.24813651 | AF13: {=IFERROR(_xll.FDS($B13,"FG_PRICE(0,,,USD)/FG_PRICE_MAVG(0,,,USD,200)")-1, "")} -> -0.24773573 | AG13: {=IFERROR(_xll.FDS($B13,"FE_RATING(MEAN,TEXTONLY,0,NOW,,,'')"), "")} -> Overweight | AH13: =IFERROR(IF('3 — Weights'!$E$2=1,PERCENTRANK(I$4:I$91,I13),1-PERCENTRANK(I$4:I$91,I13))*100,"") -> 56.3 | AI13: =IFERROR(IF('3 — Weights'!$E$3=1,PERCENTRANK(J$4:J$91,J13),1-PERCENTRANK(J$4:J$91,J13))*100,"") -> 100 | AJ13: =IFERROR(IF('3 — Weights'!$E$4=1,PERCENTRANK(K$4:K$91,K13),1-PERCENTRANK(K$4:K$91,K13))*100,"") -> 77 | AK13: =IFERROR(IF('3 — Weights'!$E$5=1,PERCENTRANK(L$4:L$91,L13),1-PERCENTRANK(L$4:L$91,L13))*100,"") -> 78.5 | AL13: =IFERROR(IF('3 — Weights'!$E$6=1,PERCENTRANK(M$4:M$91,M13),1-PERCENTRANK(M$4:M$91,M13))*100,"") -> 89 | AM13: =IFERROR(IF('3 — Weights'!$E$7=1,PERCENTRANK(N$4:N$91,N13),1-PERCENTRANK(N$4:N$91,N13))*100,"") -> 94.8 | AN13: =IFERROR(IF('3 — Weights'!$E$8=1,PERCENTRANK(O$4:O$91,O13),1-PERCENTRANK(O$4:O$91,O13))*100,"") -> 91.5 | AO13: =IFERROR(IF('3 — Weights'!$E$9=1,PERCENTRANK(P$4:P$91,P13),1-PERCENTRANK(P$4:P$91,P13))*100,"") -> 9.7 | AP13: =IFERROR(IF('3 — Weights'!$E$10=1,PERCENTRANK(Q$4:Q$91,Q13),1-PERCENTRANK(Q$4:Q$91,Q13))*100,"") -> 32.1 | AQ13: =IFERROR(IF('3 — Weights'!$E$11=1,PERCENTRANK(R$4:R$91,R13),1-PERCENTRANK(R$4:R$91,R13))*100,"") -> 0 | AR13: =IFERROR(IF('3 — Weights'!$E$12=1,PERCENTRANK(S$4:S$91,S13),1-PERCENTRANK(S$4:S$91,S13))*100,"") | AS13: =IFERROR(IF('3 — Weights'!$E$13=1,PERCENTRANK(T$4:T$91,T13),1-PERCENTRANK(T$4:T$91,T13))*100,"") -> 100 | AT13: =IFERROR(IF('3 — Weights'!$E$14=1,PERCENTRANK(U$4:U$91,U13),1-PERCENTRANK(U$4:U$91,U13))*100,"") -> 92.6 | AU13: =IFERROR(IF('3 — Weights'!$E$15=1,PERCENTRANK(V$4:V$91,V13),1-PERCENTRANK(V$4:V$91,V13))*100,"") -> 34.5 | AV13: =IFERROR(IF('3 — Weights'!$E$16=1,PERCENTRANK(W$4:W$91,W13),1-PERCENTRANK(W$4:W$91,W13))*100,"") -> 10.4 | AW13: =IFERROR(IF('3 — Weights'!$E$17=1,PERCENTRANK(X$4:X$91,X13),1-PERCENTRANK(X$4:X$91,X13))*100,"") -> 8.1 | AX13: =IFERROR(IF('3 — Weights'!$E$18=1,PERCENTRANK(Y$4:Y$91,Y13),1-PERCENTRANK(Y$4:Y$91,Y13))*100,"") -> 29.1 | AY13: =IFERROR(IF('3 — Weights'!$E$18=1,PERCENTRANK(Z$4:Z$91,Z13),1-PERCENTRANK(Z$4:Z$91,Z13))*100,"") -> 72.5 | AZ13: =IFERROR(IF('3 — Weights'!$E$18=1,PERCENTRANK(AA$4:AA$91,AA13),1-PERCENTRANK(AA$4:AA$91,AA13))*100,"") -> 62.8 | BA13: =IFERROR(IF('3 — Weights'!$E$21=1,PERCENTRANK(AB$4:AB$91,AB13),1-PERCENTRANK(AB$4:AB$91,AB13))*100,"") -> 48.2 | BB13: =IFERROR(IF('3 — Weights'!$E$22=1,PERCENTRANK(AC$4:AC$91,AC13),1-PERCENTRANK(AC$4:AC$91,AC13))*100,"") -> 54 | BC13: =IFERROR(IF('3 — Weights'!$E$23=1,PERCENTRANK(AD$4:AD$91,AD13),1-PERCENTRANK(AD$4:AD$91,AD13))*100,"") -> 64.4 | BD13: =IFERROR(IF('3 — Weights'!$E$24=1,PERCENTRANK(AE$4:AE$91,AE13),1-PERCENTRANK(AE$4:AE$91,AE13))*100,"") -> 47.2 | BE13: =IFERROR(IF('3 — Weights'!$E$25=1,PERCENTRANK(AF$4:AF$91,AF13),1-PERCENTRANK(AF$4:AF$91,AF13))*100,"") -> 38 | BF13: {=IFERROR(SUMPRODUCT(TRANSPOSE(AH13:BE13), [1]!Table2[Weight Claude]),"")} -> 61.82 | BG13: {=IFERROR(SUMPRODUCT(TRANSPOSE(AH13:BE13), [1]!Table2[Weight Cape IMC]),"")} -> 61.82
A14: =IFERROR(RANK(BG14,BG$4:BG$91),"") -> 11 | B14: DOCU-US | C14: DocuSign, Inc. | D14: {=IFERROR(_xll.FDS($B14,"FR_RBICS_NAME_CURR(""IND"")"), "")} -> Content Management Software | E14: {=PROPER(IFERROR(_xll.FDS($B14,"P_DCOUNTRY"), ""))} -> United States | F14: {=IFERROR(_xll.FDS($B14,"FCS_EV_DAILY(MV,NOW,,,USD,M)"), "")} -> 9687.6822 | G14: {=IFERROR(_xll.FDS($B14,"AVG(P_VOLUME_FRQ(-1AM,NOW,D,,6))*P_PRICE_AVG(-1AM,NOW,,USD)"), "")} -> 231.98859 | H14: {=IFERROR(_xll.FDS($B14,"OS_SEC_FLT_PCT(0D,,MTD,SEC)")/100, "")} -> 0.98991 | I14: {=IFERROR(_xll.FDS($B14,"FE_ACTUAL(ACTUAL,SALES,ANN_ROLL,0,,,,'CURRENCY=USD')"), "")} -> 2976.739 | J14: {=IFERROR(_xll.FDS($B14,"FE_ACTUAL(ACTUAL,EPS,ANN_ROLL,0,,,,'CURRENCY=USD')"), "")} -> 3.55 | K14: {=IFERROR(_xll.FDS($B14,"POW(FE_ESTIMATE(SALES,MEAN,STMA,,NOW,,,'CURRENCY=USD')/FE_ESTIMATE(SALES,MEAN,LTMA,,NOW,,,'CURRENCY=USD'),0.5)-1"), "")} -> 0.066447373 | L14: {=IFERROR(_xll.FDS($B14,"POW(FE_ESTIMATE(EPS,MEAN,STMA,,NOW,,,'CURRENCY=USD')/FE_ESTIMATE(EPS,MEAN,LTMA,,NOW,,,'CURRENCY=USD'),0.5)-1"), "")} -> 0.089046372 | M14: {=IFERROR(_xll.FDS($B14,"FF_GROSS_MGN(LTM_R,0)"), "")} -> 78.887249 | N14: {=IFERROR(_xll.FDS($B14,"FF_EBITDA_OPER_MGN(LTM_R,0)"), "")} -> 12.335369 | O14: {=IFERROR(_xll.FDS($B14,"FF_NET_MGN(LTM_R,0)"), "")} -> 9.5689565 | P14: {=IFERROR(_xll.FDS($B14,"FE_VALUATION(NETDEBT_EBITDA,MEAN,NTMA,,NOW,,,'')"), "")} -> -1.5786965 | Q14: {=IFERROR(_xll.FDS($B14,"FE_VALUATION(MCAP_FCF,MEAN,NTMA,,NOW,,,'')"), "")} -> 12.631592 | R14: {=IFERROR(_xll.FDS($B14,"FE_VALUATION(DIV_YLD,MEAN,NTMA,,NOW,,,'')"), "")} -> 0 | S14: {=IFERROR(_xll.FDS($B14,"FE_VALUATION(ROE,MEAN,NTMA,,0,,,'')" ), "")} -> 27.819582 | T14: {=IFERROR(_xll.FDS($B14,"FE_VALUATION(ROIC,MEAN,NTMA,,0,,,'')" ), "")} -> 26.94141 | U14: {=IFERROR(((_xll.FDS($B14,"FE_ACTUAL(ACTUAL,SALES,ANN_ROLL,0,,,,'CURRENCY=USD')")/_xll.FDS($B14,"FE_ACTUAL(ACTUAL,SALES,ANN_ROLL,-1,,,,'CURRENCY=USD')")-1)*100)+(_xll.FDS($B14,"FE_VALUATION(EBITDA_MARGIN,MEAN,ANN_ROLL,0,NOW,,,'')") ), "")} -> 38.710344 | V14: {=IFERROR(_xll.FDS($B14,"FE_VALUATION(PE,MEAN,NTMA,,0,,,'')" ), "")} -> 10.345724 | W14: {=IFERROR(_xll.FDS($B14,"FE_VALUATION(P_SALESPS,MEAN,NTMA,,0,,,'')" ), "")} -> 2.496073 | X14: {=IFERROR(_xll.FDS($B14,"FE_VALUATION(FFEV_SALES,MEAN,NTMA,,0,,,'')" ), "")} -> 2.3926935 | Y14: {=IFERROR(_xll.FDS($B14,"FE_VALUATION(FFEV_EBITDA,MEAN,NTMA,,0,,,'')" ), "")} -> 6.8800344 | Z14: {=IFERROR(_xll.FDS($B14,"PERCENT_CHANGE(FE_VALUATION(PE,MEAN,NTMA,,0,,,''),MAX(FE_VALUATION(PE,MEAN,NTMA,,-1AY,0,,'')))")/100,"")} -> -0.60247348 | AA14: {=IFERROR(_xll.FDS($B14,"PERCENT_CHANGE(FE_VALUATION(FFEV_EBITDA,MEAN,NTMA,,0,,,''),MAX(FE_VALUATION(FFEV_EBITDA,MEAN,NTMA,,-1AY,0,,'')))")/100,"")} -> -0.61694771 | AB14: {=IFERROR(_xll.FDS($B14,"FG_PRICE(0,,,USD)/P_PRICE_HIGH(-1AY,0,USD,,,""PRICE"",""INTRA"")")-1, "")} -> -0.54737509 | AC14: {=IFERROR(_xll.FDS($B14,"RTP_PRICE_TARGET(USD)/FG_PRICE(0,,,USD)")-1, "")} -> 0.84801634 | AD14: {=IFERROR(_xll.FDS($B14,"FG_PRICE(0,,,USD)/FG_PRICE_MAVG(0,,,USD,50)")-1, "")} -> -0.26504513 | AE14: {=IFERROR(_xll.FDS($B14,"FG_PRICE(0,,,USD)/FG_PRICE_MAVG(0,,,USD,100)")-1, "")} -> -0.32738418 | AF14: {=IFERROR(_xll.FDS($B14,"FG_PRICE(0,,,USD)/FG_PRICE_MAVG(0,,,USD,200)")-1, "")} -> -0.40009982 | AG14: {=IFERROR(_xll.FDS($B14,"FE_RATING(MEAN,TEXTONLY,0,NOW,,,'')"), "")} -> Overweight | AH14: =IFERROR(IF('3 — Weights'!$E$2=1,PERCENTRANK(I$4:I$91,I14),1-PERCENTRANK(I$4:I$91,I14))*100,"") -> 66.6 | AI14: =IFERROR(IF('3 — Weights'!$E$3=1,PERCENTRANK(J$4:J$91,J14),1-PERCENTRANK(J$4:J$91,J14))*100,"") -> 62 | AJ14: =IFERROR(IF('3 — Weights'!$E$4=1,PERCENTRANK(K$4:K$91,K14),1-PERCENTRANK(K$4:K$91,K14))*100,"") -> 12.6 | AK14: =IFERROR(IF('3 — Weights'!$E$5=1,PERCENTRANK(L$4:L$91,L14),1-PERCENTRANK(L$4:L$91,L14))*100,"") -> 13 | AL14: =IFERROR(IF('3 — Weights'!$E$6=1,PERCENTRANK(M$4:M$91,M14),1-PERCENTRANK(M$4:M$91,M14))*100,"") -> 76.8 | AM14: =IFERROR(IF('3 — Weights'!$E$7=1,PERCENTRANK(N$4:N$91,N14),1-PERCENTRANK(N$4:N$91,N14))*100,"") -> 37.6 | AN14: =IFERROR(IF('3 — Weights'!$E$8=1,PERCENTRANK(O$4:O$91,O14),1-PERCENTRANK(O$4:O$91,O14))*100,"") -> 46.9 | AO14: =IFERROR(IF('3 — Weights'!$E$9=1,PERCENTRANK(P$4:P$91,P14),1-PERCENTRANK(P$4:P$91,P14))*100,"") -> 59.1 | AP14: =IFERROR(IF('3 — Weights'!$E$10=1,PERCENTRANK(Q$4:Q$91,Q14),1-PERCENTRANK(Q$4:Q$91,Q14))*100,"") -> 97.6 | AQ14: =IFERROR(IF('3 — Weights'!$E$11=1,PERCENTRANK(R$4:R$91,R14),1-PERCENTRANK(R$4:R$91,R14))*100,"") -> 0 | AR14: =IFERROR(IF('3 — Weights'!$E$12=1,PERCENTRANK(S$4:S$91,S14),1-PERCENTRANK(S$4:S$91,S14))*100,"") -> 71.6 | AS14: =IFERROR(IF('3 — Weights'!$E$13=1,PERCENTRANK(T$4:T$91,T14),1-PERCENTRANK(T$4:T$91,T14))*100,"") -> 84.7 | AT14: =IFERROR(IF('3 — Weights'!$E$14=1,PERCENTRANK(U$4:U$91,U14),1-PERCENTRANK(U$4:U$91,U14))*100,"") -> 35.3 | AU14: =IFERROR(IF('3 — Weights'!$E$15=1,PERCENTRANK(V$4:V$91,V14),1-PERCENTRANK(V$4:V$91,V14))*100,"") -> 92 | AV14: =IFERROR(IF('3 — Weights'!$E$16=1,PERCENTRANK(W$4:W$91,W14),1-PERCENTRANK(W$4:W$91,W14))*100,"") -> 88.6 | AW14: =IFERROR(IF('3 — Weights'!$E$17=1,PERCENTRANK(X$4:X$91,X14),1-PERCENTRANK(X$4:X$91,X14))*100,"") -> 89.7 | AX14: =IFERROR(IF('3 — Weights'!$E$18=1,PERCENTRANK(Y$4:Y$91,Y14),1-PERCENTRANK(Y$4:Y$91,Y14))*100,"") -> 94.2 | AY14: =IFERROR(IF('3 — Weights'!$E$18=1,PERCENTRANK(Z$4:Z$91,Z14),1-PERCENTRANK(Z$4:Z$91,Z14))*100,"") -> 74.8 | AZ14: =IFERROR(IF('3 — Weights'!$E$18=1,PERCENTRANK(AA$4:AA$91,AA14),1-PERCENTRANK(AA$4:AA$91,AA14))*100,"") -> 79.1 | BA14: =IFERROR(IF('3 — Weights'!$E$21=1,PERCENTRANK(AB$4:AB$91,AB14),1-PERCENTRANK(AB$4:AB$91,AB14))*100,"") -> 13.7 | BB14: =IFERROR(IF('3 — Weights'!$E$22=1,PERCENTRANK(AC$4:AC$91,AC14),1-PERCENTRANK(AC$4:AC$91,AC14))*100,"") -> 83.9 | BC14: =IFERROR(IF('3 — Weights'!$E$23=1,PERCENTRANK(AD$4:AD$91,AD14),1-PERCENTRANK(AD$4:AD$91,AD14))*100,"") -> 79.4 | BD14: =IFERROR(IF('3 — Weights'!$E$24=1,PERCENTRANK(AE$4:AE$91,AE14),1-PERCENTRANK(AE$4:AE$91,AE14))*100,"") -> 80.5 | BE14: =IFERROR(IF('3 — Weights'!$E$25=1,PERCENTRANK(AF$4:AF$91,AF14),1-PERCENTRANK(AF$4:AF$91,AF14))*100,"") -> 82.8 | BF14: {=IFERROR(SUMPRODUCT(TRANSPOSE(AH14:BE14), [1]!Table2[Weight Claude]),"")} -> 60.135 | BG14: {=IFERROR(SUMPRODUCT(TRANSPOSE(AH14:BE14), [1]!Table2[Weight Cape IMC]),"")} -> 60.135
A15: =IFERROR(RANK(BG15,BG$4:BG$91),"") -> 14 | B15: CVLT-US | C15: Commvault Systems, Inc. | D15: {=IFERROR(_xll.FDS($B15,"FR_RBICS_NAME_CURR(""IND"")"), "")} -> Data Storage Infrastructure Software | E15: {=PROPER(IFERROR(_xll.FDS($B15,"P_DCOUNTRY"), ""))} -> United States | F15: {=IFERROR(_xll.FDS($B15,"FCS_EV_DAILY(MV,NOW,,,USD,M)"), "")} -> 4029.6919 | G15: {=IFERROR(_xll.FDS($B15,"AVG(P_VOLUME_FRQ(-1AM,NOW,D,,6))*P_PRICE_AVG(-1AM,NOW,,USD)"), "")} -> 119.70477 | H15: {=IFERROR(_xll.FDS($B15,"OS_SEC_FLT_PCT(0D,,MTD,SEC)")/100, "")} -> 0.985375 | I15: {=IFERROR(_xll.FDS($B15,"FE_ACTUAL(ACTUAL,SALES,ANN_ROLL,0,,,,'CURRENCY=USD')"), "")} -> 995.619 | J15: {=IFERROR(_xll.FDS($B15,"FE_ACTUAL(ACTUAL,EPS,ANN_ROLL,0,,,,'CURRENCY=USD')"), "")} -> 3.65 | K15: {=IFERROR(_xll.FDS($B15,"POW(FE_ESTIMATE(SALES,MEAN,STMA,,NOW,,,'CURRENCY=USD')/FE_ESTIMATE(SALES,MEAN,LTMA,,NOW,,,'CURRENCY=USD'),0.5)-1"), "")} -> 0.12304083 | L15: {=IFERROR(_xll.FDS($B15,"POW(FE_ESTIMATE(EPS,MEAN,STMA,,NOW,,,'CURRENCY=USD')/FE_ESTIMATE(EPS,MEAN,LTMA,,NOW,,,'CURRENCY=USD'),0.5)-1"), "")} -> 0.16265984 | M15: {=IFERROR(_xll.FDS($B15,"FF_GROSS_MGN(LTM_R,0)"), "")} -> 80.552676 | N15: {=IFERROR(_xll.FDS($B15,"FF_EBITDA_OPER_MGN(LTM_R,0)"), "")} -> 9.5521766 | O15: {=IFERROR(_xll.FDS($B15,"FF_NET_MGN(LTM_R,0)"), "")} -> 7.5848469 | P15: {=IFERROR(_xll.FDS($B15,"FE_VALUATION(NETDEBT_EBITDA,MEAN,NTMA,,NOW,,,'')"), "")} -> -1.3269114 | Q15: {=IFERROR(_xll.FDS($B15,"FE_VALUATION(MCAP_FCF,MEAN,NTMA,,NOW,,,'')"), "")} -> 6.67095 | R15: {=IFERROR(_xll.FDS($B15,"FE_VALUATION(DIV_YLD,MEAN,NTMA,,NOW,,,'')"), "")} | S15: {=IFERROR(_xll.FDS($B15,"FE_VALUATION(ROE,MEAN,NTMA,,0,,,'')" ), "")} -> 49.05138 | T15: {=IFERROR(_xll.FDS($B15,"FE_VALUATION(ROIC,MEAN,NTMA,,0,,,'')" ), "")} -> 19.34519 | U15: {=IFERROR(((_xll.FDS($B15,"FE_ACTUAL(ACTUAL,SALES,ANN_ROLL,0,,,,'CURRENCY=USD')")/_xll.FDS($B15,"FE_ACTUAL(ACTUAL,SALES,ANN_ROLL,-1,,,,'CURRENCY=USD')")-1)*100)+(_xll.FDS($B15,"FE_VALUATION(EBITDA_MARGIN,MEAN,ANN_ROLL,0,NOW,,,'')") ), "")} -> 40.619273 | V15: {=IFERROR(_xll.FDS($B15,"FE_VALUATION(PE,MEAN,NTMA,,0,,,'')" ), "")} -> 18.581944 | W15: {=IFERROR(_xll.FDS($B15,"FE_VALUATION(P_SALESPS,MEAN,NTMA,,0,,,'')" ), "")} -> 2.989787 | X15: {=IFERROR(_xll.FDS($B15,"FE_VALUATION(FFEV_SALES,MEAN,NTMA,,0,,,'')" ), "")} -> 2.9504561 | Y15: {=IFERROR(_xll.FDS($B15,"FE_VALUATION(FFEV_EBITDA,MEAN,NTMA,,0,,,'')" ), "")} -> 14.2976 | Z15: {=IFERROR(_xll.FDS($B15,"PERCENT_CHANGE(FE_VALUATION(PE,MEAN,NTMA,,0,,,''),MAX(FE_VALUATION(PE,MEAN,NTMA,,-1AY,0,,'')))")/100,"")} -> -0.58833688 | AA15: {=IFERROR(_xll.FDS($B15,"PERCENT_CHANGE(FE_VALUATION(FFEV_EBITDA,MEAN,NTMA,,0,,,''),MAX(FE_VALUATION(FFEV_EBITDA,MEAN,NTMA,,-1AY,0,,'')))")/100,"")} -> -0.56076659 | AB15: {=IFERROR(_xll.FDS($B15,"FG_PRICE(0,,,USD)/P_PRICE_HIGH(-1AY,0,USD,,,""PRICE"",""INTRA"")")-1, "")} -> -0.55905934 | AC15: {=IFERROR(_xll.FDS($B15,"RTP_PRICE_TARGET(USD)/FG_PRICE(0,,,USD)")-1, "")} -> 0.58586654 | AD15: {=IFERROR(_xll.FDS($B15,"FG_PRICE(0,,,USD)/FG_PRICE_MAVG(0,,,USD,50)")-1, "")} -> -0.19343225 | AE15: {=IFERROR(_xll.FDS($B15,"FG_PRICE(0,,,USD)/FG_PRICE_MAVG(0,,,USD,100)")-1, "")} -> -0.30538521 | AF15: {=IFERROR(_xll.FDS($B15,"FG_PRICE(0,,,USD)/FG_PRICE_MAVG(0,,,USD,200)")-1, "")} -> -0.42445517 | AG15: {=IFERROR(_xll.FDS($B15,"FE_RATING(MEAN,TEXTONLY,0,NOW,,,'')"), "")} -> Buy | AH15: =IFERROR(IF('3 — Weights'!$E$2=1,PERCENTRANK(I$4:I$91,I15),1-PERCENTRANK(I$4:I$91,I15))*100,"") -> 31 | AI15: =IFERROR(IF('3 — Weights'!$E$3=1,PERCENTRANK(J$4:J$91,J15),1-PERCENTRANK(J$4:J$91,J15))*100,"") -> 63.2 | AJ15: =IFERROR(IF('3 — Weights'!$E$4=1,PERCENTRANK(K$4:K$91,K15),1-PERCENTRANK(K$4:K$91,K15))*100,"") -> 44.8 | AK15: =IFERROR(IF('3 — Weights'!$E$5=1,PERCENTRANK(L$4:L$91,L15),1-PERCENTRANK(L$4:L$91,L15))*100,"") -> 50 | AL15: =IFERROR(IF('3 — Weights'!$E$6=1,PERCENTRANK(M$4:M$91,M15),1-PERCENTRANK(M$4:M$91,M15))*100,"") -> 81.7 | AM15: =IFERROR(IF('3 — Weights'!$E$7=1,PERCENTRANK(N$4:N$91,N15),1-PERCENTRANK(N$4:N$91,N15))*100,"") -> 33.7 | AN15: =IFERROR(IF('3 — Weights'!$E$8=1,PERCENTRANK(O$4:O$91,O15),1-PERCENTRANK(O$4:O$91,O15))*100,"") -> 42.1 | AO15: =IFERROR(IF('3 — Weights'!$E$9=1,PERCENTRANK(P$4:P$91,P15),1-PERCENTRANK(P$4:P$91,P15))*100,"") -> 54.3 | AP15: =IFERROR(IF('3 — Weights'!$E$10=1,PERCENTRANK(Q$4:Q$91,Q15),1-PERCENTRANK(Q$4:Q$91,Q15))*100,"") -> 67.8 | AQ15: =IFERROR(IF('3 — Weights'!$E$11=1,PERCENTRANK(R$4:R$91,R15),1-PERCENTRANK(R$4:R$91,R15))*100,"") | AR15: =IFERROR(IF('3 — Weights'!$E$12=1,PERCENTRANK(S$4:S$91,S15),1-PERCENTRANK(S$4:S$91,S15))*100,"") -> 90.1 | AS15: =IFERROR(IF('3 — Weights'!$E$13=1,PERCENTRANK(T$4:T$91,T15),1-PERCENTRANK(T$4:T$91,T15))*100,"") -> 58.3 | AT15: =IFERROR(IF('3 — Weights'!$E$14=1,PERCENTRANK(U$4:U$91,U15),1-PERCENTRANK(U$4:U$91,U15))*100,"") -> 39 | AU15: =IFERROR(IF('3 — Weights'!$E$15=1,PERCENTRANK(V$4:V$91,V15),1-PERCENTRANK(V$4:V$91,V15))*100,"") -> 61 | AV15: =IFERROR(IF('3 — Weights'!$E$16=1,PERCENTRANK(W$4:W$91,W15),1-PERCENTRANK(W$4:W$91,W15))*100,"") -> 77.1 | AW15: =IFERROR(IF('3 — Weights'!$E$17=1,PERCENTRANK(X$4:X$91,X15),1-PERCENTRANK(X$4:X$91,X15))*100,"") -> 78.2 | AX15: =IFERROR(IF('3 — Weights'!$E$18=1,PERCENTRANK(Y$4:Y$91,Y15),1-PERCENTRANK(Y$4:Y$91,Y15))*100,"") -> 53.5 | AY15: =IFERROR(IF('3 — Weights'!$E$18=1,PERCENTRANK(Z$4:Z$91,Z15),1-PERCENTRANK(Z$4:Z$91,Z15))*100,"") -> 66.7 | AZ15: =IFERROR(IF('3 — Weights'!$E$18=1,PERCENTRANK(AA$4:AA$91,AA15),1-PERCENTRANK(AA$4:AA$91,AA15))*100,"") -> 60.5 | BA15: =IFERROR(IF('3 — Weights'!$E$21=1,PERCENTRANK(AB$4:AB$91,AB15),1-PERCENTRANK(AB$4:AB$91,AB15))*100,"") -> 10.3 | BB15: =IFERROR(IF('3 — Weights'!$E$22=1,PERCENTRANK(AC$4:AC$91,AC15),1-PERCENTRANK(AC$4:AC$91,AC15))*100,"") -> 56.3 | BC15: =IFERROR(IF('3 — Weights'!$E$23=1,PERCENTRANK(AD$4:AD$91,AD15),1-PERCENTRANK(AD$4:AD$91,AD15))*100,"") -> 52.9 | BD15: =IFERROR(IF('3 — Weights'!$E$24=1,PERCENTRANK(AE$4:AE$91,AE15),1-PERCENTRANK(AE$4:AE$91,AE15))*100,"") -> 72.5 | BE15: =IFERROR(IF('3 — Weights'!$E$25=1,PERCENTRANK(AF$4:AF$91,AF15),1-PERCENTRANK(AF$4:AF$91,AF15))*100,"") -> 89.7 | BF15: {=IFERROR(SUMPRODUCT(TRANSPOSE(AH15:BE15), [1]!Table2[Weight Claude]),"")} -> 58.535 | BG15: {=IFERROR(SUMPRODUCT(TRANSPOSE(AH15:BE15), [1]!Table2[Weight Cape IMC]),"")} -> 58.535
... A91: =IFERROR(RANK(BG91,BG$4:BG$91),"") -> 88 | B91: 402340-KR | C91: SK Square Co., Ltd. | D91: {=IFERROR(_xll.FDS($B91,"FR_RBICS_NAME_CURR(""IND"")"), "")} -> Customer Relationship Management Software | E91: {=PROPER(IFERROR(_xll.FDS($B91,"P_DCOUNTRY"), ""))} -> South Korea | F91: {=IFERROR(_xll.FDS($B91,"FCS_EV_DAILY(MV,NOW,,,USD,M)"), "")} -> 56375.015 | G91: {=IFERROR(_xll.FDS($B91,"AVG(P_VOLUME_FRQ(-1AM,NOW,D,,6))*P_PRICE_AVG(-1AM,NOW,,USD)"), "")} -> 281.94959 | H91: {=IFERROR(_xll.FDS($B91,"OS_SEC_FLT_PCT(0D,,MTD,SEC)")/100, "")} -> 0.674351 | I91: {=IFERROR(_xll.FDS($B91,"FE_ACTUAL(ACTUAL,SALES,ANN_ROLL,0,,,,'CURRENCY=USD')"), "")} -> 1312.099 | J91: {=IFERROR(_xll.FDS($B91,"FE_ACTUAL(ACTUAL,EPS,ANN_ROLL,0,,,,'CURRENCY=USD')"), "")} -> 18.967724 | K91: {=IFERROR(_xll.FDS($B91,"POW(FE_ESTIMATE(SALES,MEAN,STMA,,NOW,,,'CURRENCY=USD')/FE_ESTIMATE(SALES,MEAN,LTMA,,NOW,,,'CURRENCY=USD'),0.5)-1"), "")} -> 0.0066641446 | L91: {=IFERROR(_xll.FDS($B91,"POW(FE_ESTIMATE(EPS,MEAN,STMA,,NOW,,,'CURRENCY=USD')/FE_ESTIMATE(EPS,MEAN,LTMA,,NOW,,,'CURRENCY=USD'),0.5)-1"), "")} -> 0.31495277 | M91: {=IFERROR(_xll.FDS($B91,"FF_GROSS_MGN(LTM_R,0)"), "")} | N91: {=IFERROR(_xll.FDS($B91,"FF_EBITDA_OPER_MGN(LTM_R,0)"), "")} | O91: {=IFERROR(_xll.FDS($B91,"FF_NET_MGN(LTM_R,0)"), "")} -> 624.74926 | P91: {=IFERROR(_xll.FDS($B91,"FE_VALUATION(NETDEBT_EBITDA,MEAN,NTMA,,NOW,,,'')"), "")} -> -0.41803536 | Q91: {=IFERROR(_xll.FDS($B91,"FE_VALUATION(MCAP_FCF,MEAN,NTMA,,NOW,,,'')"), "")} -> 0.034963045 | R91: {=IFERROR(_xll.FDS($B91,"FE_VALUATION(DIV_YLD,MEAN,NTMA,,NOW,,,'')"), "")} -> 0.05547204 | S91: {=IFERROR(_xll.FDS($B91,"FE_VALUATION(ROE,MEAN,NTMA,,0,,,'')" ), "")} -> 41.47687 | T91: {=IFERROR(_xll.FDS($B91,"FE_VALUATION(ROIC,MEAN,NTMA,,0,,,'')" ), "")} -> 36.306705 | U91: {=IFERROR(((_xll.FDS($B91,"FE_ACTUAL(ACTUAL,SALES,ANN_ROLL,0,,,,'CURRENCY=USD')")/_xll.FDS($B91,"FE_ACTUAL(ACTUAL,SALES,ANN_ROLL,-1,,,,'CURRENCY=USD')")-1)*100)+(_xll.FDS($B91,"FE_VALUATION(EBITDA_MARGIN,MEAN,ANN_ROLL,0,NOW,,,'')") ), "")} -> 187.4264 | V91: {=IFERROR(_xll.FDS($B91,"FE_VALUATION(PE,MEAN,NTMA,,0,,,'')" ), "")} -> 5.5869603 | W91: {=IFERROR(_xll.FDS($B91,"FE_VALUATION(P_SALESPS,MEAN,NTMA,,0,,,'')" ), "")} -> 49.160564 | X91: {=IFERROR(_xll.FDS($B91,"FE_VALUATION(FFEV_SALES,MEAN,NTMA,,0,,,'')" ), "")} -> 48.442513 | Y91: {=IFERROR(_xll.FDS($B91,"FE_VALUATION(FFEV_EBITDA,MEAN,NTMA,,0,,,'')" ), "")} -> 5.168069 | Z91: {=IFERROR(_xll.FDS($B91,"PERCENT_CHANGE(FE_VALUATION(PE,MEAN,NTMA,,0,,,''),MAX(FE_VALUATION(PE,MEAN,NTMA,,-1AY,0,,'')))")/100,"")} -> -0.15253576 | AA91: {=IFERROR(_xll.FDS($B91,"PERCENT_CHANGE(FE_VALUATION(FFEV_EBITDA,MEAN,NTMA,,0,,,''),MAX(FE_VALUATION(FFEV_EBITDA,MEAN,NTMA,,-1AY,0,,'')))")/100,"")} -> -0.26263856 | AB91: {=IFERROR(_xll.FDS($B91,"FG_PRICE(0,,,USD)/P_PRICE_HIGH(-1AY,0,USD,,,""PRICE"",""INTRA"")")-1, "")} -> -0.026813866 | AC91: {=IFERROR(_xll.FDS($B91,"RTP_PRICE_TARGET(USD)/FG_PRICE(0,,,USD)")-1, "")} -> 0.026472196 | AD91: {=IFERROR(_xll.FDS($B91,"FG_PRICE(0,,,USD)/FG_PRICE_MAVG(0,,,USD,50)")-1, "")} -> 0.42361583 | AE91: {=IFERROR(_xll.FDS($B91,"FG_PRICE(0,,,USD)/FG_PRICE_MAVG(0,,,USD,100)")-1, "")} -> 0.75494734 | AF91: {=IFERROR(_xll.FDS($B91,"FG_PRICE(0,,,USD)/FG_PRICE_MAVG(0,,,USD,200)")-1, "")} -> 1.4523003 | AG91: {=IFERROR(_xll.FDS($B91,"FE_RATING(MEAN,TEXTONLY,0,NOW,,,'')"), "")} -> Buy | AH91: =IFERROR(IF('3 — Weights'!$E$2=1,PERCENTRANK(I$4:I$91,I91),1-PERCENTRANK(I$4:I$91,I91))*100,"") -> 43.6 | AI91: =IFERROR(IF('3 — Weights'!$E$3=1,PERCENTRANK(J$4:J$91,J91),1-PERCENTRANK(J$4:J$91,J91))*100,"") -> 96.5 | AJ91: =IFERROR(IF('3 — Weights'!$E$4=1,PERCENTRANK(K$4:K$91,K91),1-PERCENTRANK(K$4:K$91,K91))*100,"") -> 0 | AK91: =IFERROR(IF('3 — Weights'!$E$5=1,PERCENTRANK(L$4:L$91,L91),1-PERCENTRANK(L$4:L$91,L91))*100,"") -> 88 | AL91: =IFERROR(IF('3 — Weights'!$E$6=1,PERCENTRANK(M$4:M$91,M91),1-PERCENTRANK(M$4:M$91,M91))*100,"") | AM91: =IFERROR(IF('3 — Weights'!$E$7=1,PERCENTRANK(N$4:N$91,N91),1-PERCENTRANK(N$4:N$91,N91))*100,"") | AN91: =IFERROR(IF('3 — Weights'!$E$8=1,PERCENTRANK(O$4:O$91,O91),1-PERCENTRANK(O$4:O$91,O91))*100,"") -> 100 | AO91: =IFERROR(IF('3 — Weights'!$E$9=1,PERCENTRANK(P$4:P$91,P91),1-PERCENTRANK(P$4:P$91,P91))*100,"") -> 33.8 | AP91: =IFERROR(IF('3 — Weights'!$E$10=1,PERCENTRANK(Q$4:Q$91,Q91),1-PERCENTRANK(Q$4:Q$91,Q91))*100,"") -> 3.5 | AQ91: =IFERROR(IF('3 — Weights'!$E$11=1,PERCENTRANK(R$4:R$91,R91),1-PERCENTRANK(R$4:R$91,R91))*100,"") -> 70.5 | AR91: =IFERROR(IF('3 — Weights'!$E$12=1,PERCENTRANK(S$4:S$91,S91),1-PERCENTRANK(S$4:S$91,S91))*100,"") -> 85.1 | AS91: =IFERROR(IF('3 — Weights'!$E$13=1,PERCENTRANK(T$4:T$91,T91),1-PERCENTRANK(T$4:T$91,T91))*100,"") -> 94.4 | AT91: =IFERROR(IF('3 — Weights'!$E$14=1,PERCENTRANK(U$4:U$91,U91),1-PERCENTRANK(U$4:U$91,U91))*100,"") -> 100 | AU91: =IFERROR(IF('3 — Weights'!$E$15=1,PERCENTRANK(V$4:V$91,V91),1-PERCENTRANK(V$4:V$91,V91))*100,"") -> 98.9 | AV91: =IFERROR(IF('3 — Weights'!$E$16=1,PERCENTRANK(W$4:W$91,W91),1-PERCENTRANK(W$4:W$91,W91))*100,"") -> 0 | AW91: =IFERROR(IF('3 — Weights'!$E$17=1,PERCENTRANK(X$4:X$91,X91),1-PERCENTRANK(X$4:X$91,X91))*100,"") -> 0 | AX91: =IFERROR(IF('3 — Weights'!$E$18=1,PERCENTRANK(Y$4:Y$91,Y91),1-PERCENTRANK(Y$4:Y$91,Y91))*100,"") -> 100 | AY91: =IFERROR(IF('3 — Weights'!$E$18=1,PERCENTRANK(Z$4:Z$91,Z91),1-PERCENTRANK(Z$4:Z$91,Z91))*100,"") -> 0 | AZ91: =IFERROR(IF('3 — Weights'!$E$18=1,PERCENTRANK(AA$4:AA$91,AA91),1-PERCENTRANK(AA$4:AA$91,AA91))*100,"") -> 7 | BA91: =IFERROR(IF('3 — Weights'!$E$21=1,PERCENTRANK(AB$4:AB$91,AB91),1-PERCENTRANK(AB$4:AB$91,AB91))*100,"") -> 100 | BB91: =IFERROR(IF('3 — Weights'!$E$22=1,PERCENTRANK(AC$4:AC$91,AC91),1-PERCENTRANK(AC$4:AC$91,AC91))*100,"") -> 1.1 | BC91: =IFERROR(IF('3 — Weights'!$E$23=1,PERCENTRANK(AD$4:AD$91,AD91),1-PERCENTRANK(AD$4:AD$91,AD91))*100,"") -> 0 | BD91: =IFERROR(IF('3 — Weights'!$E$24=1,PERCENTRANK(AE$4:AE$91,AE91),1-PERCENTRANK(AE$4:AE$91,AE91))*100,"") -> 0 | BE91: =IFERROR(IF('3 — Weights'!$E$25=1,PERCENTRANK(AF$4:AF$91,AF91),1-PERCENTRANK(AF$4:AF$91,AF91))*100,"") -> 0 | BF91: {=IFERROR(SUMPRODUCT(TRANSPOSE(AH91:BE91), [1]!Table2[Weight Claude]),"")} -> 17.11 | BG91: {=IFERROR(SUMPRODUCT(TRANSPOSE(AH91:BE91), [1]!Table2[Weight Cape IMC]),"")} -> 17.11

Sheet 3 — Weights
A1: Factor | B1: Metric | C1: Weight Cape IMC | D1: Weight Claude | E1: Direction | F1: Formula | G1: Description
A2: FUNDAMENTAL QUALITY | B2: REVENUE ANNUAL | E2: 1 | F2: =IFERROR(_xlfn.FORMULATEXT('2 — IC Universe Table'!I45), '2 — IC Universe Table'!I45) -> {=IFERROR(FDS($B45,"FE_ACTUAL(ACTUAL,SALES,ANN_ROLL,0,,,,'CURRENCY=USD')"), "")} | G2: The most recently reported annual sales figure in million USD.
A3: FUNDAMENTAL QUALITY | B3: EPS ANNUAL | E3: 1 | F3: =IFERROR(_xlfn.FORMULATEXT('2 — IC Universe Table'!J45), '2 — IC Universe Table'!J45) -> {=IFERROR(FDS($B45,"FE_ACTUAL(ACTUAL,EPS,ANN_ROLL,0,,,,'CURRENCY=USD')"), "")} | G3: The most recently reported annual earnings per share in USD.
A4: FUNDAMENTAL QUALITY | B4: SALES GROWTH 2Y FORWARD | C4: 0.15 | D4: 0.15 | E4: 1 | F4: =IFERROR(_xlfn.FORMULATEXT('2 — IC Universe Table'!K45), '2 — IC Universe Table'!K45) -> {=IFERROR(FDS($B45,"POW(FE_ESTIMATE(SALES,MEAN,STMA,,NOW,,,'CURRENCY=USD')/FE_ESTIMATE(SALES,MEAN,LTMA,,NOW,,,'CURRENCY=USD'),0.5)-1"), "")} | G4: Consensus analyst estimate for annualized revenue growth over the next two years.
A5: FUNDAMENTAL QUALITY | B5: EPS GROWTH 2Y FORWARD | E5: 1 | F5: =IFERROR(_xlfn.FORMULATEXT('2 — IC Universe Table'!L45), '2 — IC Universe Table'!L45) -> {=IFERROR(FDS($B45,"POW(FE_ESTIMATE(EPS,MEAN,STMA,,NOW,,,'CURRENCY=USD')/FE_ESTIMATE(EPS,MEAN,LTMA,,NOW,,,'CURRENCY=USD'),0.5)-1"), "")} | G5: Consensus analyst estimate for annualized earnings per share growth over the next two years.
A6: FUNDAMENTAL QUALITY | B6: GROSS MARGIN LTM | C6: 0.2 | D6: 0.2 | E6: 1 | F6: =IFERROR(_xlfn.FORMULATEXT('2 — IC Universe Table'!M45), '2 — IC Universe Table'!M45) -> {=IFERROR(FDS($B45,"FF_GROSS_MGN(LTM_R,0)"), "")} | G6: Gross profit as a percentage of revenue over the last twelve months, reflecting production and direct cost efficiency.
A7: FUNDAMENTAL QUALITY | B7: EBITDA MARGIN LTM | C7: 0.1 | D7: 0.1 | E7: 1 | F7: =IFERROR(_xlfn.FORMULATEXT('2 — IC Universe Table'!N45), '2 — IC Universe Table'!N45) -> {=IFERROR(FDS($B45,"FF_EBITDA_OPER_MGN(LTM_R,0)"), "")} | G7: EBITDA as a percentage of revenue over the last twelve months, reflecting core operating profitability before non-cash and financing items.
A8: FUNDAMENTAL QUALITY | B8: NET PROFIT MARGIN LTM | E8: 1 | F8: =IFERROR(_xlfn.FORMULATEXT('2 — IC Universe Table'!O45), '2 — IC Universe Table'!O45) -> {=IFERROR(FDS($B45,"FF_NET_MGN(LTM_R,0)"), "")} | G8: Net income as a percentage of revenue over the last twelve months, reflecting bottom-line profitability after all expenses.
A9: FUNDAMENTAL QUALITY | B9: NET DEBT/EBITDA NTM | C9: 0.05 | D9: 0.05 | E9: -1 | F9: =IFERROR(_xlfn.FORMULATEXT('2 — IC Universe Table'!P45), '2 — IC Universe Table'!P45) -> {=IFERROR(FDS($B45,"FE_VALUATION(NETDEBT_EBITDA,MEAN,NTMA,,NOW,,,'')"), "")} | G9: Ratio of net debt to forward-looking EBITDA, indicating how many years of earnings would be needed to pay off debt.
A10: FUNDAMENTAL QUALITY | B10: FCF YIELD NTM | C10: 0.1 | D10: 0.1 | E10: 1 | F10: =IFERROR(_xlfn.FORMULATEXT('2 — IC Universe Table'!Q45), '2 — IC Universe Table'!Q45) -> {=IFERROR(FDS($B45,"FE_VALUATION(MCAP_FCF,MEAN,NTMA,,NOW,,,'')"), "")} | G10: Next twelve months free cash flow divided by market capitalization, showing how much cash a company generates relative to its size.
A11: FUNDAMENTAL QUALITY | B11: DIVIDEND YIELD NTM | E11: 1 | F11: =IFERROR(_xlfn.FORMULATEXT('2 — IC Universe Table'!R45), '2 — IC Universe Table'!R45) -> {=IFERROR(FDS($B45,"FE_VALUATION(DIV_YLD,MEAN,NTMA,,NOW,,,'')"), "")} | G11: Expected annual dividend payments over the next twelve months as a percentage of the current share price.
A12: FUNDAMENTAL QUALITY | B12: ROE NTM | E12: 1 | F12: =IFERROR(_xlfn.FORMULATEXT('2 — IC Universe Table'!S45), '2 — IC Universe Table'!S45) -> {=IFERROR(FDS($B45,"FE_VALUATION(ROE,MEAN,NTMA,,0,,,'')" ), "")} | G12: Next twelve months net income divided by shareholders' equity, measuring how efficiently a company generates profit from equity.
A13: FUNDAMENTAL QUALITY | B13: ROIC NTM | C13: 0.05 | D13: 0.05 | E13: 1 | F13: =IFERROR(_xlfn.FORMULATEXT('2 — IC Universe Table'!T45), '2 — IC Universe Table'!T45) -> {=IFERROR(FDS($B45,"FE_VALUATION(ROIC,MEAN,NTMA,,0,,,'')" ), "")} | G13: Next twelve months net operating profit divided by invested capital, measuring how efficiently a company deploys all capital to generate returns.
A14: FUNDAMENTAL QUALITY | B14: RULE OF 40 | E14: 1 | F14: =IFERROR(_xlfn.FORMULATEXT('2 — IC Universe Table'!U45), '2 — IC Universe Table'!U45) -> {=IFERROR(((FDS($B45,"FE_ACTUAL(ACTUAL,SALES,ANN_ROLL,0,,,,'CURRENCY=USD')")/FDS($B45,"FE_ACTUAL(ACTUAL,SALES,ANN_ROLL,-1,,,,'CURRENCY=USD')")-1)*100)+(FDS($B45,"FE_VALUATION(EBITDA_MARGIN,MEAN,ANN_ROLL,0,NOW,,,'')") ), "")} | G14: The sum of a company's revenue growth rate and profit margin, a common health check for software and growth companies.
A15: VALUATION | B15: P/E NTM | E15: -1 | F15: =IFERROR(_xlfn.FORMULATEXT('2 — IC Universe Table'!V45), '2 — IC Universe Table'!V45) -> {=IFERROR(FDS($B45,"FE_VALUATION(PE,MEAN,NTMA,,0,,,'')" ), "")} | G15: Current share price divided by next twelve months consensus earnings per share, indicating how much investors are paying per dollar of forward earnings.
A16: VALUATION | B16: P/S NTM | E16: -1 | F16: =IFERROR(_xlfn.FORMULATEXT('2 — IC Universe Table'!W45), '2 — IC Universe Table'!W45) -> {=IFERROR(FDS($B45,"FE_VALUATION(P_SALESPS,MEAN,NTMA,,0,,,'')" ), "")} | G16: Current share price divided by next twelve months consensus revenue per share, indicating how much investors are paying per dollar of forward sales.
A17: VALUATION | B17: EV/SALES NTM | C17: 0.1 | D17: 0.1 | E17: -1 | F17: =IFERROR(_xlfn.FORMULATEXT('2 — IC Universe Table'!X45), '2 — IC Universe Table'!X45) -> {=IFERROR(FDS($B45,"FE_VALUATION(FFEV_SALES,MEAN,NTMA,,0,,,'')" ), "")} | G17: Enterprise value divided by next twelve months consensus revenue, a capital-structure-neutral measure of how the market values forward sales.
A18: VALUATION | B18: EV/EBITDA NTM | E18: -1 | F18: =IFERROR(_xlfn.FORMULATEXT('2 — IC Universe Table'!Y45), '2 — IC Universe Table'!Y45) -> {=IFERROR(FDS($B45,"FE_VALUATION(FFEV_EBITDA,MEAN,NTMA,,0,,,'')" ), "")} | G18: Enterprise value divided by next twelve months consensus EBITDA, a widely used valuation multiple that adjusts for differences in capital structure and depreciation.
A19: VALUATION | B19: P/E NTM CHANGE 52W | C19: 0.05 | D19: 0.05 | E19: -1 | F19: =IFERROR(_xlfn.FORMULATEXT('2 — IC Universe Table'!Z45), '2 — IC Universe Table'!Z45) -> {=IFERROR(FDS($B45,"PERCENT_CHANGE(FE_VALUATION(PE,MEAN,NTMA,,0,,,''),MAX(FE_VALUATION(PE,MEAN,NTMA,,-1AY,0,,'')))")/100,"")} | G19: The percentage change in the forward price-to-earnings multiple over the past 52 weeks, indicating whether the stock's valuation has expanded or contracted relative to a year ago.
A20: VALUATION | B20: EV/EBITDA NTM CHANGE 52W | C20: 0.05 | D20: 0.05 | E20: -1 | F20: =IFERROR(_xlfn.FORMULATEXT('2 — IC Universe Table'!AA45), '2 — IC Universe Table'!AA45) -> {=IFERROR(FDS($B45,"PERCENT_CHANGE(FE_VALUATION(FFEV_EBITDA,MEAN,NTMA,,0,,,''),MAX(FE_VALUATION(FFEV_EBITDA,MEAN,NTMA,,-1AY,0,,'')))")/100,"")} | G20: The percentage change in the forward EV/EBITDA multiple over the past 52 weeks, indicating whether the stock's enterprise valuation has expanded or contracted relative to a year ago.
A21: MOMENTUM | B21: PRICE VS 52W HIGH | C21: 0.1 | D21: 0.1 | E21: 1 | F21: =IFERROR(_xlfn.FORMULATEXT('2 — IC Universe Table'!AB45), '2 — IC Universe Table'!AB45) -> {=IFERROR(FDS($B45,"FG_PRICE(0,,,USD)/P_PRICE_HIGH(-1AY,0,USD,,,""PRICE"",""INTRA"")")-1, "")} | G21: The current share price expressed as a percentage of the stock's 52-week high, indicating proximity to its recent peak.
A22: MOMENTUM | B22: TGT PRICE UPSIDE | E22: 1 | F22: =IFERROR(_xlfn.FORMULATEXT('2 — IC Universe Table'!AC45), '2 — IC Universe Table'!AC45) -> {=IFERROR(FDS($B45,"RTP_PRICE_TARGET(USD)/FG_PRICE(0,,,USD)")-1, "")} | G22: The percentage difference between the consensus analyst target price and the current share price, reflecting implied upside potential.
A23: MOMENTUM | B23: PRICE VS 50 DAY MA | E23: -1 | F23: =IFERROR(_xlfn.FORMULATEXT('2 — IC Universe Table'!AD45), '2 — IC Universe Table'!AD45) -> {=IFERROR(FDS($B45,"FG_PRICE(0,,,USD)/FG_PRICE_MAVG(0,,,USD,50)")-1, "")} | G23: The current share price as a percentage above or below its 50-day moving average, a short-term momentum and trend indicator.
A24: MOMENTUM | B24: PRICE VS 100 DAY MA | E24: -1 | F24: =IFERROR(_xlfn.FORMULATEXT('2 — IC Universe Table'!AE45), '2 — IC Universe Table'!AE45) -> {=IFERROR(FDS($B45,"FG_PRICE(0,,,USD)/FG_PRICE_MAVG(0,,,USD,100)")-1, "")} | G24: The current share price as a percentage above or below its 100-day moving average, a medium-term momentum and trend indicator.
A25: MOMENTUM | B25: PRICE VS 200 DAY MA | C25: 0.05 | D25: 0.05 | E25: -1 | F25: =IFERROR(_xlfn.FORMULATEXT('2 — IC Universe Table'!AF45), '2 — IC Universe Table'!AF45) -> {=IFERROR(FDS($B45,"FG_PRICE(0,,,USD)/FG_PRICE_MAVG(0,,,USD,200)")-1, "")} | G25: The current share price as a percentage above or below its 200-day moving average, a long-term momentum and trend indicator.
B26: TOTAL | C26: =SUM(C2:C25) -> 1 | D26: =SUM(D2:D25) -> 1

Sheet 4 — Geography & Industry
A1: GEOGRAPHY EXPOSURE | Y1: INDUSTRY EXPOSURE
A2: Identifier | B2: Name | C2: Top 3 COUNTRIES | H2: % REVENUE | M2: TOP 5 COUNTRIES | R2: % REVENUE | Y2: Identifier | Z2: Name | AA2: Top 5 INDUSTRIES | AF2: % Revenue | AK2: TOP 5 INDUSTRIES | AP2: % REVENUE
A3: ='2 — IC Universe Table'!B4 -> HUBS-US | B3: ='2 — IC Universe Table'!C4 -> HubSpot, Inc. | C3: {=TRANSPOSE(_xll.FDS(A3,"TRANSPOSE(TRANSPOSE(FF_GEOREV_COUNTRY_REV_PCT_MATRIX)[1:1])[0:4]"))} -> United States | D3: United States | E3: United States | F3: United States | G3: United States | H3: {=TRANSPOSE(_xll.FDS(A3,"TRANSPOSE(TRANSPOSE(FF_GEOREV_COUNTRY_REV_PCT_MATRIX)[2:2])[0:4]"))} -> 57.398004 | I3: 16.143119 | J3: 3.520623 | K3: 2.848654 | L3: 2.502672 | M3: =IFERROR(C3, "") -> United States | N3: =IFERROR(D3, "") -> United States | O3: =IFERROR(E3, "") -> United States | P3: =IFERROR(F3, "") -> United States | Q3: =IFERROR(G3, "") -> United States | R3: =IFERROR(ROUND(VALUE(H3), 0)/100, "") -> 0.57 | S3: =IFERROR(ROUND(VALUE(I3), 0)/100, "") -> 0.16 | T3: =IFERROR(ROUND(VALUE(J3), 0)/100, "") -> 0.04 | U3: =IFERROR(ROUND(VALUE(K3), 0)/100, "") -> 0.03 | V3: =IFERROR(ROUND(VALUE(L3), 0)/100, "") -> 0.03 | Y3: ='2 — IC Universe Table'!B4 -> HUBS-US | Z3: ='2 — IC Universe Table'!C4 -> HubSpot, Inc. | AA3: {=TRANSPOSE(_xll.FDS(Y3,"String_array Name= TRANSPOSE(TRANSPOSE(SA_SUBARRAY(FR_RBICS_REV_MATRIX_CURRENT(""IND""),1,9))[13:13]);float_array pct=TRANSPOSE(TRANSPOSE(SA_SUBARRAY(FR_RBICS_REV_MATRIX_CURRENT(""IND""),1,9))[14:14]);SORT_INDIRECT(Name,pct,2)[0:4]"))} -> Customer Relationship Management Software | AB3: Customer Relationship Management Software | AC3: Customer Relationship Management Software | AD3: Customer Relationship Management Software | AE3: Customer Relationship Management Software | AF3: {=TRANSPOSE(_xll.FDS(Y3,"String_array Name= TRANSPOSE(TRANSPOSE(SA_SUBARRAY(FR_RBICS_REV_MATRIX_CURRENT(""IND""),1,9))[14:14]);float_array pct=TRANSPOSE(TRANSPOSE(SA_SUBARRAY(FR_RBICS_REV_MATRIX_CURRENT(""IND""),1,9))[14:14]);SORT_INDIRECT(Name,pct,2)[0:4]"))} -> 100.000000 | AG3: 100.000000 | AH3: 100.000000 | AI3: 100.000000 | AJ3: 100.000000 | AK3: =IFERROR(AA3, "") -> Customer Relationship Management Software | AL3: =IFERROR(AB3, "") -> Customer Relationship Management Software | AM3: =IFERROR(AC3, "") -> Customer Relationship Management Software | AN3: =IFERROR(AD3, "") -> Customer Relationship Management Software | AO3: =IFERROR(AE3, "") -> Customer Relationship Management Software | AP3: =IFERROR(ROUND(VALUE(AF3), 0)/100, "") -> 1 | AQ3: =IFERROR(ROUND(VALUE(AG3), 0)/100, "") -> 1 | AR3: =IFERROR(ROUND(VALUE(AH3), 0)/100, "") -> 1 | AS3: =IFERROR(ROUND(VALUE(AI3), 0)/100, "") -> 1 | AT3: =IFERROR(ROUND(VALUE(AJ3), 0)/100, "") -> 1
A4: ='2 — IC Universe Table'!B5 -> NTNX-US | B4: ='2 — IC Universe Table'!C5 -> Nutanix, Inc. | C4: {=TRANSPOSE(_xll.FDS(A4,"TRANSPOSE(TRANSPOSE(FF_GEOREV_COUNTRY_REV_PCT_MATRIX)[1:1])[0:4]"))} -> United States | D4: Mainland China | E4: India | F4: Japan | G4: France | H4: {=TRANSPOSE(_xll.FDS(A4,"TRANSPOSE(TRANSPOSE(FF_GEOREV_COUNTRY_REV_PCT_MATRIX)[2:2])[0:4]"))} -> 55.532212 | I4: 2.861865 | J4: 2.416489 | K4: 2.416151 | L4: 2.357529 | M4: =IFERROR(C4, "") -> United States | N4: =IFERROR(D4, "") -> Mainland China | O4: =IFERROR(E4, "") -> India | P4: =IFERROR(F4, "") -> Japan | Q4: =IFERROR(G4, "") -> France | R4: =IFERROR(ROUND(VALUE(H4), 0)/100, "") -> 0.56 | S4: =IFERROR(ROUND(VALUE(I4), 0)/100, "") -> 0.03 | T4: =IFERROR(ROUND(VALUE(J4), 0)/100, "") -> 0.02 | U4: =IFERROR(ROUND(VALUE(K4), 0)/100, "") -> 0.02 | V4: =IFERROR(ROUND(VALUE(L4), 0)/100, "") -> 0.02 | Y4: ='2 — IC Universe Table'!B5 -> NTNX-US | Z4: ='2 — IC Universe Table'!C5 -> Nutanix, Inc. | AA4: {=TRANSPOSE(_xll.FDS(Y4,"String_array Name= TRANSPOSE(TRANSPOSE(SA_SUBARRAY(FR_RBICS_REV_MATRIX_CURRENT(""IND""),1,9))[13:13]);float_array pct=TRANSPOSE(TRANSPOSE(SA_SUBARRAY(FR_RBICS_REV_MATRIX_CURRENT(""IND""),1,9))[14:14]);SORT_INDIRECT(Name,pct,2)[0:4]"))} -> Data Storage Infrastructure Software | AB4: #N/A | AC4: #N/A | AD4: #N/A | AE4: #N/A | AF4: {=TRANSPOSE(_xll.FDS(Y4,"String_array Name= TRANSPOSE(TRANSPOSE(SA_SUBARRAY(FR_RBICS_REV_MATRIX_CURRENT(""IND""),1,9))[14:14]);float_array pct=TRANSPOSE(TRANSPOSE(SA_SUBARRAY(FR_RBICS_REV_MATRIX_CURRENT(""IND""),1,9))[14:14]);SORT_INDIRECT(Name,pct,2)[0:4]"))} -> 100.000000 | AG4: #N/A | AH4: #N/A | AI4: #N/A | AJ4: #N/A | AK4: =IFERROR(AA4, "") -> Data Storage Infrastructure Software | AL4: =IFERROR(AB4, "") | AM4: =IFERROR(AC4, "") | AN4: =IFERROR(AD4, "") | AO4: =IFERROR(AE4, "") | AP4: =IFERROR(ROUND(VALUE(AF4), 0)/100, "") -> 1 | AQ4: =IFERROR(ROUND(VALUE(AG4), 0)/100, "") | AR4: =IFERROR(ROUND(VALUE(AH4), 0)/100, "") | AS4: =IFERROR(ROUND(VALUE(AI4), 0)/100, "") | AT4: =IFERROR(ROUND(VALUE(AJ4), 0)/100, "")
A5: ='2 — IC Universe Table'!B6 -> APP-US | B5: ='2 — IC Universe Table'!C6 -> AppLovin Corp. Class A | C5: {=TRANSPOSE(_xll.FDS(A5,"TRANSPOSE(TRANSPOSE(FF_GEOREV_COUNTRY_REV_PCT_MATRIX)[1:1])[0:4]"))} -> United States | D5: Mainland China | E5: Germany | F5: India | G5: Japan | H5: {=TRANSPOSE(_xll.FDS(A5,"TRANSPOSE(TRANSPOSE(FF_GEOREV_COUNTRY_REV_PCT_MATRIX)[2:2])[0:4]"))} -> 51.585367 | I5: 11.150833 | J5: 2.751109 | K5: 2.427696 | L5: 2.427356 | M5: =IFERROR(C5, "") -> United States | N5: =IFERROR(D5, "") -> Mainland China | O5: =IFERROR(E5, "") -> Germany | P5: =IFERROR(F5, "") -> India | Q5: =IFERROR(G5, "") -> Japan | R5: =IFERROR(ROUND(VALUE(H5), 0)/100, "") -> 0.52 | S5: =IFERROR(ROUND(VALUE(I5), 0)/100, "") -> 0.11 | T5: =IFERROR(ROUND(VALUE(J5), 0)/100, "") -> 0.03 | U5: =IFERROR(ROUND(VALUE(K5), 0)/100, "") -> 0.02 | V5: =IFERROR(ROUND(VALUE(L5), 0)/100, "") -> 0.02 | Y5: ='2 — IC Universe Table'!B6 -> APP-US | Z5: ='2 — IC Universe Table'!C6 -> AppLovin Corp. Class A | AA5: {=TRANSPOSE(_xll.FDS(Y5,"String_array Name= TRANSPOSE(TRANSPOSE(SA_SUBARRAY(FR_RBICS_REV_MATRIX_CURRENT(""IND""),1,9))[13:13]);float_array pct=TRANSPOSE(TRANSPOSE(SA_SUBARRAY(FR_RBICS_REV_MATRIX_CURRENT(""IND""),1,9))[14:14]);SORT_INDIRECT(Name,pct,2)[0:4]"))} -> Customer Relationship Management Software | AB5: Handheld/Smart Phone Games Software | AC5: #N/A | AD5: #N/A | AE5: #N/A | AF5: {=TRANSPOSE(_xll.FDS(Y5,"String_array Name= TRANSPOSE(TRANSPOSE(SA_SUBARRAY(FR_RBICS_REV_MATRIX_CURRENT(""IND""),1,9))[14:14]);float_array pct=TRANSPOSE(TRANSPOSE(SA_SUBARRAY(FR_RBICS_REV_MATRIX_CURRENT(""IND""),1,9))[14:14]);SORT_INDIRECT(Name,pct,2)[0:4]"))} -> 68.462268 | AG5: 31.537732 | AH5: #N/A | AI5: #N/A | AJ5: #N/A | AK5: =IFERROR(AA5, "") -> Customer Relationship Management Software | AL5: =IFERROR(AB5, "") -> Handheld/Smart Phone Games Software | AM5: =IFERROR(AC5, "") | AN5: =IFERROR(AD5, "") | AO5: =IFERROR(AE5, "") | AP5: =IFERROR(ROUND(VALUE(AF5), 0)/100, "") -> 0.68 | AQ5: =IFERROR(ROUND(VALUE(AG5), 0)/100, "") -> 0.32 | AR5: =IFERROR(ROUND(VALUE(AH5), 0)/100, "") | AS5: =IFERROR(ROUND(VALUE(AI5), 0)/100, "") | AT5: =IFERROR(ROUND(VALUE(AJ5), 0)/100, "")
A6: ='2 — IC Universe Table'!B7 -> QLYS-US | B6: ='2 — IC Universe Table'!C7 -> Qualys, Inc. | C6: {=TRANSPOSE(_xll.FDS(A6,"TRANSPOSE(TRANSPOSE(FF_GEOREV_COUNTRY_REV_PCT_MATRIX)[1:1])[0:4]"))} -> United States | D6: Mainland China | E6: Germany | F6: India | G6: Japan | H6: {=TRANSPOSE(_xll.FDS(A6,"TRANSPOSE(TRANSPOSE(FF_GEOREV_COUNTRY_REV_PCT_MATRIX)[2:2])[0:4]"))} -> 56.412479 | I6: 10.039055 | J6: 2.476814 | K6: 2.185646 | L6: 2.18534 | M6: =IFERROR(C6, "") -> United States | N6: =IFERROR(D6, "") -> Mainland China | O6: =IFERROR(E6, "") -> Germany | P6: =IFERROR(F6, "") -> India | Q6: =IFERROR(G6, "") -> Japan | R6: =IFERROR(ROUND(VALUE(H6), 0)/100, "") -> 0.56 | S6: =IFERROR(ROUND(VALUE(I6), 0)/100, "") -> 0.1 | T6: =IFERROR(ROUND(VALUE(J6), 0)/100, "") -> 0.02 | U6: =IFERROR(ROUND(VALUE(K6), 0)/100, "") -> 0.02 | V6: =IFERROR(ROUND(VALUE(L6), 0)/100, "") -> 0.02 | Y6: ='2 — IC Universe Table'!B7 -> QLYS-US | Z6: ='2 — IC Universe Table'!C7 -> Qualys, Inc. | AA6: {=TRANSPOSE(_xll.FDS(Y6,"String_array Name= TRANSPOSE(TRANSPOSE(SA_SUBARRAY(FR_RBICS_REV_MATRIX_CURRENT(""IND""),1,9))[13:13]);float_array pct=TRANSPOSE(TRANSPOSE(SA_SUBARRAY(FR_RBICS_REV_MATRIX_CURRENT(""IND""),1,9))[14:14]);SORT_INDIRECT(Name,pct,2)[0:4]"))} -> Network Infrastructure Software | AB6: #N/A | AC6: #N/A | AD6: #N/A | AE6: #N/A | AF6: {=TRANSPOSE(_xll.FDS(Y6,"String_array Name= TRANSPOSE(TRANSPOSE(SA_SUBARRAY(FR_RBICS_REV_MATRIX_CURRENT(""IND""),1,9))[14:14]);float_array pct=TRANSPOSE(TRANSPOSE(SA_SUBARRAY(FR_RBICS_REV_MATRIX_CURRENT(""IND""),1,9))[14:14]);SORT_INDIRECT(Name,pct,2)[0:4]"))} -> 100.000000 | AG6: #N/A | AH6: #N/A | AI6: #N/A | AJ6: #N/A | AK6: =IFERROR(AA6, "") -> Network Infrastructure Software | AL6: =IFERROR(AB6, "") | AM6: =IFERROR(AC6, "") | AN6: =IFERROR(AD6, "") | AO6: =IFERROR(AE6, "") | AP6: =IFERROR(ROUND(VALUE(AF6), 0)/100, "") -> 1 | AQ6: =IFERROR(ROUND(VALUE(AG6), 0)/100, "") | AR6: =IFERROR(ROUND(VALUE(AH6), 0)/100, "") | AS6: =IFERROR(ROUND(VALUE(AI6), 0)/100, "") | AT6: =IFERROR(ROUND(VALUE(AJ6), 0)/100, "")
A7: ='2 — IC Universe Table'!B8 -> WK-US | B7: ='2 — IC Universe Table'!C8 -> Workiva Inc. | C7: {=TRANSPOSE(_xll.FDS(A7,"TRANSPOSE(TRANSPOSE(FF_GEOREV_COUNTRY_REV_PCT_MATRIX)[1:1])[0:4]"))} -> United States | D7: Mainland China | E7: Germany | F7: India | G7: Japan | H7: {=TRANSPOSE(_xll.FDS(A7,"TRANSPOSE(TRANSPOSE(FF_GEOREV_COUNTRY_REV_PCT_MATRIX)[2:2])[0:4]"))} -> 73.301205 | I7: 6.149253 | J7: 1.51713 | K7: 1.33878 | L7: 1.338593 | M7: =IFERROR(C7, "") -> United States | N7: =IFERROR(D7, "") -> Mainland China | O7: =IFERROR(E7, "") -> Germany | P7: =IFERROR(F7, "") -> India | Q7: =IFERROR(G7, "") -> Japan | R7: =IFERROR(ROUND(VALUE(H7), 0)/100, "") -> 0.73 | S7: =IFERROR(ROUND(VALUE(I7), 0)/100, "") -> 0.06 | T7: =IFERROR(ROUND(VALUE(J7), 0)/100, "") -> 0.02 | U7: =IFERROR(ROUND(VALUE(K7), 0)/100, "") -> 0.01 | V7: =IFERROR(ROUND(VALUE(L7), 0)/100, "") -> 0.01 | Y7: ='2 — IC Universe Table'!B8 -> WK-US | Z7: ='2 — IC Universe Table'!C8 -> Workiva Inc. | AA7: {=TRANSPOSE(_xll.FDS(Y7,"String_array Name= TRANSPOSE(TRANSPOSE(SA_SUBARRAY(FR_RBICS_REV_MATRIX_CURRENT(""IND""),1,9))[13:13]);float_array pct=TRANSPOSE(TRANSPOSE(SA_SUBARRAY(FR_RBICS_REV_MATRIX_CURRENT(""IND""),1,9))[14:14]);SORT_INDIRECT(Name,pct,2)[0:4]"))} -> Enterprise Resource Planning Software | AB7: #N/A | AC7: #N/A | AD7: #N/A | AE7: #N/A | AF7: {=TRANSPOSE(_xll.FDS(Y7,"String_array Name= TRANSPOSE(TRANSPOSE(SA_SUBARRAY(FR_RBICS_REV_MATRIX_CURRENT(""IND""),1,9))[14:14]);float_array pct=TRANSPOSE(TRANSPOSE(SA_SUBARRAY(FR_RBICS_REV_MATRIX_CURRENT(""IND""),1,9))[14:14]);SORT_INDIRECT(Name,pct,2)[0:4]"))} -> 100.000000 | AG7: #N/A | AH7: #N/A | AI7: #N/A | AJ7: #N/A | AK7: =IFERROR(AA7, "") -> Enterprise Resource Planning Software | AL7: =IFERROR(AB7, "") | AM7: =IFERROR(AC7, "") | AN7: =IFERROR(AD7, "") | AO7: =IFERROR(AE7, "") | AP7: =IFERROR(ROUND(VALUE(AF7), 0)/100, "") -> 1 | AQ7: =IFERROR(ROUND(VALUE(AG7), 0)/100, "") | AR7: =IFERROR(ROUND(VALUE(AH7), 0)/100, "") | AS7: =IFERROR(ROUND(VALUE(AI7), 0)/100, "") | AT7: =IFERROR(ROUND(VALUE(AJ7), 0)/100, "")
A8: ='2 — IC Universe Table'!B9 -> PLTR-US | B8: ='2 — IC Universe Table'!C9 -> Palantir Technologies Inc. Class A | C8: {=TRANSPOSE(_xll.FDS(A8,"TRANSPOSE(TRANSPOSE(FF_GEOREV_COUNTRY_REV_PCT_MATRIX)[1:1])[0:4]"))} -> United States | D8: United Kingdom | E8: Germany | F8: India | G8: Japan | H8: {=TRANSPOSE(_xll.FDS(A8,"TRANSPOSE(TRANSPOSE(FF_GEOREV_COUNTRY_REV_PCT_MATRIX)[2:2])[0:4]"))} -> 74.183511 | I8: 9.549842 | J8: 1.27723 | K8: 1.127082 | L8: 1.126925 | M8: =IFERROR(C8, "") -> United States | N8: =IFERROR(D8, "") -> United Kingdom | O8: =IFERROR(E8, "") -> Germany | P8: =IFERROR(F8, "") -> India | Q8: =IFERROR(G8, "") -> Japan | R8: =IFERROR(ROUND(VALUE(H8), 0)/100, "") -> 0.74 | S8: =IFERROR(ROUND(VALUE(I8), 0)/100, "") -> 0.1 | T8: =IFERROR(ROUND(VALUE(J8), 0)/100, "") -> 0.01 | U8: =IFERROR(ROUND(VALUE(K8), 0)/100, "") -> 0.01 | V8: =IFERROR(ROUND(VALUE(L8), 0)/100, "") -> 0.01 | Y8: ='2 — IC Universe Table'!B9 -> PLTR-US | Z8: ='2 — IC Universe Table'!C9 -> Palantir Technologies Inc. Class A | AA8: {=TRANSPOSE(_xll.FDS(Y8,"String_array Name= TRANSPOSE(TRANSPOSE(SA_SUBARRAY(FR_RBICS_REV_MATRIX_CURRENT(""IND""),1,9))[13:13]);float_array pct=TRANSPOSE(TRANSPOSE(SA_SUBARRAY(FR_RBICS_REV_MATRIX_CURRENT(""IND""),1,9))[14:14]);SORT_INDIRECT(Name,pct,2)[0:4]"))} -> Government and Not-For-Profit Industry Software | AB8: Business Intelligence Software | AC8: #N/A | AD8: #N/A | AE8: #N/A | AF8: {=TRANSPOSE(_xll.FDS(Y8,"String_array Name= TRANSPOSE(TRANSPOSE(SA_SUBARRAY(FR_RBICS_REV_MATRIX_CURRENT(""IND""),1,9))[14:14]);float_array pct=TRANSPOSE(TRANSPOSE(SA_SUBARRAY(FR_RBICS_REV_MATRIX_CURRENT(""IND""),1,9))[14:14]);SORT_INDIRECT(Name,pct,2)[0:4]"))} -> 54.775822 | AG8: 45.224178 | AH8: #N/A | AI8: #N/A | AJ8: #N/A | AK8: =IFERROR(AA8, "") -> Government and Not-For-Profit Industry Software | AL8: =IFERROR(AB8, "") -> Business Intelligence Software | AM8: =IFERROR(AC8, "") | AN8: =IFERROR(AD8, "") | AO8: =IFERROR(AE8, "") | AP8: =IFERROR(ROUND(VALUE(AF8), 0)/100, "") -> 0.55 | AQ8: =IFERROR(ROUND(VALUE(AG8), 0)/100, "") -> 0.45 | AR8: =IFERROR(ROUND(VALUE(AH8), 0)/100, "") | AS8: =IFERROR(ROUND(VALUE(AI8), 0)/100, "") | AT8: =IFERROR(ROUND(VALUE(AJ8), 0)/100, "")
A9: ='2 — IC Universe Table'!B10 -> DT-US | B9: ='2 — IC Universe Table'!C10 -> Dynatrace, Inc. | C9: {=TRANSPOSE(_xll.FDS(A9,"TRANSPOSE(TRANSPOSE(FF_GEOREV_COUNTRY_REV_PCT_MATRIX)[1:1])[0:4]"))} -> United States | D9: Canada | E9: Mainland China | F9: Germany | G9: United Kingdom | H9: {=TRANSPOSE(_xll.FDS(A9,"TRANSPOSE(TRANSPOSE(FF_GEOREV_COUNTRY_REV_PCT_MATRIX)[2:2])[0:4]"))} -> 58.115611 | I9: 2.911903 | J9: 2.807108 | K9: 2.096321 | L9: 2.092057 | M9: =IFERROR(C9, "") -> United States | N9: =IFERROR(D9, "") -> Canada | O9: =IFERROR(E9, "") -> Mainland China | P9: =IFERROR(F9, "") -> Germany | Q9: =IFERROR(G9, "") -> United Kingdom | R9: =IFERROR(ROUND(VALUE(H9), 0)/100, "") -> 0.58 | S9: =IFERROR(ROUND(VALUE(I9), 0)/100, "") -> 0.03 | T9: =IFERROR(ROUND(VALUE(J9), 0)/100, "") -> 0.03 | U9: =IFERROR(ROUND(VALUE(K9), 0)/100, "") -> 0.02 | V9: =IFERROR(ROUND(VALUE(L9), 0)/100, "") -> 0.02 | Y9: ='2 — IC Universe Table'!B10 -> DT-US | Z9: ='2 — IC Universe Table'!C10 -> Dynatrace, Inc. | AA9: {=TRANSPOSE(_xll.FDS(Y9,"String_array Name= TRANSPOSE(TRANSPOSE(SA_SUBARRAY(FR_RBICS_REV_MATRIX_CURRENT(""IND""),1,9))[13:13]);float_array pct=TRANSPOSE(TRANSPOSE(SA_SUBARRAY(FR_RBICS_REV_MATRIX_CURRENT(""IND""),1,9))[14:14]);SORT_INDIRECT(Name,pct,2)[0:4]"))} -> Network Infrastructure Software | AB9: #N/A | AC9: #N/A | AD9: #N/A | AE9: #N/A | AF9: {=TRANSPOSE(_xll.FDS(Y9,"String_array Name= TRANSPOSE(TRANSPOSE(SA_SUBARRAY(FR_RBICS_REV_MATRIX_CURRENT(""IND""),1,9))[14:14]);float_array pct=TRANSPOSE(TRANSPOSE(SA_SUBARRAY(FR_RBICS_REV_MATRIX_CURRENT(""IND""),1,9))[14:14]);SORT_INDIRECT(Name,pct,2)[0:4]"))} -> 100.000000 | AG9: #N/A | AH9: #N/A | AI9: #N/A | AJ9: #N/A | AK9: =IFERROR(AA9, "") -> Network Infrastructure Software | AL9: =IFERROR(AB9, "") | AM9: =IFERROR(AC9, "") | AN9: =IFERROR(AD9, "") | AO9: =IFERROR(AE9, "") | AP9: =IFERROR(ROUND(VALUE(AF9), 0)/100, "") -> 1 | AQ9: =IFERROR(ROUND(VALUE(AG9), 0)/100, "") | AR9: =IFERROR(ROUND(VALUE(AH9), 0)/100, "") | AS9: =IFERROR(ROUND(VALUE(AI9), 0)/100, "") | AT9: =IFERROR(ROUND(VALUE(AJ9), 0)/100, "")
A10: ='2 — IC Universe Table'!B11 -> NOW-US | B10: ='2 — IC Universe Table'!C11 -> ServiceNow, Inc. | C10: {=TRANSPOSE(_xll.FDS(A10,"TRANSPOSE(TRANSPOSE(FF_GEOREV_COUNTRY_REV_PCT_MATRIX)[1:1])[0:4]"))} -> United States | D10: Canada | E10: Mainland China | F10: France | G10: Italy | H10: {=TRANSPOSE(_xll.FDS(A10,"TRANSPOSE(TRANSPOSE(FF_GEOREV_COUNTRY_REV_PCT_MATRIX)[2:2])[0:4]"))} -> 59.098659 | I10: 3.772255 | J10: 2.995982 | K10: 2.236076 | L10: 1.687075 | M10: =IFERROR(C10, "") -> United States | N10: =IFERROR(D10, "") -> Canada | O10: =IFERROR(E10, "") -> Mainland China | P10: =IFERROR(F10, "") -> France | Q10: =IFERROR(G10, "") -> Italy | R10: =IFERROR(ROUND(VALUE(H10), 0)/100, "") -> 0.59 | S10: =IFERROR(ROUND(VALUE(I10), 0)/100, "") -> 0.04 | T10: =IFERROR(ROUND(VALUE(J10), 0)/100, "") -> 0.03 | U10: =IFERROR(ROUND(VALUE(K10), 0)/100, "") -> 0.02 | V10: =IFERROR(ROUND(VALUE(L10), 0)/100, "") -> 0.02 | Y10: ='2 — IC Universe Table'!B11 -> NOW-US | Z10: ='2 — IC Universe Table'!C11 -> ServiceNow, Inc. | AA10: {=TRANSPOSE(_xll.FDS(Y10,"String_array Name= TRANSPOSE(TRANSPOSE(SA_SUBARRAY(FR_RBICS_REV_MATRIX_CURRENT(""IND""),1,9))[13:13]);float_array pct=TRANSPOSE(TRANSPOSE(SA_SUBARRAY(FR_RBICS_REV_MATRIX_CURRENT(""IND""),1,9))[14:14]);SORT_INDIRECT(Name,pct,2)[0:4]"))} -> General Enterprise Management Software | AB10: #N/A | AC10: #N/A | AD10: #N/A | AE10: #N/A | AF10: {=TRANSPOSE(_xll.FDS(Y10,"String_array Name= TRANSPOSE(TRANSPOSE(SA_SUBARRAY(FR_RBICS_REV_MATRIX_CURRENT(""IND""),1,9))[14:14]);float_array pct=TRANSPOSE(TRANSPOSE(SA_SUBARRAY(FR_RBICS_REV_MATRIX_CURRENT(""IND""),1,9))[14:14]);SORT_INDIRECT(Name,pct,2)[0:4]"))} -> 100.000000 | AG10: #N/A | AH10: #N/A | AI10: #N/A | AJ10: #N/A | AK10: =IFERROR(AA10, "") -> General Enterprise Management Software | AL10: =IFERROR(AB10, "") | AM10: =IFERROR(AC10, "") | AN10: =IFERROR(AD10, "") | AO10: =IFERROR(AE10, "") | AP10: =IFERROR(ROUND(VALUE(AF10), 0)/100, "") -> 1 | AQ10: =IFERROR(ROUND(VALUE(AG10), 0)/100, "") | AR10: =IFERROR(ROUND(VALUE(AH10), 0)/100, "") | AS10: =IFERROR(ROUND(VALUE(AI10), 0)/100, "") | AT10: =IFERROR(ROUND(VALUE(AJ10), 0)/100, "")
A11: ='2 — IC Universe Table'!B12 -> TENB-US | B11: ='2 — IC Universe Table'!C12 -> Tenable Holdings, Inc. | C11: {=TRANSPOSE(_xll.FDS(A11,"TRANSPOSE(TRANSPOSE(FF_GEOREV_COUNTRY_REV_PCT_MATRIX)[1:1])[0:4]"))} -> United States | D11: Mainland China | E11: Brazil | F11: Canada | G11: Germany | H11: {=TRANSPOSE(_xll.FDS(A11,"TRANSPOSE(TRANSPOSE(FF_GEOREV_COUNTRY_REV_PCT_MATRIX)[2:2])[0:4]"))} -> 54 | I11: 2.012783 | J11: 1.96535 | K11: 1.890147 | L11: 1.88413 | M11: =IFERROR(C11, "") -> United States | N11: =IFERROR(D11, "") -> Mainland China | O11: =IFERROR(E11, "") -> Brazil | P11: =IFERROR(F11, "") -> Canada | Q11: =IFERROR(G11, "") -> Germany | R11: =IFERROR(ROUND(VALUE(H11), 0)/100, "") -> 0.54 | S11: =IFERROR(ROUND(VALUE(I11), 0)/100, "") -> 0.02 | T11: =IFERROR(ROUND(VALUE(J11), 0)/100, "") -> 0.02 | U11: =IFERROR(ROUND(VALUE(K11), 0)/100, "") -> 0.02 | V11: =IFERROR(ROUND(VALUE(L11), 0)/100, "") -> 0.02 | Y11: ='2 — IC Universe Table'!B12 -> TENB-US | Z11: ='2 — IC Universe Table'!C12 -> Tenable Holdings, Inc. | AA11: {=TRANSPOSE(_xll.FDS(Y11,"String_array Name= TRANSPOSE(TRANSPOSE(SA_SUBARRAY(FR_RBICS_REV_MATRIX_CURRENT(""IND""),1,9))[13:13]);float_array pct=TRANSPOSE(TRANSPOSE(SA_SUBARRAY(FR_RBICS_REV_MATRIX_CURRENT(""IND""),1,9))[14:14]);SORT_INDIRECT(Name,pct,2)[0:4]"))} -> Network Infrastructure Software | AB11: #N/A | AC11: #N/A | AD11: #N/A | AE11: #N/A | AF11: {=TRANSPOSE(_xll.FDS(Y11,"String_array Name= TRANSPOSE(TRANSPOSE(SA_SUBARRAY(FR_RBICS_REV_MATRIX_CURRENT(""IND""),1,9))[14:14]);float_array pct=TRANSPOSE(TRANSPOSE(SA_SUBARRAY(FR_RBICS_REV_MATRIX_CURRENT(""IND""),1,9))[14:14]);SORT_INDIRECT(Name,pct,2)[0:4]"))} -> 100.000000 | AG11: #N/A | AH11: #N/A | AI11: #N/A | AJ11: #N/A | AK11: =IFERROR(AA11, "") -> Network Infrastructure Software | AL11: =IFERROR(AB11, "") | AM11: =IFERROR(AC11, "") | AN11: =IFERROR(AD11, "") | AO11: =IFERROR(AE11, "") | AP11: =IFERROR(ROUND(VALUE(AF11), 0)/100, "") -> 1 | AQ11: =IFERROR(ROUND(VALUE(AG11), 0)/100, "") | AR11: =IFERROR(ROUND(VALUE(AH11), 0)/100, "") | AS11: =IFERROR(ROUND(VALUE(AI11), 0)/100, "") | AT11: =IFERROR(ROUND(VALUE(AJ11), 0)/100, "")
A12: ='2 — IC Universe Table'!B13 -> FICO-US | B12: ='2 — IC Universe Table'!C13 -> Fair Isaac Corporation | C12: {=TRANSPOSE(_xll.FDS(A12,"TRANSPOSE(TRANSPOSE(FF_GEOREV_COUNTRY_REV_PCT_MATRIX)[1:1])[0:4]"))} -> United States | D12: Canada | E12: Brazil | F12: Mexico | G12: Mainland China | H12: {=TRANSPOSE(_xll.FDS(A12,"TRANSPOSE(TRANSPOSE(FF_GEOREV_COUNTRY_REV_PCT_MATRIX)[2:2])[0:4]"))} -> 77 | I12: 2.431836 | J12: 2.323231 | K12: 1.849704 | L12: 0.916663 | M12: =IFERROR(C12, "") -> United States | N12: =IFERROR(D12, "") -> Canada | O12: =IFERROR(E12, "") -> Brazil | P12: =IFERROR(F12, "") -> Mexico | Q12: =IFERROR(G12, "") -> Mainland China | R12: =IFERROR(ROUND(VALUE(H12), 0)/100, "") -> 0.77 | S12: =IFERROR(ROUND(VALUE(I12), 0)/100, "") -> 0.02 | T12: =IFERROR(ROUND(VALUE(J12), 0)/100, "") -> 0.02 | U12: =IFERROR(ROUND(VALUE(K12), 0)/100, "") -> 0.02 | V12: =IFERROR(ROUND(VALUE(L12), 0)/100, "") -> 0.01 | Y12: ='2 — IC Universe Table'!B13 -> FICO-US | Z12: ='2 — IC Universe Table'!C13 -> Fair Isaac Corporation | AA12: {=TRANSPOSE(_xll.FDS(Y12,"String_array Name= TRANSPOSE(TRANSPOSE(SA_SUBARRAY(FR_RBICS_REV_MATRIX_CURRENT(""IND""),1,9))[13:13]);float_array pct=TRANSPOSE(TRANSPOSE(SA_SUBARRAY(FR_RBICS_REV_MATRIX_CURRENT(""IND""),1,9))[14:14]);SORT_INDIRECT(Name,pct,2)[0:4]"))} -> Other Business Administrative Services | AB12: General and Mixed-Type Software | AC12: #N/A | AD12: #N/A | AE12: #N/A | AF12: {=TRANSPOSE(_xll.FDS(Y12,"String_array Name= TRANSPOSE(TRANSPOSE(SA_SUBARRAY(FR_RBICS_REV_MATRIX_CURRENT(""IND""),1,9))[14:14]);float_array pct=TRANSPOSE(TRANSPOSE(SA_SUBARRAY(FR_RBICS_REV_MATRIX_CURRENT(""IND""),1,9))[14:14]);SORT_INDIRECT(Name,pct,2)[0:4]"))} -> 58.696729 | AG12: 41.303271 | AH12: #N/A | AI12: #N/A | AJ12: #N/A | AK12: =IFERROR(AA12, "") -> Other Business Administrative Services | AL12: =IFERROR(AB12, "") -> General and Mixed-Type Software | AM12: =IFERROR(AC12, "") | AN12: =IFERROR(AD12, "") | AO12: =IFERROR(AE12, "") | AP12: =IFERROR(ROUND(VALUE(AF12), 0)/100, "") -> 0.59 | AQ12: =IFERROR(ROUND(VALUE(AG12), 0)/100, "") -> 0.41 | AR12: =IFERROR(ROUND(VALUE(AH12), 0)/100, "") | AS12: =IFERROR(ROUND(VALUE(AI12), 0)/100, "") | AT12: =IFERROR(ROUND(VALUE(AJ12), 0)/100, "")
A13: ='2 — IC Universe Table'!B14 -> DOCU-US | B13: ='2 — IC Universe Table'!C14 -> DocuSign, Inc. | C13: {=TRANSPOSE(_xll.FDS(A13,"TRANSPOSE(TRANSPOSE(FF_GEOREV_COUNTRY_REV_PCT_MATRIX)[1:1])[0:4]"))} -> #N/A | D13: #N/A | E13: #N/A | F13: #N/A | G13: #N/A | H13: {=TRANSPOSE(_xll.FDS(A13,"TRANSPOSE(TRANSPOSE(FF_GEOREV_COUNTRY_REV_PCT_MATRIX)[2:2])[0:4]"))} -> #N/A | I13: #N/A | J13: #N/A | K13: #N/A | L13: #N/A | M13: =IFERROR(C13, "") | N13: =IFERROR(D13, "") | O13: =IFERROR(E13, "") | P13: =IFERROR(F13, "") | Q13: =IFERROR(G13, "") | R13: =IFERROR(ROUND(VALUE(H13), 0)/100, "") | S13: =IFERROR(ROUND(VALUE(I13), 0)/100, "") | T13: =IFERROR(ROUND(VALUE(J13), 0)/100, "") | U13: =IFERROR(ROUND(VALUE(K13), 0)/100, "") | V13: =IFERROR(ROUND(VALUE(L13), 0)/100, "") | Y13: ='2 — IC Universe Table'!B14 -> DOCU-US | Z13: ='2 — IC Universe Table'!C14 -> DocuSign, Inc. | AA13: {=TRANSPOSE(_xll.FDS(Y13,"String_array Name= TRANSPOSE(TRANSPOSE(SA_SUBARRAY(FR_RBICS_REV_MATRIX_CURRENT(""IND""),1,9))[13:13]);float_array pct=TRANSPOSE(TRANSPOSE(SA_SUBARRAY(FR_RBICS_REV_MATRIX_CURRENT(""IND""),1,9))[14:14]);SORT_INDIRECT(Name,pct,2)[0:4]"))} -> Content Management Software | AB13: #N/A | AC13: #N/A | AD13: #N/A | AE13: #N/A | AF13: {=TRANSPOSE(_xll.FDS(Y13,"String_array Name= TRANSPOSE(TRANSPOSE(SA_SUBARRAY(FR_RBICS_REV_MATRIX_CURRENT(""IND""),1,9))[14:14]);float_array pct=TRANSPOSE(TRANSPOSE(SA_SUBARRAY(FR_RBICS_REV_MATRIX_CURRENT(""IND""),1,9))[14:14]);SORT_INDIRECT(Name,pct,2)[0:4]"))} -> 100.000000 | AG13: #N/A | AH13: #N/A | AI13: #N/A | AJ13: #N/A | AK13: =IFERROR(AA13, "") -> Content Management Software | AL13: =IFERROR(AB13, "") | AM13: =IFERROR(AC13, "") | AN13: =IFERROR(AD13, "") | AO13: =IFERROR(AE13, "") | AP13: =IFERROR(ROUND(VALUE(AF13), 0)/100, "") -> 1 | AQ13: =IFERROR(ROUND(VALUE(AG13), 0)/100, "") | AR13: =IFERROR(ROUND(VALUE(AH13), 0)/100, "") | AS13: =IFERROR(ROUND(VALUE(AI13), 0)/100, "") | AT13: =IFERROR(ROUND(VALUE(AJ13), 0)/100, "")
A14: ='2 — IC Universe Table'!B15 -> CVLT-US | B14: ='2 — IC Universe Table'!C15 -> Commvault Systems, Inc. | C14: {=TRANSPOSE(_xll.FDS(A14,"TRANSPOSE(TRANSPOSE(FF_GEOREV_COUNTRY_REV_PCT_MATRIX)[1:1])[0:4]"))} -> United States | D14: Mainland China | E14: Germany | F14: India | G14: United Kingdom | H14: {=TRANSPOSE(_xll.FDS(A14,"TRANSPOSE(TRANSPOSE(FF_GEOREV_COUNTRY_REV_PCT_MATRIX)[2:2])[0:4]"))} -> 53.687606 | I14: 11.304324 | J14: 2.800427 | K14: 2.401453 | L14: 2.131999 | M14: =IFERROR(C14, "") -> United States | N14: =IFERROR(D14, "") -> Mainland China | O14: =IFERROR(E14, "") -> Germany | P14: =IFERROR(F14, "") -> India | Q14: =IFERROR(G14, "") -> United Kingdom | R14: =IFERROR(ROUND(VALUE(H14), 0)/100, "") -> 0.54 | S14: =IFERROR(ROUND(VALUE(I14), 0)/100, "") -> 0.11 | T14: =IFERROR(ROUND(VALUE(J14), 0)/100, "") -> 0.03 | U14: =IFERROR(ROUND(VALUE(K14), 0)/100, "") -> 0.02 | V14: =IFERROR(ROUND(VALUE(L14), 0)/100, "") -> 0.02 | Y14: ='2 — IC Universe Table'!B15 -> CVLT-US | Z14: ='2 — IC Universe Table'!C15 -> Commvault Systems, Inc. | AA14: {=TRANSPOSE(_xll.FDS(Y14,"String_array Name= TRANSPOSE(TRANSPOSE(SA_SUBARRAY(FR_RBICS_REV_MATRIX_CURRENT(""IND""),1,9))[13:13]);float_array pct=TRANSPOSE(TRANSPOSE(SA_SUBARRAY(FR_RBICS_REV_MATRIX_CURRENT(""IND""),1,9))[14:14]);SORT_INDIRECT(Name,pct,2)[0:4]"))} -> Data Storage Infrastructure Software | AB14: #N/A | AC14: #N/A | AD14: #N/A | AE14: #N/A | AF14: {=TRANSPOSE(_xll.FDS(Y14,"String_array Name= TRANSPOSE(TRANSPOSE(SA_SUBARRAY(FR_RBICS_REV_MATRIX_CURRENT(""IND""),1,9))[14:14]);float_array pct=TRANSPOSE(TRANSPOSE(SA_SUBARRAY(FR_RBICS_REV_MATRIX_CURRENT(""IND""),1,9))[14:14]);SORT_INDIRECT(Name,pct,2)[0:4]"))} -> 100.000000 | AG14: #N/A | AH14: #N/A | AI14: #N/A | AJ14: #N/A | AK14: =IFERROR(AA14, "") -> Data Storage Infrastructure Software | AL14: =IFERROR(AB14, "") | AM14: =IFERROR(AC14, "") | AN14: =IFERROR(AD14, "") | AO14: =IFERROR(AE14, "") | AP14: =IFERROR(ROUND(VALUE(AF14), 0)/100, "") -> 1 | AQ14: =IFERROR(ROUND(VALUE(AG14), 0)/100, "") | AR14: =IFERROR(ROUND(VALUE(AH14), 0)/100, "") | AS14: =IFERROR(ROUND(VALUE(AI14), 0)/100, "") | AT14: =IFERROR(ROUND(VALUE(AJ14), 0)/100, "")
A15: ='2 — IC Universe Table'!B16 -> WDAY-US | B15: ='2 — IC Universe Table'!C16 -> Workday, Inc. Class A | C15: {=TRANSPOSE(_xll.FDS(A15,"TRANSPOSE(TRANSPOSE(FF_GEOREV_COUNTRY_REV_PCT_MATRIX)[1:1])[0:4]"))} -> United States | D15: Mainland China | E15: Germany | F15: Japan | G15: India | H15: {=TRANSPOSE(_xll.FDS(A15,"TRANSPOSE(TRANSPOSE(FF_GEOREV_COUNTRY_REV_PCT_MATRIX)[2:2])[0:4]"))} -> 74.9704 | I15: 5.729917 | J15: 1.419476 | K15: 1.270869 | L15: 1.217244 | M15: =IFERROR(C15, "") -> United States | N15: =IFERROR(D15, "") -> Mainland China | O15: =IFERROR(E15, "") -> Germany | P15: =IFERROR(F15, "") -> Japan | Q15: =IFERROR(G15, "") -> India | R15: =IFERROR(ROUND(VALUE(H15), 0)/100, "") -> 0.75 | S15: =IFERROR(ROUND(VALUE(I15), 0)/100, "") -> 0.06 | T15: =IFERROR(ROUND(VALUE(J15), 0)/100, "") -> 0.01 | U15: =IFERROR(ROUND(VALUE(K15), 0)/100, "") -> 0.01 | V15: =IFERROR(ROUND(VALUE(L15), 0)/100, "") -> 0.01 | Y15: ='2 — IC Universe Table'!B16 -> WDAY-US | Z15: ='2 — IC Universe Table'!C16 -> Workday, Inc. Class A | AA15: {=TRANSPOSE(_xll.FDS(Y15,"String_array Name= TRANSPOSE(TRANSPOSE(SA_SUBARRAY(FR_RBICS_REV_MATRIX_CURRENT(""IND""),1,9))[13:13]);float_array pct=TRANSPOSE(TRANSPOSE(SA_SUBARRAY(FR_RBICS_REV_MATRIX_CURRENT(""IND""),1,9))[14:14]);SORT_INDIRECT(Name,pct,2)[0:4]"))} -> Enterprise Resource Planning Software | AB15: #N/A | AC15: #N/A | AD15: #N/A | AE15: #N/A | AF15: {=TRANSPOSE(_xll.FDS(Y15,"String_array Name= TRANSPOSE(TRANSPOSE(SA_SUBARRAY(FR_RBICS_REV_MATRIX_CURRENT(""IND""),1,9))[14:14]);float_array pct=TRANSPOSE(TRANSPOSE(SA_SUBARRAY(FR_RBICS_REV_MATRIX_CURRENT(""IND""),1,9))[14:14]);SORT_INDIRECT(Name,pct,2)[0:4]"))} -> 100.000000 | AG15: #N/A | AH15: #N/A | AI15: #N/A | AJ15: #N/A | AK15: =IFERROR(AA15, "") -> Enterprise Resource Planning Software | AL15: =IFERROR(AB15, "") | AM15: =IFERROR(AC15, "") | AN15: =IFERROR(AD15, "") | AO15: =IFERROR(AE15, "") | AP15: =IFERROR(ROUND(VALUE(AF15), 0)/100, "") -> 1 | AQ15: =IFERROR(ROUND(VALUE(AG15), 0)/100, "") | AR15: =IFERROR(ROUND(VALUE(AH15), 0)/100, "") | AS15: =IFERROR(ROUND(VALUE(AI15), 0)/100, "") | AT15: =IFERROR(ROUND(VALUE(AJ15), 0)/100, "")
A16: ='2 — IC Universe Table'!B17 -> PATH-US | B16: ='2 — IC Universe Table'!C17 -> UiPath, Inc. Class A | C16: {=TRANSPOSE(_xll.FDS(A16,"TRANSPOSE(TRANSPOSE(FF_GEOREV_COUNTRY_REV_PCT_MATRIX)[1:1])[0:4]"))} -> United States | D16: Japan | E16: Mainland China | F16: Germany | G16: Italy | H16: {=TRANSPOSE(_xll.FDS(A16,"TRANSPOSE(TRANSPOSE(FF_GEOREV_COUNTRY_REV_PCT_MATRIX)[2:2])[0:4]"))} -> 44 | I16: 9 | J16: 5.946985 | K16: 2.264493 | L16: 2.12734 | M16: =IFERROR(C16, "") -> United States | N16: =IFERROR(D16, "") -> Japan | O16: =IFERROR(E16, "") -> Mainland China | P16: =IFERROR(F16, "") -> Germany | Q16: =IFERROR(G16, "") -> Italy | R16: =IFERROR(ROUND(VALUE(H16), 0)/100, "") -> 0.44 | S16: =IFERROR(ROUND(VALUE(I16), 0)/100, "") -> 0.09 | T16: =IFERROR(ROUND(VALUE(J16), 0)/100, "") -> 0.06 | U16: =IFERROR(ROUND(VALUE(K16), 0)/100, "") -> 0.02 | V16: =IFERROR(ROUND(VALUE(L16), 0)/100, "") -> 0.02 | Y16: ='2 — IC Universe Table'!B17 -> PATH-US | Z16: ='2 — IC Universe Table'!C17 -> UiPath, Inc. Class A | AA16: {=TRANSPOSE(_xll.FDS(Y16,"String_array Name= TRANSPOSE(TRANSPOSE(SA_SUBARRAY(FR_RBICS_REV_MATRIX_CURRENT(""IND""),1,9))[13:13]);float_array pct=TRANSPOSE(TRANSPOSE(SA_SUBARRAY(FR_RBICS_REV_MATRIX_CURRENT(""IND""),1,9))[14:14]);SORT_INDIRECT(Name,pct,2)[0:4]"))} -> Enterprise Resource Planning Software | AB16: #N/A | AC16: #N/A | AD16: #N/A | AE16: #N/A | AF16: {=TRANSPOSE(_xll.FDS(Y16,"String_array Name= TRANSPOSE(TRANSPOSE(SA_SUBARRAY(FR_RBICS_REV_MATRIX_CURRENT(""IND""),1,9))[14:14]);float_array pct=TRANSPOSE(TRANSPOSE(SA_SUBARRAY(FR_RBICS_REV_MATRIX_CURRENT(""IND""),1,9))[14:14]);SORT_INDIRECT(Name,pct,2)[0:4]"))} -> 100.000000 | AG16: #N/A | AH16: #N/A | AI16: #N/A | AJ16: #N/A | AK16: =IFERROR(AA16, "") -> Enterprise Resource Planning Software | AL16: =IFERROR(AB16, "") | AM16: =IFERROR(AC16, "") | AN16: =IFERROR(AD16, "") | AO16: =IFERROR(AE16, "") | AP16: =IFERROR(ROUND(VALUE(AF16), 0)/100, "") -> 1 | AQ16: =IFERROR(ROUND(VALUE(AG16), 0)/100, "") | AR16: =IFERROR(ROUND(VALUE(AH16), 0)/100, "") | AS16: =IFERROR(ROUND(VALUE(AI16), 0)/100, "") | AT16: =IFERROR(ROUND(VALUE(AJ16), 0)/100, "")
A17: ='2 — IC Universe Table'!B18 -> INTU-US | B17: ='2 — IC Universe Table'!C18 -> Intuit Inc. | C17: {=TRANSPOSE(_xll.FDS(A17,"TRANSPOSE(TRANSPOSE(FF_GEOREV_COUNTRY_REV_PCT_MATRIX)[1:1])[0:4]"))} -> United States | D17: Mainland China | E17: Germany | F17: India | G17: Japan | H17: {=TRANSPOSE(_xll.FDS(A17,"TRANSPOSE(TRANSPOSE(FF_GEOREV_COUNTRY_REV_PCT_MATRIX)[2:2])[0:4]"))} -> 92 | I17: 1.842556 | J17: 0.454591 | K17: 0.401151 | L17: 0.401095 | M17: =IFERROR(C17, "") -> United States | N17: =IFERROR(D17, "") -> Mainland China | O17: =IFERROR(E17, "") -> Germany | P17: =IFERROR(F17, "") -> India | Q17: =IFERROR(G17, "") -> Japan | R17: =IFERROR(ROUND(VALUE(H17), 0)/100, "") -> 0.92 | S17: =IFERROR(ROUND(VALUE(I17), 0)/100, "") -> 0.02 | T17: =IFERROR(ROUND(VALUE(J17), 0)/100, "") -> 0 | U17: =IFERROR(ROUND(VALUE(K17), 0)/100, "") -> 0 | V17: =IFERROR(ROUND(VALUE(L17), 0)/100, "") -> 0 | Y17: ='2 — IC Universe Table'!B18 -> INTU-US | Z17: ='2 — IC Universe Table'!C18 -> Intuit Inc. | AA17: {=TRANSPOSE(_xll.FDS(Y17,"String_array Name= TRANSPOSE(TRANSPOSE(SA_SUBARRAY(FR_RBICS_REV_MATRIX_CURRENT(""IND""),1,9))[13:13]);float_array pct=TRANSPOSE(TRANSPOSE(SA_SUBARRAY(FR_RBICS_REV_MATRIX_CURRENT(""IND""),1,9))[14:14]);SORT_INDIRECT(Name,pct,2)[0:4]"))} -> Enterprise Resource Planning Software | AB17: Productivity Software | AC17: Accounting, Tax Preparers and Bookkeeping Services | AD17: #N/A | AE17: #N/A | AF17: {=TRANSPOSE(_xll.FDS(Y17,"String_array Name= TRANSPOSE(TRANSPOSE(SA_SUBARRAY(FR_RBICS_REV_MATRIX_CURRENT(""IND""),1,9))[14:14]);float_array pct=TRANSPOSE(TRANSPOSE(SA_SUBARRAY(FR_RBICS_REV_MATRIX_CURRENT(""IND""),1,9))[14:14]);SORT_INDIRECT(Name,pct,2)[0:4]"))} -> 58.823217 | AG17: 37.879029 | AH17: 3.297754 | AI17: #N/A | AJ17: #N/A | AK17: =IFERROR(AA17, "") -> Enterprise Resource Planning Software | AL17: =IFERROR(AB17, "") -> Productivity Software | AM17: =IFERROR(AC17, "") -> Accounting, Tax Preparers and Bookkeeping Services | AN17: =IFERROR(AD17, "") | AO17: =IFERROR(AE17, "") | AP17: =IFERROR(ROUND(VALUE(AF17), 0)/100, "") -> 0.59 | AQ17: =IFERROR(ROUND(VALUE(AG17), 0)/100, "") -> 0.38 | AR17: =IFERROR(ROUND(VALUE(AH17), 0)/100, "") -> 0.03 | AS17: =IFERROR(ROUND(VALUE(AI17), 0)/100, "") | AT17: =IFERROR(ROUND(VALUE(AJ17), 0)/100, "")
A18: ='2 — IC Universe Table'!B19 -> AVPT-US | B18: ='2 — IC Universe Table'!C19 -> AvePoint, Inc. Class A | C18: {=TRANSPOSE(_xll.FDS(A18,"TRANSPOSE(TRANSPOSE(FF_GEOREV_COUNTRY_REV_PCT_MATRIX)[1:1])[0:4]"))} -> United States | D18: Singapore | E18: Germany | F18: Mainland China | G18: United Kingdom | H18: {=TRANSPOSE(_xll.FDS(A18,"TRANSPOSE(TRANSPOSE(FF_GEOREV_COUNTRY_REV_PCT_MATRIX)[2:2])[0:4]"))} -> 40.936572 | I18: 13.045491 | J18: 12.637602 | K18: 8.161202 | L18: 1.997248 | M18: =IFERROR(C18, "") -> United States | N18: =IFERROR(D18, "") -> Singapore | O18: =IFERROR(E18, "") -> Germany | P18: =IFERROR(F18, "") -> Mainland China | Q18: =IFERROR(G18, "") -> United Kingdom | R18: =IFERROR(ROUND(VALUE(H18), 0)/100, "") -> 0.41 | S18: =IFERROR(ROUND(VALUE(I18), 0)/100, "") -> 0.13 | T18: =IFERROR(ROUND(VALUE(J18), 0)/100, "") -> 0.13 | U18: =IFERROR(ROUND(VALUE(K18), 0)/100, "") -> 0.08 | V18: =IFERROR(ROUND(VALUE(L18), 0)/100, "") -> 0.02 | Y18: ='2 — IC Universe Table'!B19 -> AVPT-US | Z18: ='2 — IC Universe Table'!C19 -> AvePoint, Inc. Class A | AA18: {=TRANSPOSE(_xll.FDS(Y18,"String_array Name= TRANSPOSE(TRANSPOSE(SA_SUBARRAY(FR_RBICS_REV_MATRIX_CURRENT(""IND""),1,9))[13:13]);float_array pct=TRANSPOSE(TRANSPOSE(SA_SUBARRAY(FR_RBICS_REV_MATRIX_CURRENT(""IND""),1,9))[14:14]);SORT_INDIRECT(Name,pct,2)[0:4]"))} -> Data Storage Infrastructure Software | AB18: Software Design and Engineering Consulting | AC18: #N/A | AD18: #N/A | AE18: #N/A | AF18: {=TRANSPOSE(_xll.FDS(Y18,"String_array Name= TRANSPOSE(TRANSPOSE(SA_SUBARRAY(FR_RBICS_REV_MATRIX_CURRENT(""IND""),1,9))[14:14]);float_array pct=TRANSPOSE(TRANSPOSE(SA_SUBARRAY(FR_RBICS_REV_MATRIX_CURRENT(""IND""),1,9))[14:14]);SORT_INDIRECT(Name,pct,2)[0:4]"))} -> 86.675220 | AG18: 13.324780 | AH18: #N/A | AI18: #N/A | AJ18: #N/A | AK18: =IFERROR(AA18, "") -> Data Storage Infrastructure Software | AL18: =IFERROR(AB18, "") -> Software Design and Engineering Consulting | AM18: =IFERROR(AC18, "") | AN18: =IFERROR(AD18, "") | AO18: =IFERROR(AE18, "") | AP18: =IFERROR(ROUND(VALUE(AF18), 0)/100, "") -> 0.87 | AQ18: =IFERROR(ROUND(VALUE(AG18), 0)/100, "") -> 0.13 | AR18: =IFERROR(ROUND(VALUE(AH18), 0)/100, "") | AS18: =IFERROR(ROUND(VALUE(AI18), 0)/100, "") | AT18: =IFERROR(ROUND(VALUE(AJ18), 0)/100, "")
A19: ='2 — IC Universe Table'!B20 -> ADSK-US | B19: ='2 — IC Universe Table'!C20 -> Autodesk, Inc. | C19: {=TRANSPOSE(_xll.FDS(A19,"TRANSPOSE(TRANSPOSE(FF_GEOREV_COUNTRY_REV_PCT_MATRIX)[1:1])[0:4]"))} -> United States | D19: Mainland China | E19: Japan | F19: India | G19: Germany | H19: {=TRANSPOSE(_xll.FDS(A19,"TRANSPOSE(TRANSPOSE(FF_GEOREV_COUNTRY_REV_PCT_MATRIX)[2:2])[0:4]"))} -> 36.339912 | I19: 3.202995 | J19: 2.855317 | K19: 2.734837 | L19: 2.661568 | M19: =IFERROR(C19, "") -> United States | N19: =IFERROR(D19, "") -> Mainland China | O19: =IFERROR(E19, "") -> Japan | P19: =IFERROR(F19, "") -> India | Q19: =IFERROR(G19, "") -> Germany | R19: =IFERROR(ROUND(VALUE(H19), 0)/100, "") -> 0.36 | S19: =IFERROR(ROUND(VALUE(I19), 0)/100, "") -> 0.03 | T19: =IFERROR(ROUND(VALUE(J19), 0)/100, "") -> 0.03 | U19: =IFERROR(ROUND(VALUE(K19), 0)/100, "") -> 0.03 | V19: =IFERROR(ROUND(VALUE(L19), 0)/100, "") -> 0.03 | Y19: ='2 — IC Universe Table'!B20 -> ADSK-US | Z19: ='2 — IC Universe Table'!C20 -> Autodesk, Inc. | AA19: {=TRANSPOSE(_xll.FDS(Y19,"String_array Name= TRANSPOSE(TRANSPOSE(SA_SUBARRAY(FR_RBICS_REV_MATRIX_CURRENT(""IND""),1,9))[13:13]);float_array pct=TRANSPOSE(TRANSPOSE(SA_SUBARRAY(FR_RBICS_REV_MATRIX_CURRENT(""IND""),1,9))[14:14]);SORT_INDIRECT(Name,pct,2)[0:4]"))} -> Computer Aided Design Software | AB19: Specialized Design and Engineering Software | AC19: Other Design and Engineering Software | AD19: #N/A | AE19: #N/A | AF19: {=TRANSPOSE(_xll.FDS(Y19,"String_array Name= TRANSPOSE(TRANSPOSE(SA_SUBARRAY(FR_RBICS_REV_MATRIX_CURRENT(""IND""),1,9))[14:14]);float_array pct=TRANSPOSE(TRANSPOSE(SA_SUBARRAY(FR_RBICS_REV_MATRIX_CURRENT(""IND""),1,9))[14:14]);SORT_INDIRECT(Name,pct,2)[0:4]"))} -> 92.937531 | AG19: 5.137824 | AH19: 1.924645 | AI19: #N/A | AJ19: #N/A | AK19: =IFERROR(AA19, "") -> Computer Aided Design Software | AL19: =IFERROR(AB19, "") -> Specialized Design and Engineering Software | AM19: =IFERROR(AC19, "") -> Other Design and Engineering Software | AN19: =IFERROR(AD19, "") | AO19: =IFERROR(AE19, "") | AP19: =IFERROR(ROUND(VALUE(AF19), 0)/100, "") -> 0.93 | AQ19: =IFERROR(ROUND(VALUE(AG19), 0)/100, "") -> 0.05 | AR19: =IFERROR(ROUND(VALUE(AH19), 0)/100, "") -> 0.02 | AS19: =IFERROR(ROUND(VALUE(AI19), 0)/100, "") | AT19: =IFERROR(ROUND(VALUE(AJ19), 0)/100, "")
A20: ='2 — IC Universe Table'!B21 -> ESTC-US | B20: ='2 — IC Universe Table'!C21 -> Elastic NV | C20: {=TRANSPOSE(_xll.FDS(A20,"TRANSPOSE(TRANSPOSE(FF_GEOREV_COUNTRY_REV_PCT_MATRIX)[1:1])[0:4]"))} -> United States | D20: Mainland China | E20: Germany | F20: Japan | G20: India | H20: {=TRANSPOSE(_xll.FDS(A20,"TRANSPOSE(TRANSPOSE(FF_GEOREV_COUNTRY_REV_PCT_MATRIX)[2:2])[0:4]"))} -> 56.376205 | I20: 10.020736 | J20: 2.489963 | K20: 2.151994 | L20: 2.089397 | M20: =IFERROR(C20, "") -> United States | N20: =IFERROR(D20, "") -> Mainland China | O20: =IFERROR(E20, "") -> Germany | P20: =IFERROR(F20, "") -> Japan | Q20: =IFERROR(G20, "") -> India | R20: =IFERROR(ROUND(VALUE(H20), 0)/100, "") -> 0.56 | S20: =IFERROR(ROUND(VALUE(I20), 0)/100, "") -> 0.1 | T20: =IFERROR(ROUND(VALUE(J20), 0)/100, "") -> 0.02 | U20: =IFERROR(ROUND(VALUE(K20), 0)/100, "") -> 0.02 | V20: =IFERROR(ROUND(VALUE(L20), 0)/100, "") -> 0.02 | Y20: ='2 — IC Universe Table'!B21 -> ESTC-US | Z20: ='2 — IC Universe Table'!C21 -> Elastic NV | AA20: {=TRANSPOSE(_xll.FDS(Y20,"String_array Name= TRANSPOSE(TRANSPOSE(SA_SUBARRAY(FR_RBICS_REV_MATRIX_CURRENT(""IND""),1,9))[13:13]);float_array pct=TRANSPOSE(TRANSPOSE(SA_SUBARRAY(FR_RBICS_REV_MATRIX_CURRENT(""IND""),1,9))[14:14]);SORT_INDIRECT(Name,pct,2)[0:4]"))} -> Business Intelligence Software | AB20: #N/A | AC20: #N/A | AD20: #N/A | AE20: #N/A | AF20: {=TRANSPOSE(_xll.FDS(Y20,"String_array Name= TRANSPOSE(TRANSPOSE(SA_SUBARRAY(FR_RBICS_REV_MATRIX_CURRENT(""IND""),1,9))[14:14]);float_array pct=TRANSPOSE(TRANSPOSE(SA_SUBARRAY(FR_RBICS_REV_MATRIX_CURRENT(""IND""),1,9))[14:14]);SORT_INDIRECT(Name,pct,2)[0:4]"))} -> 100.000000 | AG20: #N/A | AH20: #N/A | AI20: #N/A | AJ20: #N/A | AK20: =IFERROR(AA20, "") -> Business Intelligence Software | AL20: =IFERROR(AB20, "") | AM20: =IFERROR(AC20, "") | AN20: =IFERROR(AD20, "") | AO20: =IFERROR(AE20, "") | AP20: =IFERROR(ROUND(VALUE(AF20), 0)/100, "") -> 1 | AQ20: =IFERROR(ROUND(VALUE(AG20), 0)/100, "") | AR20: =IFERROR(ROUND(VALUE(AH20), 0)/100, "") | AS20: =IFERROR(ROUND(VALUE(AI20), 0)/100, "") | AT20: =IFERROR(ROUND(VALUE(AJ20), 0)/100, "")
A21: ='2 — IC Universe Table'!B22 -> FTNT-US | B21: ='2 — IC Universe Table'!C22 -> Fortinet, Inc. | C21: {=TRANSPOSE(_xll.FDS(A21,"TRANSPOSE(TRANSPOSE(FF_GEOREV_COUNTRY_REV_PCT_MATRIX)[1:1])[0:4]"))} -> United States | D21: Mainland China | E21: Japan | F21: Germany | G21: India | H21: {=TRANSPOSE(_xll.FDS(A21,"TRANSPOSE(TRANSPOSE(FF_GEOREV_COUNTRY_REV_PCT_MATRIX)[2:2])[0:4]"))} -> 29.868364 | I21: 3.325189 | J21: 2.964247 | K21: 2.845799 | L21: 2.839171 | M21: =IFERROR(C21, "") -> United States | N21: =IFERROR(D21, "") -> Mainland China | O21: =IFERROR(E21, "") -> Japan | P21: =IFERROR(F21, "") -> Germany | Q21: =IFERROR(G21, "") -> India | R21: =IFERROR(ROUND(VALUE(H21), 0)/100, "") -> 0.3 | S21: =IFERROR(ROUND(VALUE(I21), 0)/100, "") -> 0.03 | T21: =IFERROR(ROUND(VALUE(J21), 0)/100, "") -> 0.03 | U21: =IFERROR(ROUND(VALUE(K21), 0)/100, "") -> 0.03 | V21: =IFERROR(ROUND(VALUE(L21), 0)/100, "") -> 0.03 | Y21: ='2 — IC Universe Table'!B22 -> FTNT-US | Z21: ='2 — IC Universe Table'!C22 -> Fortinet, Inc. | AA21: {=TRANSPOSE(_xll.FDS(Y21,"String_array Name= TRANSPOSE(TRANSPOSE(SA_SUBARRAY(FR_RBICS_REV_MATRIX_CURRENT(""IND""),1,9))[13:13]);float_array pct=TRANSPOSE(TRANSPOSE(SA_SUBARRAY(FR_RBICS_REV_MATRIX_CURRENT(""IND""),1,9))[14:14]);SORT_INDIRECT(Name,pct,2)[0:4]"))} -> Network Infrastructure Software | AB21: Customer Premises Network Security Equipment | AC21: #N/A | AD21: #N/A | AE21: #N/A | AF21: {=TRANSPOSE(_xll.FDS(Y21,"String_array Name= TRANSPOSE(TRANSPOSE(SA_SUBARRAY(FR_RBICS_REV_MATRIX_CURRENT(""IND""),1,9))[14:14]);float_array pct=TRANSPOSE(TRANSPOSE(SA_SUBARRAY(FR_RBICS_REV_MATRIX_CURRENT(""IND""),1,9))[14:14]);SORT_INDIRECT(Name,pct,2)[0:4]"))} -> 67.952248 | AG21: 32.047752 | AH21: #N/A | AI21: #N/A | AJ21: #N/A | AK21: =IFERROR(AA21, "") -> Network Infrastructure Software | AL21: =IFERROR(AB21, "") -> Customer Premises Network Security Equipment | AM21: =IFERROR(AC21, "") | AN21: =IFERROR(AD21, "") | AO21: =IFERROR(AE21, "") | AP21: =IFERROR(ROUND(VALUE(AF21), 0)/100, "") -> 0.68 | AQ21: =IFERROR(ROUND(VALUE(AG21), 0)/100, "") -> 0.32 | AR21: =IFERROR(ROUND(VALUE(AH21), 0)/100, "") | AS21: =IFERROR(ROUND(VALUE(AI21), 0)/100, "") | AT21: =IFERROR(ROUND(VALUE(AJ21), 0)/100, "")
A22: ='2 — IC Universe Table'!B23 -> PAYC-US | B22: ='2 — IC Universe Table'!C23 -> Paycom Software, Inc. | C22: {=TRANSPOSE(_xll.FDS(A22,"TRANSPOSE(TRANSPOSE(FF_GEOREV_COUNTRY_REV_PCT_MATRIX)[1:1])[0:4]"))} -> United States | D22: #N/A | E22: #N/A | F22: #N/A | G22: #N/A | H22: {=TRANSPOSE(_xll.FDS(A22,"TRANSPOSE(TRANSPOSE(FF_GEOREV_COUNTRY_REV_PCT_MATRIX)[2:2])[0:4]"))} -> 100 | I22: #N/A | J22: #N/A | K22: #N/A | L22: #N/A | M22: =IFERROR(C22, "") -> United States | N22: =IFERROR(D22, "") | O22: =IFERROR(E22, "") | P22: =IFERROR(F22, "") | Q22: =IFERROR(G22, "") | R22: =IFERROR(ROUND(VALUE(H22), 0)/100, "") -> 1 | S22: =IFERROR(ROUND(VALUE(I22), 0)/100, "") | T22: =IFERROR(ROUND(VALUE(J22), 0)/100, "") | U22: =IFERROR(ROUND(VALUE(K22), 0)/100, "") | V22: =IFERROR(ROUND(VALUE(L22), 0)/100, "") | Y22: ='2 — IC Universe Table'!B23 -> PAYC-US | Z22: ='2 — IC Universe Table'!C23 -> Paycom Software, Inc. | AA22: {=TRANSPOSE(_xll.FDS(Y22,"String_array Name= TRANSPOSE(TRANSPOSE(SA_SUBARRAY(FR_RBICS_REV_MATRIX_CURRENT(""IND""),1,9))[13:13]);float_array pct=TRANSPOSE(TRANSPOSE(SA_SUBARRAY(FR_RBICS_REV_MATRIX_CURRENT(""IND""),1,9))[14:14]);SORT_INDIRECT(Name,pct,2)[0:4]"))} -> Enterprise Resource Planning Software | AB22: #N/A | AC22: #N/A | AD22: #N/A | AE22: #N/A | AF22: {=TRANSPOSE(_xll.FDS(Y22,"String_array Name= TRANSPOSE(TRANSPOSE(SA_SUBARRAY(FR_RBICS_REV_MATRIX_CURRENT(""IND""),1,9))[14:14]);float_array pct=TRANSPOSE(TRANSPOSE(SA_SUBARRAY(FR_RBICS_REV_MATRIX_CURRENT(""IND""),1,9))[14:14]);SORT_INDIRECT(Name,pct,2)[0:4]"))} -> 100.000000 | AG22: #N/A | AH22: #N/A | AI22: #N/A | AJ22: #N/A | AK22: =IFERROR(AA22, "") -> Enterprise Resource Planning Software | AL22: =IFERROR(AB22, "") | AM22: =IFERROR(AC22, "") | AN22: =IFERROR(AD22, "") | AO22: =IFERROR(AE22, "") | AP22: =IFERROR(ROUND(VALUE(AF22), 0)/100, "") -> 1 | AQ22: =IFERROR(ROUND(VALUE(AG22), 0)/100, "") | AR22: =IFERROR(ROUND(VALUE(AH22), 0)/100, "") | AS22: =IFERROR(ROUND(VALUE(AI22), 0)/100, "") | AT22: =IFERROR(ROUND(VALUE(AJ22), 0)/100, "")
A23: ='2 — IC Universe Table'!B24 -> CRM-US | B23: ='2 — IC Universe Table'!C24 -> Salesforce, Inc. | C23: {=TRANSPOSE(_xll.FDS(A23,"TRANSPOSE(TRANSPOSE(FF_GEOREV_COUNTRY_REV_PCT_MATRIX)[1:1])[0:4]"))} -> United States | D23: Mainland China | E23: Germany | F23: United Kingdom | G23: France | H23: {=TRANSPOSE(_xll.FDS(A23,"TRANSPOSE(TRANSPOSE(FF_GEOREV_COUNTRY_REV_PCT_MATRIX)[2:2])[0:4]"))} -> 61.704684 | I23: 5.520619 | J23: 5.080256 | K23: 3.86766 | L23: 3.463495 | M23: =IFERROR(C23, "") -> United States | N23: =IFERROR(D23, "") -> Mainland China | O23: =IFERROR(E23, "") -> Germany | P23: =IFERROR(F23, "") -> United Kingdom | Q23: =IFERROR(G23, "") -> France | R23: =IFERROR(ROUND(VALUE(H23), 0)/100, "") -> 0.62 | S23: =IFERROR(ROUND(VALUE(I23), 0)/100, "") -> 0.06 | T23: =IFERROR(ROUND(VALUE(J23), 0)/100, "") -> 0.05 | U23: =IFERROR(ROUND(VALUE(K23), 0)/100, "") -> 0.04 | V23: =IFERROR(ROUND(VALUE(L23), 0)/100, "") -> 0.03 | Y23: ='2 — IC Universe Table'!B24 -> CRM-US | Z23: ='2 — IC Universe Table'!C24 -> Salesforce, Inc. | AA23: {=TRANSPOSE(_xll.FDS(Y23,"String_array Name= TRANSPOSE(TRANSPOSE(SA_SUBARRAY(FR_RBICS_REV_MATRIX_CURRENT(""IND""),1,9))[13:13]);float_array pct=TRANSPOSE(TRANSPOSE(SA_SUBARRAY(FR_RBICS_REV_MATRIX_CURRENT(""IND""),1,9))[14:14]);SORT_INDIRECT(Name,pct,2)[0:4]"))} -> Customer Relationship Management Software | AB23: Specialized Design and Engineering Software | AC23: #N/A | AD23: #N/A | AE23: #N/A | AF23: {=TRANSPOSE(_xll.FDS(Y23,"String_array Name= TRANSPOSE(TRANSPOSE(SA_SUBARRAY(FR_RBICS_REV_MATRIX_CURRENT(""IND""),1,9))[14:14]);float_array pct=TRANSPOSE(TRANSPOSE(SA_SUBARRAY(FR_RBICS_REV_MATRIX_CURRENT(""IND""),1,9))[14:14]);SORT_INDIRECT(Name,pct,2)[0:4]"))} -> 80.876105 | AG23: 19.123895 | AH23: #N/A | AI23: #N/A | AJ23: #N/A | AK23: =IFERROR(AA23, "") -> Customer Relationship Management Software | AL23: =IFERROR(AB23, "") -> Specialized Design and Engineering Software | AM23: =IFERROR(AC23, "") | AN23: =IFERROR(AD23, "") | AO23: =IFERROR(AE23, "") | AP23: =IFERROR(ROUND(VALUE(AF23), 0)/100, "") -> 0.81 | AQ23: =IFERROR(ROUND(VALUE(AG23), 0)/100, "") -> 0.19 | AR23: =IFERROR(ROUND(VALUE(AH23), 0)/100, "") | AS23: =IFERROR(ROUND(VALUE(AI23), 0)/100, "") | AT23: =IFERROR(ROUND(VALUE(AJ23), 0)/100, "")
A24: ='2 — IC Universe Table'!B25 -> BL-US | B24: ='2 — IC Universe Table'!C25 -> BlackLine, Inc. | C24: {=TRANSPOSE(_xll.FDS(A24,"TRANSPOSE(TRANSPOSE(FF_GEOREV_COUNTRY_REV_PCT_MATRIX)[1:1])[0:4]"))} -> United States | D24: Mainland China | E24: Germany | F24: Japan | G24: India | H24: {=TRANSPOSE(_xll.FDS(A24,"TRANSPOSE(TRANSPOSE(FF_GEOREV_COUNTRY_REV_PCT_MATRIX)[2:2])[0:4]"))} -> 70.094867 | I24: 6.846051 | J24: 1.695977 | K24: 1.518422 | L24: 1.454352 | M24: =IFERROR(C24, "") -> United States | N24: =IFERROR(D24, "") -> Mainland China | O24: =IFERROR(E24, "") -> Germany | P24: =IFERROR(F24, "") -> Japan | Q24: =IFERROR(G24, "") -> India | R24: =IFERROR(ROUND(VALUE(H24), 0)/100, "") -> 0.7 | S24: =IFERROR(ROUND(VALUE(I24), 0)/100, "") -> 0.07 | T24: =IFERROR(ROUND(VALUE(J24), 0)/100, "") -> 0.02 | U24: =IFERROR(ROUND(VALUE(K24), 0)/100, "") -> 0.02 | V24: =IFERROR(ROUND(VALUE(L24), 0)/100, "") -> 0.01 | Y24: ='2 — IC Universe Table'!B25 -> BL-US | Z24: ='2 — IC Universe Table'!C25 -> BlackLine, Inc. | AA24: {=TRANSPOSE(_xll.FDS(Y24,"String_array Name= TRANSPOSE(TRANSPOSE(SA_SUBARRAY(FR_RBICS_REV_MATRIX_CURRENT(""IND""),1,9))[13:13]);float_array pct=TRANSPOSE(TRANSPOSE(SA_SUBARRAY(FR_RBICS_REV_MATRIX_CURRENT(""IND""),1,9))[14:14]);SORT_INDIRECT(Name,pct,2)[0:4]"))} -> Enterprise Resource Planning Software | AB24: #N/A | AC24: #N/A | AD24: #N/A | AE24: #N/A | AF24: {=TRANSPOSE(_xll.FDS(Y24,"String_array Name= TRANSPOSE(TRANSPOSE(SA_SUBARRAY(FR_RBICS_REV_MATRIX_CURRENT(""IND""),1,9))[14:14]);float_array pct=TRANSPOSE(TRANSPOSE(SA_SUBARRAY(FR_RBICS_REV_MATRIX_CURRENT(""IND""),1,9))[14:14]);SORT_INDIRECT(Name,pct,2)[0:4]"))} -> 100.000000 | AG24: #N/A | AH24: #N/A | AI24: #N/A | AJ24: #N/A | AK24: =IFERROR(AA24, "") -> Enterprise Resource Planning Software | AL24: =IFERROR(AB24, "") | AM24: =IFERROR(AC24, "") | AN24: =IFERROR(AD24, "") | AO24: =IFERROR(AE24, "") | AP24: =IFERROR(ROUND(VALUE(AF24), 0)/100, "") -> 1 | AQ24: =IFERROR(ROUND(VALUE(AG24), 0)/100, "") | AR24: =IFERROR(ROUND(VALUE(AH24), 0)/100, "") | AS24: =IFERROR(ROUND(VALUE(AI24), 0)/100, "") | AT24: =IFERROR(ROUND(VALUE(AJ24), 0)/100, "")
A25: ='2 — IC Universe Table'!B26 -> PCOR-US | B25: ='2 — IC Universe Table'!C26 -> Procore Technologies Inc | C25: {=TRANSPOSE(_xll.FDS(A25,"TRANSPOSE(TRANSPOSE(FF_GEOREV_COUNTRY_REV_PCT_MATRIX)[1:1])[0:4]"))} -> United States | D25: Mainland China | E25: Germany | F25: Japan | G25: India | H25: {=TRANSPOSE(_xll.FDS(A25,"TRANSPOSE(TRANSPOSE(FF_GEOREV_COUNTRY_REV_PCT_MATRIX)[2:2])[0:4]"))} -> 85.253293 | I25: 3.375899 | J25: 0.836314 | K25: 0.748758 | L25: 0.717165 | M25: =IFERROR(C25, "") -> United States | N25: =IFERROR(D25, "") -> Mainland China | O25: =IFERROR(E25, "") -> Germany | P25: =IFERROR(F25, "") -> Japan | Q25: =IFERROR(G25, "") -> India | R25: =IFERROR(ROUND(VALUE(H25), 0)/100, "") -> 0.85 | S25: =IFERROR(ROUND(VALUE(I25), 0)/100, "") -> 0.03 | T25: =IFERROR(ROUND(VALUE(J25), 0)/100, "") -> 0.01 | U25: =IFERROR(ROUND(VALUE(K25), 0)/100, "") -> 0.01 | V25: =IFERROR(ROUND(VALUE(L25), 0)/100, "") -> 0.01 | Y25: ='2 — IC Universe Table'!B26 -> PCOR-US | Z25: ='2 — IC Universe Table'!C26 -> Procore Technologies Inc | AA25: {=TRANSPOSE(_xll.FDS(Y25,"String_array Name= TRANSPOSE(TRANSPOSE(SA_SUBARRAY(FR_RBICS_REV_MATRIX_CURRENT(""IND""),1,9))[13:13]);float_array pct=TRANSPOSE(TRANSPOSE(SA_SUBARRAY(FR_RBICS_REV_MATRIX_CURRENT(""IND""),1,9))[14:14]);SORT_INDIRECT(Name,pct,2)[0:4]"))} -> Other Real Estate Investment and Services | AB25: #N/A | AC25: #N/A | AD25: #N/A | AE25: #N/A | AF25: {=TRANSPOSE(_xll.FDS(Y25,"String_array Name= TRANSPOSE(TRANSPOSE(SA_SUBARRAY(FR_RBICS_REV_MATRIX_CURRENT(""IND""),1,9))[14:14]);float_array pct=TRANSPOSE(TRANSPOSE(SA_SUBARRAY(FR_RBICS_REV_MATRIX_CURRENT(""IND""),1,9))[14:14]);SORT_INDIRECT(Name,pct,2)[0:4]"))} -> 100.000000 | AG25: #N/A | AH25: #N/A | AI25: #N/A | AJ25: #N/A | AK25: =IFERROR(AA25, "") -> Other Real Estate Investment and Services | AL25: =IFERROR(AB25, "") | AM25: =IFERROR(AC25, "") | AN25: =IFERROR(AD25, "") | AO25: =IFERROR(AE25, "") | AP25: =IFERROR(ROUND(VALUE(AF25), 0)/100, "") -> 1 | AQ25: =IFERROR(ROUND(VALUE(AG25), 0)/100, "") | AR25: =IFERROR(ROUND(VALUE(AH25), 0)/100, "") | AS25: =IFERROR(ROUND(VALUE(AI25), 0)/100, "") | AT25: =IFERROR(ROUND(VALUE(AJ25), 0)/100, "")
A26: ='2 — IC Universe Table'!B27 -> INTA-US | B26: ='2 — IC Universe Table'!C27 -> Intapp, Inc. | C26: {=TRANSPOSE(_xll.FDS(A26,"TRANSPOSE(TRANSPOSE(FF_GEOREV_COUNTRY_REV_PCT_MATRIX)[1:1])[0:4]"))} -> United States | D26: United Kingdom | E26: Mainland China | F26: Germany | G26: India | H26: {=TRANSPOSE(_xll.FDS(A26,"TRANSPOSE(TRANSPOSE(FF_GEOREV_COUNTRY_REV_PCT_MATRIX)[2:2])[0:4]"))} -> 67.251844 | I26: 15.688527 | J26: 4.118527 | K26: 1.016114 | L26: 0.896662 | M26: =IFERROR(C26, "") -> United States | N26: =IFERROR(D26, "") -> United Kingdom | O26: =IFERROR(E26, "") -> Mainland China | P26: =IFERROR(F26, "") -> Germany | Q26: =IFERROR(G26, "") -> India | R26: =IFERROR(ROUND(VALUE(H26), 0)/100, "") -> 0.67 | S26: =IFERROR(ROUND(VALUE(I26), 0)/100, "") -> 0.16 | T26: =IFERROR(ROUND(VALUE(J26), 0)/100, "") -> 0.04 | U26: =IFERROR(ROUND(VALUE(K26), 0)/100, "") -> 0.01 | V26: =IFERROR(ROUND(VALUE(L26), 0)/100, "") -> 0.01 | Y26: ='2 — IC Universe Table'!B27 -> INTA-US | Z26: ='2 — IC Universe Table'!C27 -> Intapp, Inc. | AA26: {=TRANSPOSE(_xll.FDS(Y26,"String_array Name= TRANSPOSE(TRANSPOSE(SA_SUBARRAY(FR_RBICS_REV_MATRIX_CURRENT(""IND""),1,9))[13:13]);float_array pct=TRANSPOSE(TRANSPOSE(SA_SUBARRAY(FR_RBICS_REV_MATRIX_CURRENT(""IND""),1,9))[14:14]);SORT_INDIRECT(Name,pct,2)[0:4]"))} -> Finance Industry Software | AB26: #N/A | AC26: #N/A | AD26: #N/A | AE26: #N/A | AF26: {=TRANSPOSE(_xll.FDS(Y26,"String_array Name= TRANSPOSE(TRANSPOSE(SA_SUBARRAY(FR_RBICS_REV_MATRIX_CURRENT(""IND""),1,9))[14:14]);float_array pct=TRANSPOSE(TRANSPOSE(SA_SUBARRAY(FR_RBICS_REV_MATRIX_CURRENT(""IND""),1,9))[14:14]);SORT_INDIRECT(Name,pct,2)[0:4]"))} -> 100.000000 | AG26: #N/A | AH26: #N/A | AI26: #N/A | AJ26: #N/A | AK26: =IFERROR(AA26, "") -> Finance Industry Software | AL26: =IFERROR(AB26, "") | AM26: =IFERROR(AC26, "") | AN26: =IFERROR(AD26, "") | AO26: =IFERROR(AE26, "") | AP26: =IFERROR(ROUND(VALUE(AF26), 0)/100, "") -> 1 | AQ26: =IFERROR(ROUND(VALUE(AG26), 0)/100, "") | AR26: =IFERROR(ROUND(VALUE(AH26), 0)/100, "") | AS26: =IFERROR(ROUND(VALUE(AI26), 0)/100, "") | AT26: =IFERROR(ROUND(VALUE(AJ26), 0)/100, "")
A27: ='2 — IC Universe Table'!B28 -> ZS-US | B27: ='2 — IC Universe Table'!C28 -> Zscaler, Inc. | C27: {=TRANSPOSE(_xll.FDS(A27,"TRANSPOSE(TRANSPOSE(FF_GEOREV_COUNTRY_REV_PCT_MATRIX)[1:1])[0:4]"))} -> United States | D27: Mainland China | E27: France | F27: India | G27: Japan | H27: {=TRANSPOSE(_xll.FDS(A27,"TRANSPOSE(TRANSPOSE(FF_GEOREV_COUNTRY_REV_PCT_MATRIX)[2:2])[0:4]"))} -> 50.851722 | I27: 2.932063 | J27: 2.588473 | K27: 2.475762 | L27: 2.475416 | M27: =IFERROR(C27, "") -> United States | N27: =IFERROR(D27, "") -> Mainland China | O27: =IFERROR(E27, "") -> France | P27: =IFERROR(F27, "") -> India | Q27: =IFERROR(G27, "") -> Japan | R27: =IFERROR(ROUND(VALUE(H27), 0)/100, "") -> 0.51 | S27: =IFERROR(ROUND(VALUE(I27), 0)/100, "") -> 0.03 | T27: =IFERROR(ROUND(VALUE(J27), 0)/100, "") -> 0.03 | U27: =IFERROR(ROUND(VALUE(K27), 0)/100, "") -> 0.02 | V27: =IFERROR(ROUND(VALUE(L27), 0)/100, "") -> 0.02 | Y27: ='2 — IC Universe Table'!B28 -> ZS-US | Z27: ='2 — IC Universe Table'!C28 -> Zscaler, Inc. | AA27: {=TRANSPOSE(_xll.FDS(Y27,"String_array Name= TRANSPOSE(TRANSPOSE(SA_SUBARRAY(FR_RBICS_REV_MATRIX_CURRENT(""IND""),1,9))[13:13]);float_array pct=TRANSPOSE(TRANSPOSE(SA_SUBARRAY(FR_RBICS_REV_MATRIX_CURRENT(""IND""),1,9))[14:14]);SORT_INDIRECT(Name,pct,2)[0:4]"))} -> Network Infrastructure Software | AB27: #N/A | AC27: #N/A | AD27: #N/A | AE27: #N/A | AF27: {=TRANSPOSE(_xll.FDS(Y27,"String_array Name= TRANSPOSE(TRANSPOSE(SA_SUBARRAY(FR_RBICS_REV_MATRIX_CURRENT(""IND""),1,9))[14:14]);float_array pct=TRANSPOSE(TRANSPOSE(SA_SUBARRAY(FR_RBICS_REV_MATRIX_CURRENT(""IND""),1,9))[14:14]);SORT_INDIRECT(Name,pct,2)[0:4]"))} -> 100.000000 | AG27: #N/A | AH27: #N/A | AI27: #N/A | AJ27: #N/A | AK27: =IFERROR(AA27, "") -> Network Infrastructure Software | AL27: =IFERROR(AB27, "") | AM27: =IFERROR(AC27, "") | AN27: =IFERROR(AD27, "") | AO27: =IFERROR(AE27, "") | AP27: =IFERROR(ROUND(VALUE(AF27), 0)/100, "") -> 1 | AQ27: =IFERROR(ROUND(VALUE(AG27), 0)/100, "") | AR27: =IFERROR(ROUND(VALUE(AH27), 0)/100, "") | AS27: =IFERROR(ROUND(VALUE(AI27), 0)/100, "") | AT27: =IFERROR(ROUND(VALUE(AJ27), 0)/100, "")
A28: ='2 — IC Universe Table'!B29 -> VEEV-US | B28: ='2 — IC Universe Table'!C29 -> Veeva Systems Inc Class A | C28: {=TRANSPOSE(_xll.FDS(A28,"TRANSPOSE(TRANSPOSE(FF_GEOREV_COUNTRY_REV_PCT_MATRIX)[1:1])[0:4]"))} -> United States | D28: Canada | E28: Germany | F28: United Kingdom | G28: France | H28: {=TRANSPOSE(_xll.FDS(A28,"TRANSPOSE(TRANSPOSE(FF_GEOREV_COUNTRY_REV_PCT_MATRIX)[2:2])[0:4]"))} -> 50.935499 | I28: 8.107892 | J28: 4.140751 | K28: 3.152404 | L28: 2.822982 | M28: =IFERROR(C28, "") -> United States | N28: =IFERROR(D28, "") -> Canada | O28: =IFERROR(E28, "") -> Germany | P28: =IFERROR(F28, "") -> United Kingdom | Q28: =IFERROR(G28, "") -> France | R28: =IFERROR(ROUND(VALUE(H28), 0)/100, "") -> 0.51 | S28: =IFERROR(ROUND(VALUE(I28), 0)/100, "") -> 0.08 | T28: =IFERROR(ROUND(VALUE(J28), 0)/100, "") -> 0.04 | U28: =IFERROR(ROUND(VALUE(K28), 0)/100, "") -> 0.03 | V28: =IFERROR(ROUND(VALUE(L28), 0)/100, "") -> 0.03 | Y28: ='2 — IC Universe Table'!B29 -> VEEV-US | Z28: ='2 — IC Universe Table'!C29 -> Veeva Systems Inc Class A | AA28: {=TRANSPOSE(_xll.FDS(Y28,"String_array Name= TRANSPOSE(TRANSPOSE(SA_SUBARRAY(FR_RBICS_REV_MATRIX_CURRENT(""IND""),1,9))[13:13]);float_array pct=TRANSPOSE(TRANSPOSE(SA_SUBARRAY(FR_RBICS_REV_MATRIX_CURRENT(""IND""),1,9))[14:14]);SORT_INDIRECT(Name,pct,2)[0:4]"))} -> Healthcare and Pharma Industry Software | AB28: #N/A | AC28: #N/A | AD28: #N/A | AE28: #N/A | AF28: {=TRANSPOSE(_xll.FDS(Y28,"String_array Name= TRANSPOSE(TRANSPOSE(SA_SUBARRAY(FR_RBICS_REV_MATRIX_CURRENT(""IND""),1,9))[14:14]);float_array pct=TRANSPOSE(TRANSPOSE(SA_SUBARRAY(FR_RBICS_REV_MATRIX_CURRENT(""IND""),1,9))[14:14]);SORT_INDIRECT(Name,pct,2)[0:4]"))} -> 100.000000 | AG28: #N/A | AH28: #N/A | AI28: #N/A | AJ28: #N/A | AK28: =IFERROR(AA28, "") -> Healthcare and Pharma Industry Software | AL28: =IFERROR(AB28, "") | AM28: =IFERROR(AC28, "") | AN28: =IFERROR(AD28, "") | AO28: =IFERROR(AE28, "") | AP28: =IFERROR(ROUND(VALUE(AF28), 0)/100, "") -> 1 | AQ28: =IFERROR(ROUND(VALUE(AG28), 0)/100, "") | AR28: =IFERROR(ROUND(VALUE(AH28), 0)/100, "") | AS28: =IFERROR(ROUND(VALUE(AI28), 0)/100, "") | AT28: =IFERROR(ROUND(VALUE(AJ28), 0)/100, "")
A29: ='2 — IC Universe Table'!B30 -> PEGA-US | B29: ='2 — IC Universe Table'!C30 -> Pegasystems Inc. | C29: {=TRANSPOSE(_xll.FDS(A29,"TRANSPOSE(TRANSPOSE(FF_GEOREV_COUNTRY_REV_PCT_MATRIX)[1:1])[0:4]"))} -> United States | D29: United Kingdom | E29: Mainland China | F29: Germany | G29: India | H29: {=TRANSPOSE(_xll.FDS(A29,"TRANSPOSE(TRANSPOSE(FF_GEOREV_COUNTRY_REV_PCT_MATRIX)[2:2])[0:4]"))} -> 54.776574 | I29: 10.882787 | J29: 2.262994 | K29: 2.231789 | L29: 1.910817 | M29: =IFERROR(C29, "") -> United States | N29: =IFERROR(D29, "") -> United Kingdom | O29: =IFERROR(E29, "") -> Mainland China | P29: =IFERROR(F29, "") -> Germany | Q29: =IFERROR(G29, "") -> India | R29: =IFERROR(ROUND(VALUE(H29), 0)/100, "") -> 0.55 | S29: =IFERROR(ROUND(VALUE(I29), 0)/100, "") -> 0.11 | T29: =IFERROR(ROUND(VALUE(J29), 0)/100, "") -> 0.02 | U29: =IFERROR(ROUND(VALUE(K29), 0)/100, "") -> 0.02 | V29: =IFERROR(ROUND(VALUE(L29), 0)/100, "") -> 0.02 | Y29: ='2 — IC Universe Table'!B30 -> PEGA-US | Z29: ='2 — IC Universe Table'!C30 -> Pegasystems Inc. | AA29: {=TRANSPOSE(_xll.FDS(Y29,"String_array Name= TRANSPOSE(TRANSPOSE(SA_SUBARRAY(FR_RBICS_REV_MATRIX_CURRENT(""IND""),1,9))[13:13]);float_array pct=TRANSPOSE(TRANSPOSE(SA_SUBARRAY(FR_RBICS_REV_MATRIX_CURRENT(""IND""),1,9))[14:14]);SORT_INDIRECT(Name,pct,2)[0:4]"))} -> Customer Relationship Management Software | AB29: #N/A | AC29: #N/A | AD29: #N/A | AE29: #N/A | AF29: {=TRANSPOSE(_xll.FDS(Y29,"String_array Name= TRANSPOSE(TRANSPOSE(SA_SUBARRAY(FR_RBICS_REV_MATRIX_CURRENT(""IND""),1,9))[14:14]);float_array pct=TRANSPOSE(TRANSPOSE(SA_SUBARRAY(FR_RBICS_REV_MATRIX_CURRENT(""IND""),1,9))[14:14]);SORT_INDIRECT(Name,pct,2)[0:4]"))} -> 100.000000 | AG29: #N/A | AH29: #N/A | AI29: #N/A | AJ29: #N/A | AK29: =IFERROR(AA29, "") -> Customer Relationship Management Software | AL29: =IFERROR(AB29, "") | AM29: =IFERROR(AC29, "") | AN29: =IFERROR(AD29, "") | AO29: =IFERROR(AE29, "") | AP29: =IFERROR(ROUND(VALUE(AF29), 0)/100, "") -> 1 | AQ29: =IFERROR(ROUND(VALUE(AG29), 0)/100, "") | AR29: =IFERROR(ROUND(VALUE(AH29), 0)/100, "") | AS29: =IFERROR(ROUND(VALUE(AI29), 0)/100, "") | AT29: =IFERROR(ROUND(VALUE(AJ29), 0)/100, "")
A30: ='2 — IC Universe Table'!B31 -> PCTY-US | B30: ='2 — IC Universe Table'!C31 -> Paylocity Holding Corp. | C30: {=TRANSPOSE(_xll.FDS(A30,"TRANSPOSE(TRANSPOSE(FF_GEOREV_COUNTRY_REV_PCT_MATRIX)[1:1])[0:4]"))} -> United States | D30: #N/A | E30: #N/A | F30: #N/A | G30: #N/A | H30: {=TRANSPOSE(_xll.FDS(A30,"TRANSPOSE(TRANSPOSE(FF_GEOREV_COUNTRY_REV_PCT_MATRIX)[2:2])[0:4]"))} -> 100 | I30: #N/A | J30: #N/A | K30: #N/A | L30: #N/A | M30: =IFERROR(C30, "") -> United States | N30: =IFERROR(D30, "") | O30: =IFERROR(E30, "") | P30: =IFERROR(F30, "") | Q30: =IFERROR(G30, "") | R30: =IFERROR(ROUND(VALUE(H30), 0)/100, "") -> 1 | S30: =IFERROR(ROUND(VALUE(I30), 0)/100, "") | T30: =IFERROR(ROUND(VALUE(J30), 0)/100, "") | U30: =IFERROR(ROUND(VALUE(K30), 0)/100, "") | V30: =IFERROR(ROUND(VALUE(L30), 0)/100, "") | Y30: ='2 — IC Universe Table'!B31 -> PCTY-US | Z30: ='2 — IC Universe Table'!C31 -> Paylocity Holding Corp. | AA30: {=TRANSPOSE(_xll.FDS(Y30,"String_array Name= TRANSPOSE(TRANSPOSE(SA_SUBARRAY(FR_RBICS_REV_MATRIX_CURRENT(""IND""),1,9))[13:13]);float_array pct=TRANSPOSE(TRANSPOSE(SA_SUBARRAY(FR_RBICS_REV_MATRIX_CURRENT(""IND""),1,9))[14:14]);SORT_INDIRECT(Name,pct,2)[0:4]"))} -> Enterprise Resource Planning Software | AB30: Proprietary Trading | AC30: #N/A | AD30: #N/A | AE30: #N/A | AF30: {=TRANSPOSE(_xll.FDS(Y30,"String_array Name= TRANSPOSE(TRANSPOSE(SA_SUBARRAY(FR_RBICS_REV_MATRIX_CURRENT(""IND""),1,9))[14:14]);float_array pct=TRANSPOSE(TRANSPOSE(SA_SUBARRAY(FR_RBICS_REV_MATRIX_CURRENT(""IND""),1,9))[14:14]);SORT_INDIRECT(Name,pct,2)[0:4]"))} -> 92.263141 | AG30: 7.736859 | AH30: #N/A | AI30: #N/A | AJ30: #N/A | AK30: =IFERROR(AA30, "") -> Enterprise Resource Planning Software | AL30: =IFERROR(AB30, "") -> Proprietary Trading | AM30: =IFERROR(AC30, "") | AN30: =IFERROR(AD30, "") | AO30: =IFERROR(AE30, "") | AP30: =IFERROR(ROUND(VALUE(AF30), 0)/100, "") -> 0.92 | AQ30: =IFERROR(ROUND(VALUE(AG30), 0)/100, "") -> 0.08 | AR30: =IFERROR(ROUND(VALUE(AH30), 0)/100, "") | AS30: =IFERROR(ROUND(VALUE(AI30), 0)/100, "") | AT30: =IFERROR(ROUND(VALUE(AJ30), 0)/100, "")
A31: ='2 — IC Universe Table'!B32 -> CDNS-US | B31: ='2 — IC Universe Table'!C32 -> Cadence Design Systems, Inc. | C31: {=TRANSPOSE(_xll.FDS(A31,"TRANSPOSE(TRANSPOSE(FF_GEOREV_COUNTRY_REV_PCT_MATRIX)[1:1])[0:4]"))} -> United States | D31: Mainland China | E31: Japan | F31: India | G31: Republic of Korea (South Korea) | H31: {=TRANSPOSE(_xll.FDS(A31,"TRANSPOSE(TRANSPOSE(FF_GEOREV_COUNTRY_REV_PCT_MATRIX)[2:2])[0:4]"))} -> 43.629793 | I31: 12.526568 | J31: 6.450605 | K31: 6.404808 | L31: 4.524312 | M31: =IFERROR(C31, "") -> United States | N31: =IFERROR(D31, "") -> Mainland China | O31: =IFERROR(E31, "") -> Japan | P31: =IFERROR(F31, "") -> India | Q31: =IFERROR(G31, "") -> Republic of Korea (South Korea) | R31: =IFERROR(ROUND(VALUE(H31), 0)/100, "") -> 0.44 | S31: =IFERROR(ROUND(VALUE(I31), 0)/100, "") -> 0.13 | T31: =IFERROR(ROUND(VALUE(J31), 0)/100, "") -> 0.06 | U31: =IFERROR(ROUND(VALUE(K31), 0)/100, "") -> 0.06 | V31: =IFERROR(ROUND(VALUE(L31), 0)/100, "") -> 0.05 | Y31: ='2 — IC Universe Table'!B32 -> CDNS-US | Z31: ='2 — IC Universe Table'!C32 -> Cadence Design Systems, Inc. | AA31: {=TRANSPOSE(_xll.FDS(Y31,"String_array Name= TRANSPOSE(TRANSPOSE(SA_SUBARRAY(FR_RBICS_REV_MATRIX_CURRENT(""IND""),1,9))[13:13]);float_array pct=TRANSPOSE(TRANSPOSE(SA_SUBARRAY(FR_RBICS_REV_MATRIX_CURRENT(""IND""),1,9))[14:14]);SORT_INDIRECT(Name,pct,2)[0:4]"))} -> Electronic Design Automation Software | AB31: Other Design and Engineering Software | AC31: #N/A | AD31: #N/A | AE31: #N/A | AF31: {=TRANSPOSE(_xll.FDS(Y31,"String_array Name= TRANSPOSE(TRANSPOSE(SA_SUBARRAY(FR_RBICS_REV_MATRIX_CURRENT(""IND""),1,9))[14:14]);float_array pct=TRANSPOSE(TRANSPOSE(SA_SUBARRAY(FR_RBICS_REV_MATRIX_CURRENT(""IND""),1,9))[14:14]);SORT_INDIRECT(Name,pct,2)[0:4]"))} -> 84.000000 | AG31: 16.000000 | AH31: #N/A | AI31: #N/A | AJ31: #N/A | AK31: =IFERROR(AA31, "") -> Electronic Design Automation Software | AL31: =IFERROR(AB31, "") -> Other Design and Engineering Software | AM31: =IFERROR(AC31, "") | AN31: =IFERROR(AD31, "") | AO31: =IFERROR(AE31, "") | AP31: =IFERROR(ROUND(VALUE(AF31), 0)/100, "") -> 0.84 | AQ31: =IFERROR(ROUND(VALUE(AG31), 0)/100, "") -> 0.16 | AR31: =IFERROR(ROUND(VALUE(AH31), 0)/100, "") | AS31: =IFERROR(ROUND(VALUE(AI31), 0)/100, "") | AT31: =IFERROR(ROUND(VALUE(AJ31), 0)/100, "")
A32: ='2 — IC Universe Table'!B33 -> IOT-US | B32: ='2 — IC Universe Table'!C33 -> Samsara, Inc. Class A | C32: {=TRANSPOSE(_xll.FDS(A32,"TRANSPOSE(TRANSPOSE(FF_GEOREV_COUNTRY_REV_PCT_MATRIX)[1:1])[0:4]"))} -> United States | D32: Mainland China | E32: Germany | F32: Japan | G32: India | H32: {=TRANSPOSE(_xll.FDS(A32,"TRANSPOSE(TRANSPOSE(FF_GEOREV_COUNTRY_REV_PCT_MATRIX)[2:2])[0:4]"))} -> 86.654008 | I32: 3.055239 | J32: 0.756876 | K32: 0.677638 | L32: 0.649045 | M32: =IFERROR(C32, "") -> United States | N32: =IFERROR(D32, "") -> Mainland China | O32: =IFERROR(E32, "") -> Germany | P32: =IFERROR(F32, "") -> Japan | Q32: =IFERROR(G32, "") -> India | R32: =IFERROR(ROUND(VALUE(H32), 0)/100, "") -> 0.87 | S32: =IFERROR(ROUND(VALUE(I32), 0)/100, "") -> 0.03 | T32: =IFERROR(ROUND(VALUE(J32), 0)/100, "") -> 0.01 | U32: =IFERROR(ROUND(VALUE(K32), 0)/100, "") -> 0.01 | V32: =IFERROR(ROUND(VALUE(L32), 0)/100, "") -> 0.01 | Y32: ='2 — IC Universe Table'!B33 -> IOT-US | Z32: ='2 — IC Universe Table'!C33 -> Samsara, Inc. Class A | AA32: {=TRANSPOSE(_xll.FDS(Y32,"String_array Name= TRANSPOSE(TRANSPOSE(SA_SUBARRAY(FR_RBICS_REV_MATRIX_CURRENT(""IND""),1,9))[13:13]);float_array pct=TRANSPOSE(TRANSPOSE(SA_SUBARRAY(FR_RBICS_REV_MATRIX_CURRENT(""IND""),1,9))[14:14]);SORT_INDIRECT(Name,pct,2)[0:4]"))} -> Asset Management Software | AB32: Automotive and Marine Electronics Manufacturing | AC32: #N/A | AD32: #N/A | AE32: #N/A | AF32: {=TRANSPOSE(_xll.FDS(Y32,"String_array Name= TRANSPOSE(TRANSPOSE(SA_SUBARRAY(FR_RBICS_REV_MATRIX_CURRENT(""IND""),1,9))[14:14]);float_array pct=TRANSPOSE(TRANSPOSE(SA_SUBARRAY(FR_RBICS_REV_MATRIX_CURRENT(""IND""),1,9))[14:14]);SORT_INDIRECT(Name,pct,2)[0:4]"))} -> 98.125039 | AG32: 1.874961 | AH32: #N/A | AI32: #N/A | AJ32: #N/A | AK32: =IFERROR(AA32, "") -> Asset Management Software | AL32: =IFERROR(AB32, "") -> Automotive and Marine Electronics Manufacturing | AM32: =IFERROR(AC32, "") | AN32: =IFERROR(AD32, "") | AO32: =IFERROR(AE32, "") | AP32: =IFERROR(ROUND(VALUE(AF32), 0)/100, "") -> 0.98 | AQ32: =IFERROR(ROUND(VALUE(AG32), 0)/100, "") -> 0.02 | AR32: =IFERROR(ROUND(VALUE(AH32), 0)/100, "") | AS32: =IFERROR(ROUND(VALUE(AI32), 0)/100, "") | AT32: =IFERROR(ROUND(VALUE(AJ32), 0)/100, "")
A33: ='2 — IC Universe Table'!B34 -> S-US | B33: ='2 — IC Universe Table'!C34 -> SentinelOne, Inc. | C33: {=TRANSPOSE(_xll.FDS(A33,"TRANSPOSE(TRANSPOSE(FF_GEOREV_COUNTRY_REV_PCT_MATRIX)[1:1])[0:4]"))} -> United States | D33: Mainland China | E33: Germany | F33: Japan | G33: India | H33: {=TRANSPOSE(_xll.FDS(A33,"TRANSPOSE(TRANSPOSE(FF_GEOREV_COUNTRY_REV_PCT_MATRIX)[2:2])[0:4]"))} -> 63.293084 | I33: 8.403154 | J33: 2.081718 | K33: 1.86378 | L33: 1.785138 | M33: =IFERROR(C33, "") -> United States | N33: =IFERROR(D33, "") -> Mainland China | O33: =IFERROR(E33, "") -> Germany | P33: =IFERROR(F33, "") -> Japan | Q33: =IFERROR(G33, "") -> India | R33: =IFERROR(ROUND(VALUE(H33), 0)/100, "") -> 0.63 | S33: =IFERROR(ROUND(VALUE(I33), 0)/100, "") -> 0.08 | T33: =IFERROR(ROUND(VALUE(J33), 0)/100, "") -> 0.02 | U33: =IFERROR(ROUND(VALUE(K33), 0)/100, "") -> 0.02 | V33: =IFERROR(ROUND(VALUE(L33), 0)/100, "") -> 0.02 | Y33: ='2 — IC Universe Table'!B34 -> S-US | Z33: ='2 — IC Universe Table'!C34 -> SentinelOne, Inc. | AA33: {=TRANSPOSE(_xll.FDS(Y33,"String_array Name= TRANSPOSE(TRANSPOSE(SA_SUBARRAY(FR_RBICS_REV_MATRIX_CURRENT(""IND""),1,9))[13:13]);float_array pct=TRANSPOSE(TRANSPOSE(SA_SUBARRAY(FR_RBICS_REV_MATRIX_CURRENT(""IND""),1,9))[14:14]);SORT_INDIRECT(Name,pct,2)[0:4]"))} -> Network Infrastructure Software | AB33: #N/A | AC33: #N/A | AD33: #N/A | AE33: #N/A | AF33: {=TRANSPOSE(_xll.FDS(Y33,"String_array Name= TRANSPOSE(TRANSPOSE(SA_SUBARRAY(FR_RBICS_REV_MATRIX_CURRENT(""IND""),1,9))[14:14]);float_array pct=TRANSPOSE(TRANSPOSE(SA_SUBARRAY(FR_RBICS_REV_MATRIX_CURRENT(""IND""),1,9))[14:14]);SORT_INDIRECT(Name,pct,2)[0:4]"))} -> 100.000000 | AG33: #N/A | AH33: #N/A | AI33: #N/A | AJ33: #N/A | AK33: =IFERROR(AA33, "") -> Network Infrastructure Software | AL33: =IFERROR(AB33, "") | AM33: =IFERROR(AC33, "") | AN33: =IFERROR(AD33, "") | AO33: =IFERROR(AE33, "") | AP33: =IFERROR(ROUND(VALUE(AF33), 0)/100, "") -> 1 | AQ33: =IFERROR(ROUND(VALUE(AG33), 0)/100, "") | AR33: =IFERROR(ROUND(VALUE(AH33), 0)/100, "") | AS33: =IFERROR(ROUND(VALUE(AI33), 0)/100, "") | AT33: =IFERROR(ROUND(VALUE(AJ33), 0)/100, "")
A34: ='2 — IC Universe Table'!B35 -> PTC-US | B34: ='2 — IC Universe Table'!C35 -> PTC Inc. | C34: {=TRANSPOSE(_xll.FDS(A34,"TRANSPOSE(TRANSPOSE(FF_GEOREV_COUNTRY_REV_PCT_MATRIX)[1:1])[0:4]"))} -> United States | D34: Germany | E34: United Kingdom | F34: France | G34: Mainland China | H34: {=TRANSPOSE(_xll.FDS(A34,"TRANSPOSE(TRANSPOSE(FF_GEOREV_COUNTRY_REV_PCT_MATRIX)[2:2])[0:4]"))} -> 47.002329 | I34: 13.463657 | J34: 3.776241 | K34: 3.158646 | L34: 2.814659 | M34: =IFERROR(C34, "") -> United States | N34: =IFERROR(D34, "") -> Germany | O34: =IFERROR(E34, "") -> United Kingdom | P34: =IFERROR(F34, "") -> France | Q34: =IFERROR(G34, "") -> Mainland China | R34: =IFERROR(ROUND(VALUE(H34), 0)/100, "") -> 0.47 | S34: =IFERROR(ROUND(VALUE(I34), 0)/100, "") -> 0.13 | T34: =IFERROR(ROUND(VALUE(J34), 0)/100, "") -> 0.04 | U34: =IFERROR(ROUND(VALUE(K34), 0)/100, "") -> 0.03 | V34: =IFERROR(ROUND(VALUE(L34), 0)/100, "") -> 0.03 | Y34: ='2 — IC Universe Table'!B35 -> PTC-US | Z34: ='2 — IC Universe Table'!C35 -> PTC Inc. | AA34: {=TRANSPOSE(_xll.FDS(Y34,"String_array Name= TRANSPOSE(TRANSPOSE(SA_SUBARRAY(FR_RBICS_REV_MATRIX_CURRENT(""IND""),1,9))[13:13]);float_array pct=TRANSPOSE(TRANSPOSE(SA_SUBARRAY(FR_RBICS_REV_MATRIX_CURRENT(""IND""),1,9))[14:14]);SORT_INDIRECT(Name,pct,2)[0:4]"))} -> Manufacturing Industry Software | AB34: Computer Aided Design Software | AC34: #N/A | AD34: #N/A | AE34: #N/A | AF34: {=TRANSPOSE(_xll.FDS(Y34,"String_array Name= TRANSPOSE(TRANSPOSE(SA_SUBARRAY(FR_RBICS_REV_MATRIX_CURRENT(""IND""),1,9))[14:14]);float_array pct=TRANSPOSE(TRANSPOSE(SA_SUBARRAY(FR_RBICS_REV_MATRIX_CURRENT(""IND""),1,9))[14:14]);SORT_INDIRECT(Name,pct,2)[0:4]"))} -> 63.569417 | AG34: 36.430583 | AH34: #N/A | AI34: #N/A | AJ34: #N/A | AK34: =IFERROR(AA34, "") -> Manufacturing Industry Software | AL34: =IFERROR(AB34, "") -> Computer Aided Design Software | AM34: =IFERROR(AC34, "") | AN34: =IFERROR(AD34, "") | AO34: =IFERROR(AE34, "") | AP34: =IFERROR(ROUND(VALUE(AF34), 0)/100, "") -> 0.64 | AQ34: =IFERROR(ROUND(VALUE(AG34), 0)/100, "") -> 0.36 | AR34: =IFERROR(ROUND(VALUE(AH34), 0)/100, "") | AS34: =IFERROR(ROUND(VALUE(AI34), 0)/100, "") | AT34: =IFERROR(ROUND(VALUE(AJ34), 0)/100, "")
A35: ='2 — IC Universe Table'!B36 -> DSY-FR | B35: ='2 — IC Universe Table'!C36 -> Dassault Systemes SE | C35: {=TRANSPOSE(_xll.FDS(A35,"TRANSPOSE(TRANSPOSE(FF_GEOREV_COUNTRY_REV_PCT_MATRIX)[1:1])[0:4]"))} -> United States | D35: France | E35: Germany | F35: Japan | G35: Mainland China | H35: {=TRANSPOSE(_xll.FDS(A35,"TRANSPOSE(TRANSPOSE(FF_GEOREV_COUNTRY_REV_PCT_MATRIX)[2:2])[0:4]"))} -> 37.19261 | I35: 11.008111 | J35: 8.194927 | K35: 7.871443 | L35: 7.821962 | M35: =IFERROR(C35, "") -> United States | N35: =IFERROR(D35, "") -> France | O35: =IFERROR(E35, "") -> Germany | P35: =IFERROR(F35, "") -> Japan | Q35: =IFERROR(G35, "") -> Mainland China | R35: =IFERROR(ROUND(VALUE(H35), 0)/100, "") -> 0.37 | S35: =IFERROR(ROUND(VALUE(I35), 0)/100, "") -> 0.11 | T35: =IFERROR(ROUND(VALUE(J35), 0)/100, "") -> 0.08 | U35: =IFERROR(ROUND(VALUE(K35), 0)/100, "") -> 0.08 | V35: =IFERROR(ROUND(VALUE(L35), 0)/100, "") -> 0.08 | Y35: ='2 — IC Universe Table'!B36 -> DSY-FR | Z35: ='2 — IC Universe Table'!C36 -> Dassault Systemes SE | AA35: {=TRANSPOSE(_xll.FDS(Y35,"String_array Name= TRANSPOSE(TRANSPOSE(SA_SUBARRAY(FR_RBICS_REV_MATRIX_CURRENT(""IND""),1,9))[13:13]);float_array pct=TRANSPOSE(TRANSPOSE(SA_SUBARRAY(FR_RBICS_REV_MATRIX_CURRENT(""IND""),1,9))[14:14]);SORT_INDIRECT(Name,pct,2)[0:4]"))} -> Computer Aided Design Software | AB35: #N/A | AC35: #N/A | AD35: #N/A | AE35: #N/A | AF35: {=TRANSPOSE(_xll.FDS(Y35,"String_array Name= TRANSPOSE(TRANSPOSE(SA_SUBARRAY(FR_RBICS_REV_MATRIX_CURRENT(""IND""),1,9))[14:14]);float_array pct=TRANSPOSE(TRANSPOSE(SA_SUBARRAY(FR_RBICS_REV_MATRIX_CURRENT(""IND""),1,9))[14:14]);SORT_INDIRECT(Name,pct,2)[0:4]"))} -> 100.000000 | AG35: #N/A | AH35: #N/A | AI35: #N/A | AJ35: #N/A | AK35: =IFERROR(AA35, "") -> Computer Aided Design Software | AL35: =IFERROR(AB35, "") | AM35: =IFERROR(AC35, "") | AN35: =IFERROR(AD35, "") | AO35: =IFERROR(AE35, "") | AP35: =IFERROR(ROUND(VALUE(AF35), 0)/100, "") -> 1 | AQ35: =IFERROR(ROUND(VALUE(AG35), 0)/100, "") | AR35: =IFERROR(ROUND(VALUE(AH35), 0)/100, "") | AS35: =IFERROR(ROUND(VALUE(AI35), 0)/100, "") | AT35: =IFERROR(ROUND(VALUE(AJ35), 0)/100, "")
A36: ='2 — IC Universe Table'!B37 -> SAP-DE | B36: ='2 — IC Universe Table'!C37 -> SAP SE | C36: {=TRANSPOSE(_xll.FDS(A36,"TRANSPOSE(TRANSPOSE(FF_GEOREV_COUNTRY_REV_PCT_MATRIX)[1:1])[0:4]"))} -> United States | D36: Germany | E36: United Kingdom | F36: France | G36: Italy | H36: {=TRANSPOSE(_xll.FDS(A36,"TRANSPOSE(TRANSPOSE(FF_GEOREV_COUNTRY_REV_PCT_MATRIX)[2:2])[0:4]"))} -> 32.350187 | I36: 15.683521 | J36: 9.468815 | K36: 8.479336 | L36: 6.306737 | M36: =IFERROR(C36, "") -> United States | N36: =IFERROR(D36, "") -> Germany | O36: =IFERROR(E36, "") -> United Kingdom | P36: =IFERROR(F36, "") -> France | Q36: =IFERROR(G36, "") -> Italy | R36: =IFERROR(ROUND(VALUE(H36), 0)/100, "") -> 0.32 | S36: =IFERROR(ROUND(VALUE(I36), 0)/100, "") -> 0.16 | T36: =IFERROR(ROUND(VALUE(J36), 0)/100, "") -> 0.09 | U36: =IFERROR(ROUND(VALUE(K36), 0)/100, "") -> 0.08 | V36: =IFERROR(ROUND(VALUE(L36), 0)/100, "") -> 0.06 | Y36: ='2 — IC Universe Table'!B37 -> SAP-DE | Z36: ='2 — IC Universe Table'!C37 -> SAP SE | AA36: {=TRANSPOSE(_xll.FDS(Y36,"String_array Name= TRANSPOSE(TRANSPOSE(SA_SUBARRAY(FR_RBICS_REV_MATRIX_CURRENT(""IND""),1,9))[13:13]);float_array pct=TRANSPOSE(TRANSPOSE(SA_SUBARRAY(FR_RBICS_REV_MATRIX_CURRENT(""IND""),1,9))[14:14]);SORT_INDIRECT(Name,pct,2)[0:4]"))} -> General Enterprise Management Software | AB36: #N/A | AC36: #N/A | AD36: #N/A | AE36: #N/A | AF36: {=TRANSPOSE(_xll.FDS(Y36,"String_array Name= TRANSPOSE(TRANSPOSE(SA_SUBARRAY(FR_RBICS_REV_MATRIX_CURRENT(""IND""),1,9))[14:14]);float_array pct=TRANSPOSE(TRANSPOSE(SA_SUBARRAY(FR_RBICS_REV_MATRIX_CURRENT(""IND""),1,9))[14:14]);SORT_INDIRECT(Name,pct,2)[0:4]"))} -> 100.000000 | AG36: #N/A | AH36: #N/A | AI36: #N/A | AJ36: #N/A | AK36: =IFERROR(AA36, "") -> General Enterprise Management Software | AL36: =IFERROR(AB36, "") | AM36: =IFERROR(AC36, "") | AN36: =IFERROR(AD36, "") | AO36: =IFERROR(AE36, "") | AP36: =IFERROR(ROUND(VALUE(AF36), 0)/100, "") -> 1 | AQ36: =IFERROR(ROUND(VALUE(AG36), 0)/100, "") | AR36: =IFERROR(ROUND(VALUE(AH36), 0)/100, "") | AS36: =IFERROR(ROUND(VALUE(AI36), 0)/100, "") | AT36: =IFERROR(ROUND(VALUE(AJ36), 0)/100, "")
A37: ='2 — IC Universe Table'!B38 -> VRNS-US | B37: ='2 — IC Universe Table'!C38 -> Varonis Systems, Inc. | C37: {=TRANSPOSE(_xll.FDS(A37,"TRANSPOSE(TRANSPOSE(FF_GEOREV_COUNTRY_REV_PCT_MATRIX)[1:1])[0:4]"))} -> United States | D37: Mainland China | E37: France | F37: Italy | G37: Russian Federation | H37: {=TRANSPOSE(_xll.FDS(A37,"TRANSPOSE(TRANSPOSE(FF_GEOREV_COUNTRY_REV_PCT_MATRIX)[2:2])[0:4]"))} -> 70.640801 | I37: 3.267138 | J37: 1.869836 | K37: 1.410753 | L37: 1.209021 | M37: =IFERROR(C37, "") -> United States | N37: =IFERROR(D37, "") -> Mainland China | O37: =IFERROR(E37, "") -> France | P37: =IFERROR(F37, "") -> Italy | Q37: =IFERROR(G37, "") -> Russian Federation | R37: =IFERROR(ROUND(VALUE(H37), 0)/100, "") -> 0.71 | S37: =IFERROR(ROUND(VALUE(I37), 0)/100, "") -> 0.03 | T37: =IFERROR(ROUND(VALUE(J37), 0)/100, "") -> 0.02 | U37: =IFERROR(ROUND(VALUE(K37), 0)/100, "") -> 0.01 | V37: =IFERROR(ROUND(VALUE(L37), 0)/100, "") -> 0.01 | Y37: ='2 — IC Universe Table'!B38 -> VRNS-US | Z37: ='2 — IC Universe Table'!C38 -> Varonis Systems, Inc. | AA37: {=TRANSPOSE(_xll.FDS(Y37,"String_array Name= TRANSPOSE(TRANSPOSE(SA_SUBARRAY(FR_RBICS_REV_MATRIX_CURRENT(""IND""),1,9))[13:13]);float_array pct=TRANSPOSE(TRANSPOSE(SA_SUBARRAY(FR_RBICS_REV_MATRIX_CURRENT(""IND""),1,9))[14:14]);SORT_INDIRECT(Name,pct,2)[0:4]"))} -> Network Infrastructure Software | AB37: #N/A | AC37: #N/A | AD37: #N/A | AE37: #N/A | AF37: {=TRANSPOSE(_xll.FDS(Y37,"String_array Name= TRANSPOSE(TRANSPOSE(SA_SUBARRAY(FR_RBICS_REV_MATRIX_CURRENT(""IND""),1,9))[14:14]);float_array pct=TRANSPOSE(TRANSPOSE(SA_SUBARRAY(FR_RBICS_REV_MATRIX_CURRENT(""IND""),1,9))[14:14]);SORT_INDIRECT(Name,pct,2)[0:4]"))} -> 100.000000 | AG37: #N/A | AH37: #N/A | AI37: #N/A | AJ37: #N/A | AK37: =IFERROR(AA37, "") -> Network Infrastructure Software | AL37: =IFERROR(AB37, "") | AM37: =IFERROR(AC37, "") | AN37: =IFERROR(AD37, "") | AO37: =IFERROR(AE37, "") | AP37: =IFERROR(ROUND(VALUE(AF37), 0)/100, "") -> 1 | AQ37: =IFERROR(ROUND(VALUE(AG37), 0)/100, "") | AR37: =IFERROR(ROUND(VALUE(AH37), 0)/100, "") | AS37: =IFERROR(ROUND(VALUE(AI37), 0)/100, "") | AT37: =IFERROR(ROUND(VALUE(AJ37), 0)/100, "")
A38: ='2 — IC Universe Table'!B39 -> DDOG-US | B38: ='2 — IC Universe Table'!C39 -> Datadog, Inc. | C38: {=TRANSPOSE(_xll.FDS(A38,"TRANSPOSE(TRANSPOSE(FF_GEOREV_COUNTRY_REV_PCT_MATRIX)[1:1])[0:4]"))} -> United States | D38: Canada | E38: Mainland China | F38: France | G38: Germany | H38: {=TRANSPOSE(_xll.FDS(A38,"TRANSPOSE(TRANSPOSE(FF_GEOREV_COUNTRY_REV_PCT_MATRIX)[2:2])[0:4]"))} -> 67.703327 | I38: 3.290861 | J38: 3.065485 | K38: 1.511766 | L38: 1.41302 | M38: =IFERROR(C38, "") -> United States | N38: =IFERROR(D38, "") -> Canada | O38: =IFERROR(E38, "") -> Mainland China | P38: =IFERROR(F38, "") -> France | Q38: =IFERROR(G38, "") -> Germany | R38: =IFERROR(ROUND(VALUE(H38), 0)/100, "") -> 0.68 | S38: =IFERROR(ROUND(VALUE(I38), 0)/100, "") -> 0.03 | T38: =IFERROR(ROUND(VALUE(J38), 0)/100, "") -> 0.03 | U38: =IFERROR(ROUND(VALUE(K38), 0)/100, "") -> 0.02 | V38: =IFERROR(ROUND(VALUE(L38), 0)/100, "") -> 0.01 | Y38: ='2 — IC Universe Table'!B39 -> DDOG-US | Z38: ='2 — IC Universe Table'!C39 -> Datadog, Inc. | AA38: {=TRANSPOSE(_xll.FDS(Y38,"String_array Name= TRANSPOSE(TRANSPOSE(SA_SUBARRAY(FR_RBICS_REV_MATRIX_CURRENT(""IND""),1,9))[13:13]);float_array pct=TRANSPOSE(TRANSPOSE(SA_SUBARRAY(FR_RBICS_REV_MATRIX_CURRENT(""IND""),1,9))[14:14]);SORT_INDIRECT(Name,pct,2)[0:4]"))} -> Network Infrastructure Software | AB38: #N/A | AC38: #N/A | AD38: #N/A | AE38: #N/A | AF38: {=TRANSPOSE(_xll.FDS(Y38,"String_array Name= TRANSPOSE(TRANSPOSE(SA_SUBARRAY(FR_RBICS_REV_MATRIX_CURRENT(""IND""),1,9))[14:14]);float_array pct=TRANSPOSE(TRANSPOSE(SA_SUBARRAY(FR_RBICS_REV_MATRIX_CURRENT(""IND""),1,9))[14:14]);SORT_INDIRECT(Name,pct,2)[0:4]"))} -> 100.000000 | AG38: #N/A | AH38: #N/A | AI38: #N/A | AJ38: #N/A | AK38: =IFERROR(AA38, "") -> Network Infrastructure Software | AL38: =IFERROR(AB38, "") | AM38: =IFERROR(AC38, "") | AN38: =IFERROR(AD38, "") | AO38: =IFERROR(AE38, "") | AP38: =IFERROR(ROUND(VALUE(AF38), 0)/100, "") -> 1 | AQ38: =IFERROR(ROUND(VALUE(AG38), 0)/100, "") | AR38: =IFERROR(ROUND(VALUE(AH38), 0)/100, "") | AS38: =IFERROR(ROUND(VALUE(AI38), 0)/100, "") | AT38: =IFERROR(ROUND(VALUE(AJ38), 0)/100, "")
A39: ='2 — IC Universe Table'!B40 -> TOST-US | B39: ='2 — IC Universe Table'!C40 -> Toast, Inc. | C39: {=TRANSPOSE(_xll.FDS(A39,"TRANSPOSE(TRANSPOSE(FF_GEOREV_COUNTRY_REV_PCT_MATRIX)[1:1])[0:4]"))} -> United States | D39: #N/A | E39: #N/A | F39: #N/A | G39: #N/A | H39: {=TRANSPOSE(_xll.FDS(A39,"TRANSPOSE(TRANSPOSE(FF_GEOREV_COUNTRY_REV_PCT_MATRIX)[2:2])[0:4]"))} -> 100 | I39: #N/A | J39: #N/A | K39: #N/A | L39: #N/A | M39: =IFERROR(C39, "") -> United States | N39: =IFERROR(D39, "") | O39: =IFERROR(E39, "") | P39: =IFERROR(F39, "") | Q39: =IFERROR(G39, "") | R39: =IFERROR(ROUND(VALUE(H39), 0)/100, "") -> 1 | S39: =IFERROR(ROUND(VALUE(I39), 0)/100, "") | T39: =IFERROR(ROUND(VALUE(J39), 0)/100, "") | U39: =IFERROR(ROUND(VALUE(K39), 0)/100, "") | V39: =IFERROR(ROUND(VALUE(L39), 0)/100, "") | Y39: ='2 — IC Universe Table'!B40 -> TOST-US | Z39: ='2 — IC Universe Table'!C40 -> Toast, Inc. | AA39: {=TRANSPOSE(_xll.FDS(Y39,"String_array Name= TRANSPOSE(TRANSPOSE(SA_SUBARRAY(FR_RBICS_REV_MATRIX_CURRENT(""IND""),1,9))[13:13]);float_array pct=TRANSPOSE(TRANSPOSE(SA_SUBARRAY(FR_RBICS_REV_MATRIX_CURRENT(""IND""),1,9))[14:14]);SORT_INDIRECT(Name,pct,2)[0:4]"))} -> Retail Industry Software | AB39: Point-of-Sale (POS) Terminal Manufacturing | AC39: #N/A | AD39: #N/A | AE39: #N/A | AF39: {=TRANSPOSE(_xll.FDS(Y39,"String_array Name= TRANSPOSE(TRANSPOSE(SA_SUBARRAY(FR_RBICS_REV_MATRIX_CURRENT(""IND""),1,9))[14:14]);float_array pct=TRANSPOSE(TRANSPOSE(SA_SUBARRAY(FR_RBICS_REV_MATRIX_CURRENT(""IND""),1,9))[14:14]);SORT_INDIRECT(Name,pct,2)[0:4]"))} -> 95.947581 | AG39: 4.052419 | AH39: #N/A | AI39: #N/A | AJ39: #N/A | AK39: =IFERROR(AA39, "") -> Retail Industry Software | AL39: =IFERROR(AB39, "") -> Point-of-Sale (POS) Terminal Manufacturing | AM39: =IFERROR(AC39, "") | AN39: =IFERROR(AD39, "") | AO39: =IFERROR(AE39, "") | AP39: =IFERROR(ROUND(VALUE(AF39), 0)/100, "") -> 0.96 | AQ39: =IFERROR(ROUND(VALUE(AG39), 0)/100, "") -> 0.04 | AR39: =IFERROR(ROUND(VALUE(AH39), 0)/100, "") | AS39: =IFERROR(ROUND(VALUE(AI39), 0)/100, "") | AT39: =IFERROR(ROUND(VALUE(AJ39), 0)/100, "")
A40: ='2 — IC Universe Table'!B41 -> NICE-US | B40: ='2 — IC Universe Table'!C41 -> NICE Ltd. | C40: {=TRANSPOSE(_xll.FDS(A40,"TRANSPOSE(TRANSPOSE(FF_GEOREV_COUNTRY_REV_PCT_MATRIX)[1:1])[0:4]"))} -> United States | D40: Germany | E40: United Kingdom | F40: France | G40: Mainland China | H40: {=TRANSPOSE(_xll.FDS(A40,"TRANSPOSE(TRANSPOSE(FF_GEOREV_COUNTRY_REV_PCT_MATRIX)[2:2])[0:4]"))} -> 84.873606 | I40: 1.337797 | J40: 1.018481 | K40: 0.912051 | L40: 0.879189 | M40: =IFERROR(C40, "") -> United States | N40: =IFERROR(D40, "") -> Germany | O40: =IFERROR(E40, "") -> United Kingdom | P40: =IFERROR(F40, "") -> France | Q40: =IFERROR(G40, "") -> Mainland China | R40: =IFERROR(ROUND(VALUE(H40), 0)/100, "") -> 0.85 | S40: =IFERROR(ROUND(VALUE(I40), 0)/100, "") -> 0.01 | T40: =IFERROR(ROUND(VALUE(J40), 0)/100, "") -> 0.01 | U40: =IFERROR(ROUND(VALUE(K40), 0)/100, "") -> 0.01 | V40: =IFERROR(ROUND(VALUE(L40), 0)/100, "") -> 0.01 | Y40: ='2 — IC Universe Table'!B41 -> NICE-US | Z40: ='2 — IC Universe Table'!C41 -> NICE Ltd. | AA40: {=TRANSPOSE(_xll.FDS(Y40,"String_array Name= TRANSPOSE(TRANSPOSE(SA_SUBARRAY(FR_RBICS_REV_MATRIX_CURRENT(""IND""),1,9))[13:13]);float_array pct=TRANSPOSE(TRANSPOSE(SA_SUBARRAY(FR_RBICS_REV_MATRIX_CURRENT(""IND""),1,9))[14:14]);SORT_INDIRECT(Name,pct,2)[0:4]"))} -> Customer Relationship Management Software | AB40: Enterprise Resource Planning Software | AC40: #N/A | AD40: #N/A | AE40: #N/A | AF40: {=TRANSPOSE(_xll.FDS(Y40,"String_array Name= TRANSPOSE(TRANSPOSE(SA_SUBARRAY(FR_RBICS_REV_MATRIX_CURRENT(""IND""),1,9))[14:14]);float_array pct=TRANSPOSE(TRANSPOSE(SA_SUBARRAY(FR_RBICS_REV_MATRIX_CURRENT(""IND""),1,9))[14:14]);SORT_INDIRECT(Name,pct,2)[0:4]"))} -> 83.420625 | AG40: 16.579375 | AH40: #N/A | AI40: #N/A | AJ40: #N/A | AK40: =IFERROR(AA40, "") -> Customer Relationship Management Software | AL40: =IFERROR(AB40, "") -> Enterprise Resource Planning Software | AM40: =IFERROR(AC40, "") | AN40: =IFERROR(AD40, "") | AO40: =IFERROR(AE40, "") | AP40: =IFERROR(ROUND(VALUE(AF40), 0)/100, "") -> 0.83 | AQ40: =IFERROR(ROUND(VALUE(AG40), 0)/100, "") -> 0.17 | AR40: =IFERROR(ROUND(VALUE(AH40), 0)/100, "") | AS40: =IFERROR(ROUND(VALUE(AI40), 0)/100, "") | AT40: =IFERROR(ROUND(VALUE(AJ40), 0)/100, "")
A41: ='2 — IC Universe Table'!B42 -> 4684-JP | B41: ='2 — IC Universe Table'!C42 -> OBIC Co., Ltd. | C41: {=TRANSPOSE(_xll.FDS(A41,"TRANSPOSE(TRANSPOSE(FF_GEOREV_COUNTRY_REV_PCT_MATRIX)[1:1])[0:4]"))} -> Japan | D41: #N/A | E41: #N/A | F41: #N/A | G41: #N/A | H41: {=TRANSPOSE(_xll.FDS(A41,"TRANSPOSE(TRANSPOSE(FF_GEOREV_COUNTRY_REV_PCT_MATRIX)[2:2])[0:4]"))} -> 100 | I41: #N/A | J41: #N/A | K41: #N/A | L41: #N/A | M41: =IFERROR(C41, "") -> Japan | N41: =IFERROR(D41, "") | O41: =IFERROR(E41, "") | P41: =IFERROR(F41, "") | Q41: =IFERROR(G41, "") | R41: =IFERROR(ROUND(VALUE(H41), 0)/100, "") -> 1 | S41: =IFERROR(ROUND(VALUE(I41), 0)/100, "") | T41: =IFERROR(ROUND(VALUE(J41), 0)/100, "") | U41: =IFERROR(ROUND(VALUE(K41), 0)/100, "") | V41: =IFERROR(ROUND(VALUE(L41), 0)/100, "") | Y41: ='2 — IC Universe Table'!B42 -> 4684-JP | Z41: ='2 — IC Universe Table'!C42 -> OBIC Co., Ltd. | AA41: {=TRANSPOSE(_xll.FDS(Y41,"String_array Name= TRANSPOSE(TRANSPOSE(SA_SUBARRAY(FR_RBICS_REV_MATRIX_CURRENT(""IND""),1,9))[13:13]);float_array pct=TRANSPOSE(TRANSPOSE(SA_SUBARRAY(FR_RBICS_REV_MATRIX_CURRENT(""IND""),1,9))[14:14]);SORT_INDIRECT(Name,pct,2)[0:4]"))} -> Enterprise Resource Planning Software | AB41: Diversified Hardware Distributors | AC41: #N/A | AD41: #N/A | AE41: #N/A | AF41: {=TRANSPOSE(_xll.FDS(Y41,"String_array Name= TRANSPOSE(TRANSPOSE(SA_SUBARRAY(FR_RBICS_REV_MATRIX_CURRENT(""IND""),1,9))[14:14]);float_array pct=TRANSPOSE(TRANSPOSE(SA_SUBARRAY(FR_RBICS_REV_MATRIX_CURRENT(""IND""),1,9))[14:14]);SORT_INDIRECT(Name,pct,2)[0:4]"))} -> 93.498792 | AG41: 6.501208 | AH41: #N/A | AI41: #N/A | AJ41: #N/A | AK41: =IFERROR(AA41, "") -> Enterprise Resource Planning Software | AL41: =IFERROR(AB41, "") -> Diversified Hardware Distributors | AM41: =IFERROR(AC41, "") | AN41: =IFERROR(AD41, "") | AO41: =IFERROR(AE41, "") | AP41: =IFERROR(ROUND(VALUE(AF41), 0)/100, "") -> 0.93 | AQ41: =IFERROR(ROUND(VALUE(AG41), 0)/100, "") -> 0.07 | AR41: =IFERROR(ROUND(VALUE(AH41), 0)/100, "") | AS41: =IFERROR(ROUND(VALUE(AI41), 0)/100, "") | AT41: =IFERROR(ROUND(VALUE(AJ41), 0)/100, "")
A42: ='2 — IC Universe Table'!B43 -> BSY-US | B42: ='2 — IC Universe Table'!C43 -> Bentley Systems, Incorporated Class B | C42: {=TRANSPOSE(_xll.FDS(A42,"TRANSPOSE(TRANSPOSE(FF_GEOREV_COUNTRY_REV_PCT_MATRIX)[1:1])[0:4]"))} -> United States | D42: Mainland China | E42: Japan | F42: Brazil | G42: India | H42: {=TRANSPOSE(_xll.FDS(A42,"TRANSPOSE(TRANSPOSE(FF_GEOREV_COUNTRY_REV_PCT_MATRIX)[2:2])[0:4]"))} -> 41.51098 | I42: 3.244601 | J42: 2.892407 | K42: 2.81783 | L42: 2.770362 | M42: =IFERROR(C42, "") -> United States | N42: =IFERROR(D42, "") -> Mainland China | O42: =IFERROR(E42, "") -> Japan | P42: =IFERROR(F42, "") -> Brazil | Q42: =IFERROR(G42, "") -> India | R42: =IFERROR(ROUND(VALUE(H42), 0)/100, "") -> 0.42 | S42: =IFERROR(ROUND(VALUE(I42), 0)/100, "") -> 0.03 | T42: =IFERROR(ROUND(VALUE(J42), 0)/100, "") -> 0.03 | U42: =IFERROR(ROUND(VALUE(K42), 0)/100, "") -> 0.03 | V42: =IFERROR(ROUND(VALUE(L42), 0)/100, "") -> 0.03 | Y42: ='2 — IC Universe Table'!B43 -> BSY-US | Z42: ='2 — IC Universe Table'!C43 -> Bentley Systems, Incorporated Class B | AA42: {=TRANSPOSE(_xll.FDS(Y42,"String_array Name= TRANSPOSE(TRANSPOSE(SA_SUBARRAY(FR_RBICS_REV_MATRIX_CURRENT(""IND""),1,9))[13:13]);float_array pct=TRANSPOSE(TRANSPOSE(SA_SUBARRAY(FR_RBICS_REV_MATRIX_CURRENT(""IND""),1,9))[14:14]);SORT_INDIRECT(Name,pct,2)[0:4]"))} -> Computer Aided Design Software | AB42: #N/A | AC42: #N/A | AD42: #N/A | AE42: #N/A | AF42: {=TRANSPOSE(_xll.FDS(Y42,"String_array Name= TRANSPOSE(TRANSPOSE(SA_SUBARRAY(FR_RBICS_REV_MATRIX_CURRENT(""IND""),1,9))[14:14]);float_array pct=TRANSPOSE(TRANSPOSE(SA_SUBARRAY(FR_RBICS_REV_MATRIX_CURRENT(""IND""),1,9))[14:14]);SORT_INDIRECT(Name,pct,2)[0:4]"))} -> 100.000000 | AG42: #N/A | AH42: #N/A | AI42: #N/A | AJ42: #N/A | AK42: =IFERROR(AA42, "") -> Computer Aided Design Software | AL42: =IFERROR(AB42, "") | AM42: =IFERROR(AC42, "") | AN42: =IFERROR(AD42, "") | AO42: =IFERROR(AE42, "") | AP42: =IFERROR(ROUND(VALUE(AF42), 0)/100, "") -> 1 | AQ42: =IFERROR(ROUND(VALUE(AG42), 0)/100, "") | AR42: =IFERROR(ROUND(VALUE(AH42), 0)/100, "") | AS42: =IFERROR(ROUND(VALUE(AI42), 0)/100, "") | AT42: =IFERROR(ROUND(VALUE(AJ42), 0)/100, "")
A43: ='2 — IC Universe Table'!B44 -> OS-US | B43: ='2 — IC Universe Table'!C44 -> Onestream, Inc. Class A | C43: {=TRANSPOSE(_xll.FDS(A43,"TRANSPOSE(TRANSPOSE(FF_GEOREV_COUNTRY_REV_PCT_MATRIX)[1:1])[0:4]"))} -> United States | D43: Mainland China | E43: Germany | F43: Japan | G43: India | H43: {=TRANSPOSE(_xll.FDS(A43,"TRANSPOSE(TRANSPOSE(FF_GEOREV_COUNTRY_REV_PCT_MATRIX)[2:2])[0:4]"))} -> 68.398286 | I43: 7.234442 | J43: 1.792193 | K43: 1.604565 | L43: 1.536861 | M43: =IFERROR(C43, "") -> United States | N43: =IFERROR(D43, "") -> Mainland China | O43: =IFERROR(E43, "") -> Germany | P43: =IFERROR(F43, "") -> Japan | Q43: =IFERROR(G43, "") -> India | R43: =IFERROR(ROUND(VALUE(H43), 0)/100, "") -> 0.68 | S43: =IFERROR(ROUND(VALUE(I43), 0)/100, "") -> 0.07 | T43: =IFERROR(ROUND(VALUE(J43), 0)/100, "") -> 0.02 | U43: =IFERROR(ROUND(VALUE(K43), 0)/100, "") -> 0.02 | V43: =IFERROR(ROUND(VALUE(L43), 0)/100, "") -> 0.02 | Y43: ='2 — IC Universe Table'!B44 -> OS-US | Z43: ='2 — IC Universe Table'!C44 -> Onestream, Inc. Class A | AA43: {=TRANSPOSE(_xll.FDS(Y43,"String_array Name= TRANSPOSE(TRANSPOSE(SA_SUBARRAY(FR_RBICS_REV_MATRIX_CURRENT(""IND""),1,9))[13:13]);float_array pct=TRANSPOSE(TRANSPOSE(SA_SUBARRAY(FR_RBICS_REV_MATRIX_CURRENT(""IND""),1,9))[14:14]);SORT_INDIRECT(Name,pct,2)[0:4]"))} -> Enterprise Resource Planning Software | AB43: #N/A | AC43: #N/A | AD43: #N/A | AE43: #N/A | AF43: {=TRANSPOSE(_xll.FDS(Y43,"String_array Name= TRANSPOSE(TRANSPOSE(SA_SUBARRAY(FR_RBICS_REV_MATRIX_CURRENT(""IND""),1,9))[14:14]);float_array pct=TRANSPOSE(TRANSPOSE(SA_SUBARRAY(FR_RBICS_REV_MATRIX_CURRENT(""IND""),1,9))[14:14]);SORT_INDIRECT(Name,pct,2)[0:4]"))} -> 100.000000 | AG43: #N/A | AH43: #N/A | AI43: #N/A | AJ43: #N/A | AK43: =IFERROR(AA43, "") -> Enterprise Resource Planning Software | AL43: =IFERROR(AB43, "") | AM43: =IFERROR(AC43, "") | AN43: =IFERROR(AD43, "") | AO43: =IFERROR(AE43, "") | AP43: =IFERROR(ROUND(VALUE(AF43), 0)/100, "") -> 1 | AQ43: =IFERROR(ROUND(VALUE(AG43), 0)/100, "") | AR43: =IFERROR(ROUND(VALUE(AH43), 0)/100, "") | AS43: =IFERROR(ROUND(VALUE(AI43), 0)/100, "") | AT43: =IFERROR(ROUND(VALUE(AJ43), 0)/100, "")
A44: ='2 — IC Universe Table'!B45 -> 301269-CN | B44: ='2 — IC Universe Table'!C45 -> Empyrean Technology Co., Ltd. Class A | C44: {=TRANSPOSE(_xll.FDS(A44,"TRANSPOSE(TRANSPOSE(FF_GEOREV_COUNTRY_REV_PCT_MATRIX)[1:1])[0:4]"))} -> Mainland China | D44: United States | E44: Germany | F44: Japan | G44: India | H44: {=TRANSPOSE(_xll.FDS(A44,"TRANSPOSE(TRANSPOSE(FF_GEOREV_COUNTRY_REV_PCT_MATRIX)[2:2])[0:4]"))} -> 95.275828 | I44: 1.49081 | J44: 0.237811 | K44: 0.212914 | L44: 0.20393 | M44: =IFERROR(C44, "") -> Mainland China | N44: =IFERROR(D44, "") -> United States | O44: =IFERROR(E44, "") -> Germany | P44: =IFERROR(F44, "") -> Japan | Q44: =IFERROR(G44, "") -> India | R44: =IFERROR(ROUND(VALUE(H44), 0)/100, "") -> 0.95 | S44: =IFERROR(ROUND(VALUE(I44), 0)/100, "") -> 0.01 | T44: =IFERROR(ROUND(VALUE(J44), 0)/100, "") -> 0 | U44: =IFERROR(ROUND(VALUE(K44), 0)/100, "") -> 0 | V44: =IFERROR(ROUND(VALUE(L44), 0)/100, "") -> 0 | Y44: ='2 — IC Universe Table'!B45 -> 301269-CN | Z44: ='2 — IC Universe Table'!C45 -> Empyrean Technology Co., Ltd. Class A | AA44: {=TRANSPOSE(_xll.FDS(Y44,"String_array Name= TRANSPOSE(TRANSPOSE(SA_SUBARRAY(FR_RBICS_REV_MATRIX_CURRENT(""IND""),1,9))[13:13]);float_array pct=TRANSPOSE(TRANSPOSE(SA_SUBARRAY(FR_RBICS_REV_MATRIX_CURRENT(""IND""),1,9))[14:14]);SORT_INDIRECT(Name,pct,2)[0:4]"))} -> Electronic Design Automation Software | AB44: Other Design and Engineering Software | AC44: #N/A | AD44: #N/A | AE44: #N/A | AF44: {=TRANSPOSE(_xll.FDS(Y44,"String_array Name= TRANSPOSE(TRANSPOSE(SA_SUBARRAY(FR_RBICS_REV_MATRIX_CURRENT(""IND""),1,9))[14:14]);float_array pct=TRANSPOSE(TRANSPOSE(SA_SUBARRAY(FR_RBICS_REV_MATRIX_CURRENT(""IND""),1,9))[14:14]);SORT_INDIRECT(Name,pct,2)[0:4]"))} -> 90.586389 | AG44: 9.413611 | AH44: #N/A | AI44: #N/A | AJ44: #N/A | AK44: =IFERROR(AA44, "") -> Electronic Design Automation Software | AL44: =IFERROR(AB44, "") -> Other Design and Engineering Software | AM44: =IFERROR(AC44, "") | AN44: =IFERROR(AD44, "") | AO44: =IFERROR(AE44, "") | AP44: =IFERROR(ROUND(VALUE(AF44), 0)/100, "") -> 0.91 | AQ44: =IFERROR(ROUND(VALUE(AG44), 0)/100, "") -> 0.09 | AR44: =IFERROR(ROUND(VALUE(AH44), 0)/100, "") | AS44: =IFERROR(ROUND(VALUE(AI44), 0)/100, "") | AT44: =IFERROR(ROUND(VALUE(AJ44), 0)/100, "")
A45: ='2 — IC Universe Table'!B46 -> PANW-US | B45: ='2 — IC Universe Table'!C46 -> Palo Alto Networks, Inc. | C45: {=TRANSPOSE(_xll.FDS(A45,"TRANSPOSE(TRANSPOSE(FF_GEOREV_COUNTRY_REV_PCT_MATRIX)[1:1])[0:4]"))} -> United States | D45: Mainland China | E45: India | F45: Japan | G45: France | H45: {=TRANSPOSE(_xll.FDS(A45,"TRANSPOSE(TRANSPOSE(FF_GEOREV_COUNTRY_REV_PCT_MATRIX)[2:2])[0:4]"))} -> 62.746841 | I45: 2.204016 | J45: 1.861018 | K45: 1.860757 | L45: 1.814664 | M45: =IFERROR(C45, "") -> United States | N45: =IFERROR(D45, "") -> Mainland China | O45: =IFERROR(E45, "") -> India | P45: =IFERROR(F45, "") -> Japan | Q45: =IFERROR(G45, "") -> France | R45: =IFERROR(ROUND(VALUE(H45), 0)/100, "") -> 0.63 | S45: =IFERROR(ROUND(VALUE(I45), 0)/100, "") -> 0.02 | T45: =IFERROR(ROUND(VALUE(J45), 0)/100, "") -> 0.02 | U45: =IFERROR(ROUND(VALUE(K45), 0)/100, "") -> 0.02 | V45: =IFERROR(ROUND(VALUE(L45), 0)/100, "") -> 0.02 | Y45: ='2 — IC Universe Table'!B46 -> PANW-US | Z45: ='2 — IC Universe Table'!C46 -> Palo Alto Networks, Inc. | AA45: {=TRANSPOSE(_xll.FDS(Y45,"String_array Name= TRANSPOSE(TRANSPOSE(SA_SUBARRAY(FR_RBICS_REV_MATRIX_CURRENT(""IND""),1,9))[13:13]);float_array pct=TRANSPOSE(TRANSPOSE(SA_SUBARRAY(FR_RBICS_REV_MATRIX_CURRENT(""IND""),1,9))[14:14]);SORT_INDIRECT(Name,pct,2)[0:4]"))} -> Network Infrastructure Software | AB45: Customer Premises Network Security Equipment | AC45: #N/A | AD45: #N/A | AE45: #N/A | AF45: {=TRANSPOSE(_xll.FDS(Y45,"String_array Name= TRANSPOSE(TRANSPOSE(SA_SUBARRAY(FR_RBICS_REV_MATRIX_CURRENT(""IND""),1,9))[14:14]);float_array pct=TRANSPOSE(TRANSPOSE(SA_SUBARRAY(FR_RBICS_REV_MATRIX_CURRENT(""IND""),1,9))[14:14]);SORT_INDIRECT(Name,pct,2)[0:4]"))} -> 53.943502 | AG45: 46.056498 | AH45: #N/A | AI45: #N/A | AJ45: #N/A | AK45: =IFERROR(AA45, "") -> Network Infrastructure Software | AL45: =IFERROR(AB45, "") -> Customer Premises Network Security Equipment | AM45: =IFERROR(AC45, "") | AN45: =IFERROR(AD45, "") | AO45: =IFERROR(AE45, "") | AP45: =IFERROR(ROUND(VALUE(AF45), 0)/100, "") -> 0.54 | AQ45: =IFERROR(ROUND(VALUE(AG45), 0)/100, "") -> 0.46 | AR45: =IFERROR(ROUND(VALUE(AH45), 0)/100, "") | AS45: =IFERROR(ROUND(VALUE(AI45), 0)/100, "") | AT45: =IFERROR(ROUND(VALUE(AJ45), 0)/100, "")
A46: ='2 — IC Universe Table'!B47 -> SPSC-US | B46: ='2 — IC Universe Table'!C47 -> SPS Commerce, Inc. | C46: {=TRANSPOSE(_xll.FDS(A46,"TRANSPOSE(TRANSPOSE(FF_GEOREV_COUNTRY_REV_PCT_MATRIX)[1:1])[0:4]"))} -> United States | D46: Mainland China | E46: Germany | F46: India | G46: Japan | H46: {=TRANSPOSE(_xll.FDS(A46,"TRANSPOSE(TRANSPOSE(FF_GEOREV_COUNTRY_REV_PCT_MATRIX)[2:2])[0:4]"))} -> 84 | I46: 3.685112 | J46: 0.909183 | K46: 0.802301 | L46: 0.802189 | M46: =IFERROR(C46, "") -> United States | N46: =IFERROR(D46, "") -> Mainland China | O46: =IFERROR(E46, "") -> Germany | P46: =IFERROR(F46, "") -> India | Q46: =IFERROR(G46, "") -> Japan | R46: =IFERROR(ROUND(VALUE(H46), 0)/100, "") -> 0.84 | S46: =IFERROR(ROUND(VALUE(I46), 0)/100, "") -> 0.04 | T46: =IFERROR(ROUND(VALUE(J46), 0)/100, "") -> 0.01 | U46: =IFERROR(ROUND(VALUE(K46), 0)/100, "") -> 0.01 | V46: =IFERROR(ROUND(VALUE(L46), 0)/100, "") -> 0.01 | Y46: ='2 — IC Universe Table'!B47 -> SPSC-US | Z46: ='2 — IC Universe Table'!C47 -> SPS Commerce, Inc. | AA46: {=TRANSPOSE(_xll.FDS(Y46,"String_array Name= TRANSPOSE(TRANSPOSE(SA_SUBARRAY(FR_RBICS_REV_MATRIX_CURRENT(""IND""),1,9))[13:13]);float_array pct=TRANSPOSE(TRANSPOSE(SA_SUBARRAY(FR_RBICS_REV_MATRIX_CURRENT(""IND""),1,9))[14:14]);SORT_INDIRECT(Name,pct,2)[0:4]"))} -> Enterprise Resource Planning Software | AB46: Retail Industry Software | AC46: #N/A | AD46: #N/A | AE46: #N/A | AF46: {=TRANSPOSE(_xll.FDS(Y46,"String_array Name= TRANSPOSE(TRANSPOSE(SA_SUBARRAY(FR_RBICS_REV_MATRIX_CURRENT(""IND""),1,9))[14:14]);float_array pct=TRANSPOSE(TRANSPOSE(SA_SUBARRAY(FR_RBICS_REV_MATRIX_CURRENT(""IND""),1,9))[14:14]);SORT_INDIRECT(Name,pct,2)[0:4]"))} -> 91.263710 | AG46: 8.736290 | AH46: #N/A | AI46: #N/A | AJ46: #N/A | AK46: =IFERROR(AA46, "") -> Enterprise Resource Planning Software | AL46: =IFERROR(AB46, "") -> Retail Industry Software | AM46: =IFERROR(AC46, "") | AN46: =IFERROR(AD46, "") | AO46: =IFERROR(AE46, "") | AP46: =IFERROR(ROUND(VALUE(AF46), 0)/100, "") -> 0.91 | AQ46: =IFERROR(ROUND(VALUE(AG46), 0)/100, "") -> 0.09 | AR46: =IFERROR(ROUND(VALUE(AH46), 0)/100, "") | AS46: =IFERROR(ROUND(VALUE(AI46), 0)/100, "") | AT46: =IFERROR(ROUND(VALUE(AJ46), 0)/100, "")
A47: ='2 — IC Universe Table'!B48 -> PAYX-US | B47: ='2 — IC Universe Table'!C48 -> Paychex, Inc. | C47: {=TRANSPOSE(_xll.FDS(A47,"TRANSPOSE(TRANSPOSE(FF_GEOREV_COUNTRY_REV_PCT_MATRIX)[1:1])[0:4]"))} -> United States | D47: Germany | E47: United Kingdom | F47: France | G47: Italy | H47: {=TRANSPOSE(_xll.FDS(A47,"TRANSPOSE(TRANSPOSE(FF_GEOREV_COUNTRY_REV_PCT_MATRIX)[2:2])[0:4]"))} -> 99 | I47: 0.138324 | J47: 0.108219 | K47: 0.093889 | L47: 0.08707 | M47: =IFERROR(C47, "") -> United States | N47: =IFERROR(D47, "") -> Germany | O47: =IFERROR(E47, "") -> United Kingdom | P47: =IFERROR(F47, "") -> France | Q47: =IFERROR(G47, "") -> Italy | R47: =IFERROR(ROUND(VALUE(H47), 0)/100, "") -> 0.99 | S47: =IFERROR(ROUND(VALUE(I47), 0)/100, "") -> 0 | T47: =IFERROR(ROUND(VALUE(J47), 0)/100, "") -> 0 | U47: =IFERROR(ROUND(VALUE(K47), 0)/100, "") -> 0 | V47: =IFERROR(ROUND(VALUE(L47), 0)/100, "") -> 0 | Y47: ='2 — IC Universe Table'!B48 -> PAYX-US | Z47: ='2 — IC Universe Table'!C48 -> Paychex, Inc. | AA47: {=TRANSPOSE(_xll.FDS(Y47,"String_array Name= TRANSPOSE(TRANSPOSE(SA_SUBARRAY(FR_RBICS_REV_MATRIX_CURRENT(""IND""),1,9))[13:13]);float_array pct=TRANSPOSE(TRANSPOSE(SA_SUBARRAY(FR_RBICS_REV_MATRIX_CURRENT(""IND""),1,9))[14:14]);SORT_INDIRECT(Name,pct,2)[0:4]"))} -> Enterprise Resource Planning Software | AB47: Corporate or Other Unallocated Revenue | AC47: #N/A | AD47: #N/A | AE47: #N/A | AF47: {=TRANSPOSE(_xll.FDS(Y47,"String_array Name= TRANSPOSE(TRANSPOSE(SA_SUBARRAY(FR_RBICS_REV_MATRIX_CURRENT(""IND""),1,9))[14:14]);float_array pct=TRANSPOSE(TRANSPOSE(SA_SUBARRAY(FR_RBICS_REV_MATRIX_CURRENT(""IND""),1,9))[14:14]);SORT_INDIRECT(Name,pct,2)[0:4]"))} -> 97.097834 | AG47: 2.902166 | AH47: #N/A | AI47: #N/A | AJ47: #N/A | AK47: =IFERROR(AA47, "") -> Enterprise Resource Planning Software | AL47: =IFERROR(AB47, "") -> Corporate or Other Unallocated Revenue | AM47: =IFERROR(AC47, "") | AN47: =IFERROR(AD47, "") | AO47: =IFERROR(AE47, "") | AP47: =IFERROR(ROUND(VALUE(AF47), 0)/100, "") -> 0.97 | AQ47: =IFERROR(ROUND(VALUE(AG47), 0)/100, "") -> 0.03 | AR47: =IFERROR(ROUND(VALUE(AH47), 0)/100, "") | AS47: =IFERROR(ROUND(VALUE(AI47), 0)/100, "") | AT47: =IFERROR(ROUND(VALUE(AJ47), 0)/100, "")
A48: ='2 — IC Universe Table'!B49 -> APPF-US | B48: ='2 — IC Universe Table'!C49 -> AppFolio Inc Class A | C48: {=TRANSPOSE(_xll.FDS(A48,"TRANSPOSE(TRANSPOSE(FF_GEOREV_COUNTRY_REV_PCT_MATRIX)[1:1])[0:4]"))} -> United States | D48: #N/A | E48: #N/A | F48: #N/A | G48: #N/A | H48: {=TRANSPOSE(_xll.FDS(A48,"TRANSPOSE(TRANSPOSE(FF_GEOREV_COUNTRY_REV_PCT_MATRIX)[2:2])[0:4]"))} -> 100 | I48: #N/A | J48: #N/A | K48: #N/A | L48: #N/A | M48: =IFERROR(C48, "") -> United States | N48: =IFERROR(D48, "") | O48: =IFERROR(E48, "") | P48: =IFERROR(F48, "") | Q48: =IFERROR(G48, "") | R48: =IFERROR(ROUND(VALUE(H48), 0)/100, "") -> 1 | S48: =IFERROR(ROUND(VALUE(I48), 0)/100, "") | T48: =IFERROR(ROUND(VALUE(J48), 0)/100, "") | U48: =IFERROR(ROUND(VALUE(K48), 0)/100, "") | V48: =IFERROR(ROUND(VALUE(L48), 0)/100, "") | Y48: ='2 — IC Universe Table'!B49 -> APPF-US | Z48: ='2 — IC Universe Table'!C49 -> AppFolio Inc Class A | AA48: {=TRANSPOSE(_xll.FDS(Y48,"String_array Name= TRANSPOSE(TRANSPOSE(SA_SUBARRAY(FR_RBICS_REV_MATRIX_CURRENT(""IND""),1,9))[13:13]);float_array pct=TRANSPOSE(TRANSPOSE(SA_SUBARRAY(FR_RBICS_REV_MATRIX_CURRENT(""IND""),1,9))[14:14]);SORT_INDIRECT(Name,pct,2)[0:4]"))} -> Other Real Estate Investment and Services | AB48: General or Multi-Industry Revenue | AC48: #N/A | AD48: #N/A | AE48: #N/A | AF48: {=TRANSPOSE(_xll.FDS(Y48,"String_array Name= TRANSPOSE(TRANSPOSE(SA_SUBARRAY(FR_RBICS_REV_MATRIX_CURRENT(""IND""),1,9))[14:14]);float_array pct=TRANSPOSE(TRANSPOSE(SA_SUBARRAY(FR_RBICS_REV_MATRIX_CURRENT(""IND""),1,9))[14:14]);SORT_INDIRECT(Name,pct,2)[0:4]"))} -> 98.126253 | AG48: 1.873747 | AH48: #N/A | AI48: #N/A | AJ48: #N/A | AK48: =IFERROR(AA48, "") -> Other Real Estate Investment and Services | AL48: =IFERROR(AB48, "") -> General or Multi-Industry Revenue | AM48: =IFERROR(AC48, "") | AN48: =IFERROR(AD48, "") | AO48: =IFERROR(AE48, "") | AP48: =IFERROR(ROUND(VALUE(AF48), 0)/100, "") -> 0.98 | AQ48: =IFERROR(ROUND(VALUE(AG48), 0)/100, "") -> 0.02 | AR48: =IFERROR(ROUND(VALUE(AH48), 0)/100, "") | AS48: =IFERROR(ROUND(VALUE(AI48), 0)/100, "") | AT48: =IFERROR(ROUND(VALUE(AJ48), 0)/100, "")
A49: ='2 — IC Universe Table'!B50 -> QTWO-US | B49: ='2 — IC Universe Table'!C50 -> Q2 Holdings, Inc. | C49: {=TRANSPOSE(_xll.FDS(A49,"TRANSPOSE(TRANSPOSE(FF_GEOREV_COUNTRY_REV_PCT_MATRIX)[1:1])[0:4]"))} -> United States | D49: #N/A | E49: #N/A | F49: #N/A | G49: #N/A | H49: {=TRANSPOSE(_xll.FDS(A49,"TRANSPOSE(TRANSPOSE(FF_GEOREV_COUNTRY_REV_PCT_MATRIX)[2:2])[0:4]"))} -> 100 | I49: #N/A | J49: #N/A | K49: #N/A | L49: #N/A | M49: =IFERROR(C49, "") -> United States | N49: =IFERROR(D49, "") | O49: =IFERROR(E49, "") | P49: =IFERROR(F49, "") | Q49: =IFERROR(G49, "") | R49: =IFERROR(ROUND(VALUE(H49), 0)/100, "") -> 1 | S49: =IFERROR(ROUND(VALUE(I49), 0)/100, "") | T49: =IFERROR(ROUND(VALUE(J49), 0)/100, "") | U49: =IFERROR(ROUND(VALUE(K49), 0)/100, "") | V49: =IFERROR(ROUND(VALUE(L49), 0)/100, "") | Y49: ='2 — IC Universe Table'!B50 -> QTWO-US | Z49: ='2 — IC Universe Table'!C50 -> Q2 Holdings, Inc. | AA49: {=TRANSPOSE(_xll.FDS(Y49,"String_array Name= TRANSPOSE(TRANSPOSE(SA_SUBARRAY(FR_RBICS_REV_MATRIX_CURRENT(""IND""),1,9))[13:13]);float_array pct=TRANSPOSE(TRANSPOSE(SA_SUBARRAY(FR_RBICS_REV_MATRIX_CURRENT(""IND""),1,9))[14:14]);SORT_INDIRECT(Name,pct,2)[0:4]"))} -> Finance Industry Software | AB49: #N/A | AC49: #N/A | AD49: #N/A | AE49: #N/A | AF49: {=TRANSPOSE(_xll.FDS(Y49,"String_array Name= TRANSPOSE(TRANSPOSE(SA_SUBARRAY(FR_RBICS_REV_MATRIX_CURRENT(""IND""),1,9))[14:14]);float_array pct=TRANSPOSE(TRANSPOSE(SA_SUBARRAY(FR_RBICS_REV_MATRIX_CURRENT(""IND""),1,9))[14:14]);SORT_INDIRECT(Name,pct,2)[0:4]"))} -> 100.000000 | AG49: #N/A | AH49: #N/A | AI49: #N/A | AJ49: #N/A | AK49: =IFERROR(AA49, "") -> Finance Industry Software | AL49: =IFERROR(AB49, "") | AM49: =IFERROR(AC49, "") | AN49: =IFERROR(AD49, "") | AO49: =IFERROR(AE49, "") | AP49: =IFERROR(ROUND(VALUE(AF49), 0)/100, "") -> 1 | AQ49: =IFERROR(ROUND(VALUE(AG49), 0)/100, "") | AR49: =IFERROR(ROUND(VALUE(AH49), 0)/100, "") | AS49: =IFERROR(ROUND(VALUE(AI49), 0)/100, "") | AT49: =IFERROR(ROUND(VALUE(AJ49), 0)/100, "")
A50: ='2 — IC Universe Table'!B51 -> VERX-US | B50: ='2 — IC Universe Table'!C51 -> Vertex, Inc. | C50: {=TRANSPOSE(_xll.FDS(A50,"TRANSPOSE(TRANSPOSE(FF_GEOREV_COUNTRY_REV_PCT_MATRIX)[1:1])[0:4]"))} -> United States | D50: Germany | E50: United Kingdom | F50: France | G50: Italy | H50: {=TRANSPOSE(_xll.FDS(A50,"TRANSPOSE(TRANSPOSE(FF_GEOREV_COUNTRY_REV_PCT_MATRIX)[2:2])[0:4]"))} -> 90 | I50: 1.570341 | J50: 1.270615 | K50: 1.062809 | L50: 0.801868 | M50: =IFERROR(C50, "") -> United States | N50: =IFERROR(D50, "") -> Germany | O50: =IFERROR(E50, "") -> United Kingdom | P50: =IFERROR(F50, "") -> France | Q50: =IFERROR(G50, "") -> Italy | R50: =IFERROR(ROUND(VALUE(H50), 0)/100, "") -> 0.9 | S50: =IFERROR(ROUND(VALUE(I50), 0)/100, "") -> 0.02 | T50: =IFERROR(ROUND(VALUE(J50), 0)/100, "") -> 0.01 | U50: =IFERROR(ROUND(VALUE(K50), 0)/100, "") -> 0.01 | V50: =IFERROR(ROUND(VALUE(L50), 0)/100, "") -> 0.01 | Y50: ='2 — IC Universe Table'!B51 -> VERX-US | Z50: ='2 — IC Universe Table'!C51 -> Vertex, Inc. | AA50: {=TRANSPOSE(_xll.FDS(Y50,"String_array Name= TRANSPOSE(TRANSPOSE(SA_SUBARRAY(FR_RBICS_REV_MATRIX_CURRENT(""IND""),1,9))[13:13]);float_array pct=TRANSPOSE(TRANSPOSE(SA_SUBARRAY(FR_RBICS_REV_MATRIX_CURRENT(""IND""),1,9))[14:14]);SORT_INDIRECT(Name,pct,2)[0:4]"))} -> Enterprise Resource Planning Software | AB50: #N/A | AC50: #N/A | AD50: #N/A | AE50: #N/A | AF50: {=TRANSPOSE(_xll.FDS(Y50,"String_array Name= TRANSPOSE(TRANSPOSE(SA_SUBARRAY(FR_RBICS_REV_MATRIX_CURRENT(""IND""),1,9))[14:14]);float_array pct=TRANSPOSE(TRANSPOSE(SA_SUBARRAY(FR_RBICS_REV_MATRIX_CURRENT(""IND""),1,9))[14:14]);SORT_INDIRECT(Name,pct,2)[0:4]"))} -> 100.000000 | AG50: #N/A | AH50: #N/A | AI50: #N/A | AJ50: #N/A | AK50: =IFERROR(AA50, "") -> Enterprise Resource Planning Software | AL50: =IFERROR(AB50, "") | AM50: =IFERROR(AC50, "") | AN50: =IFERROR(AD50, "") | AO50: =IFERROR(AE50, "") | AP50: =IFERROR(ROUND(VALUE(AF50), 0)/100, "") -> 1 | AQ50: =IFERROR(ROUND(VALUE(AG50), 0)/100, "") | AR50: =IFERROR(ROUND(VALUE(AH50), 0)/100, "") | AS50: =IFERROR(ROUND(VALUE(AI50), 0)/100, "") | AT50: =IFERROR(ROUND(VALUE(AJ50), 0)/100, "")
A51: ='2 — IC Universe Table'!B52 -> MSFT-US | B51: ='2 — IC Universe Table'!C52 -> Microsoft Corporation | C51: {=TRANSPOSE(_xll.FDS(A51,"TRANSPOSE(TRANSPOSE(FF_GEOREV_COUNTRY_REV_PCT_MATRIX)[1:1])[0:4]"))} -> United States | D51: Mainland China | E51: Germany | F51: India | G51: Japan | H51: {=TRANSPOSE(_xll.FDS(A51,"TRANSPOSE(TRANSPOSE(FF_GEOREV_COUNTRY_REV_PCT_MATRIX)[2:2])[0:4]"))} -> 51.307663 | I51: 11.214794 | J51: 2.766889 | K51: 2.441621 | L51: 2.441279 | M51: =IFERROR(C51, "") -> United States | N51: =IFERROR(D51, "") -> Mainland China | O51: =IFERROR(E51, "") -> Germany | P51: =IFERROR(F51, "") -> India | Q51: =IFERROR(G51, "") -> Japan | R51: =IFERROR(ROUND(VALUE(H51), 0)/100, "") -> 0.51 | S51: =IFERROR(ROUND(VALUE(I51), 0)/100, "") -> 0.11 | T51: =IFERROR(ROUND(VALUE(J51), 0)/100, "") -> 0.03 | U51: =IFERROR(ROUND(VALUE(K51), 0)/100, "") -> 0.02 | V51: =IFERROR(ROUND(VALUE(L51), 0)/100, "") -> 0.02 | Y51: ='2 — IC Universe Table'!B52 -> MSFT-US | Z51: ='2 — IC Universe Table'!C52 -> Microsoft Corporation | AA51: {=TRANSPOSE(_xll.FDS(Y51,"String_array Name= TRANSPOSE(TRANSPOSE(SA_SUBARRAY(FR_RBICS_REV_MATRIX_CURRENT(""IND""),1,9))[13:13]);float_array pct=TRANSPOSE(TRANSPOSE(SA_SUBARRAY(FR_RBICS_REV_MATRIX_CURRENT(""IND""),1,9))[14:14]);SORT_INDIRECT(Name,pct,2)[0:4]"))} -> Diversified IT Infrastructure Software | AB51: Productivity Software | AC51: Electronic Gaming/Entertainment Electronics Makers | AD51: Consumer Content Providers | AE51: Multi-Type Home and Office Software | AF51: {=TRANSPOSE(_xll.FDS(Y51,"String_array Name= TRANSPOSE(TRANSPOSE(SA_SUBARRAY(FR_RBICS_REV_MATRIX_CURRENT(""IND""),1,9))[14:14]);float_array pct=TRANSPOSE(TRANSPOSE(SA_SUBARRAY(FR_RBICS_REV_MATRIX_CURRENT(""IND""),1,9))[14:14]);SORT_INDIRECT(Name,pct,2)[0:4]"))} -> 34.940226 | AG51: 33.781644 | AH51: 8.325524 | AI51: 6.322500 | AJ51: 6.145731 | AK51: =IFERROR(AA51, "") -> Diversified IT Infrastructure Software | AL51: =IFERROR(AB51, "") -> Productivity Software | AM51: =IFERROR(AC51, "") -> Electronic Gaming/Entertainment Electronics Makers | AN51: =IFERROR(AD51, "") -> Consumer Content Providers | AO51: =IFERROR(AE51, "") -> Multi-Type Home and Office Software | AP51: =IFERROR(ROUND(VALUE(AF51), 0)/100, "") -> 0.35 | AQ51: =IFERROR(ROUND(VALUE(AG51), 0)/100, "") -> 0.34 | AR51: =IFERROR(ROUND(VALUE(AH51), 0)/100, "") -> 0.08 | AS51: =IFERROR(ROUND(VALUE(AI51), 0)/100, "") -> 0.06 | AT51: =IFERROR(ROUND(VALUE(AJ51), 0)/100, "") -> 0.06
